Workbook

Sheet README
A1: Helios Instruments Pvt. Ltd. — Business Travel Expense Register, 2025
A3: PURPOSE | B3: Fictional but internally consistent travel & expense dataset for demos, audit-workflow testing, dashboards and pivot-table practice.
A4: Coverage | B4: 1 January 2025 to 31 December 2025 — 138 business trips, 2,954 individual expense line items.
A5: Grain | B5: One row per individual expense claim (a single receipt).
A6: Employees | B6: 24 travellers across Sales, Field Engineering, Product, Marketing, Customer Success, Finance, Operations and Executive.
A7: Currency | B7: Claims are recorded in the local currency of the destination and converted to US dollars at a fixed period-average FX rate.
A9: TABS
A10: Expense Details | B10: The full register — 37 columns covering who, where, when, what, how much, tax, policy check and the approval trail.
A11: Trip Summary | B11: One row per trip: duration, line-item count, total spend, cost per day, policy breaches and billability.
A12: Employee Summary | B12: Spend per traveller, split by airfare / lodging / meals / ground transport, with policy breaches and missing receipts.
A13: Category by Month | B13: Category x month matrix with share of spend and the policy limit for each category.
A14: Policy Exceptions | B14: Audit view — every claim over its limit or missing a receipt.
A16: COLOUR LEGEND
A17: Blue text | B17: Hardcoded input value — amounts, FX rates, dates, statuses.
A18: Black text | B18: Calculated by formula — do not overwrite.
A19: Green text | B19: Live link to a cell on another tab.
A20: Yellow fill | B20: Key assumption you may want to change.
A21: Red fill | B21: Flagged for review on the Policy Exceptions tab.
A23: HOW FIGURES ARE DERIVED
A24: Amount (USD) | B24: Amount (Local) x FX Rate to USD
A25: VAT / Tax (USD) | B25: Amount (USD) - (Amount (USD) / (1 + VAT Rate)) — tax is inclusive
A26: Net of Tax (USD) | B26: Amount (USD) - VAT / Tax (USD)
A27: Over Policy? | B27: Yes when Amount (USD) exceeds the category Policy Limit
A28: Variance vs Limit | B28: Amount (USD) - Policy Limit (USD); negative means under budget
A29: Reimbursable (USD) | B29: Zero for corporate-card and rejected claims; otherwise the full amount, since only out-of-pocket spend is paid back
A30: Days to Reimburse | B30: Date Reimbursed - Date Submitted
A32: EXPENSE POLICY LIMITS APPLIED
B33: Per-claim caps. Lodging and car rental limits are multiplied by the number of nights or days on the trip.
A35: Category | B35: Policy Limit (USD)
A36: Airfare | B36: 1400
A37: Hotel / Lodging | B37: 280
A38: Meals - Breakfast | B38: 25
A39: Meals - Lunch | B39: 35
A40: Meals - Dinner | B40: 75
A41: Client Entertainment | B41: 200
A42: Ground Transport - Taxi | B42: 60
A43: Ground Transport - Rail | B43: 150
A44: Car Rental | B44: 120
A45: Fuel / Mileage | B45: 90
A46: Parking & Tolls | B46: 45
A47: Conference / Event Fee | B47: 1200
... A53: Office Supplies | B53: 60
A55: Assumption | B55: Value / Note
A56: Approval mix | B56: About 87% approved, 8% pending, 5% rejected
A57: Receipt compliance | B57: About 93% of claims have a receipt attached
A58: Over-limit rate | B58: About 9% of claims were generated above their category cap
A59: Payment mix | B59: 60% corporate card, 40% out-of-pocket (personal card or cash)
A60: FX rates | B60: Fixed period-average rates, e.g. EUR 1.0850, GBP 1.2720, INR 0.01178, JPY 0.00655, AED 0.2723
A61: Random seed | B61: 451213
A63: Data source | B63: SYNTHETIC. Generated by script on 2026-09-09 at the user's request. Employee names, vendors, client codes and amounts are invented; they do not refer to any real person, company or transaction.

Sheet Expense Details
A1: Expense ID | B1: Employee ID | C1: Employee Name | D1: Department | E1: Job Title | F1: Manager / Approver | G1: Trip ID | H1: Trip Purpose | I1: Destination City | J1: Destination Country | K1: Trip Start | L1: Trip End | M1: Expense Date | N1: Month | O1: Expense Category | P1: Description | Q1: Merchant / Vendor | R1: Payment Method | S1: Currency | T1: Amount (Local) | U1: FX Rate to USD | V1: Amount (USD) | W1: VAT / Tax Rate | X1: VAT / Tax (USD) | Y1: Net of Tax (USD) | Z1: Policy Limit (USD) | AA1: Over Policy? | AB1: Variance vs Limit (USD) | AC1: Receipt Attached | AD1: Billable to Client | AE1: Client / Project Code | AF1: Reimbursable (USD) | AG1: Approval Status | AH1: Date Submitted | AI1: Date Approved | AJ1: Date Reimbursed | AK1: Days to Reimburse
A2: EXP-00001 | B2: EMP-1103 | C2: Rohit Malhotra | D2: Sales | E2: Account Executive | F2: Ananya Sengupta | G2: TRP-2025-061 | H2: Client Meeting | I2: London | J2: United Kingdom | K2: 45658 | L2: 45661 | M2: 45658 | N2: 2025-01 | O2: Airfare | P2: Round trip HQ - London, economy | Q2: Lufthansa | R2: Corporate Card | S2: GBP | T2: 1219.76 | U2: 1.272 | V2: =T2*U2 -> 1551.5347 | W2: 0 | X2: =V2-(V2/(1+W2)) -> 0 | Y2: =V2-X2 -> 1551.5347 | Z2: 1400 | AA2: =IF(V2>Z2,"Yes","No") -> Yes | AB2: =V2-Z2 -> 151.53472 | AC2: Yes | AD2: No | AE2: INTERNAL-0000 | AF2: =IF(AG2="Rejected",0,IF(R2="Corporate Card",0,V2)) -> 0 | AG2: Approved | AH2: 45667 | AI2: 45672 | AJ2: 45686 | AK2: =IF(AJ2="","",AJ2-AH2) -> 19
A3: EXP-00002 | B3: EMP-1103 | C3: Rohit Malhotra | D3: Sales | E3: Account Executive | F3: Ananya Sengupta | G3: TRP-2025-061 | H3: Client Meeting | I3: London | J3: United Kingdom | K3: 45658 | L3: 45661 | M3: 45658 | N3: 2025-01 | O3: Baggage & Excess Fees | P3: Checked demo equipment | Q3: Emirates | R3: Personal Card (Reimbursable) | S3: GBP | T3: 64.39 | U3: 1.272 | V3: =T3*U3 -> 81.90408 | W3: 0 | X3: =V3-(V3/(1+W3)) -> 0 | Y3: =V3-X3 -> 81.90408 | Z3: 120 | AA3: =IF(V3>Z3,"Yes","No") -> No | AB3: =V3-Z3 -> -38.09592 | AC3: Yes | AD3: No | AE3: INTERNAL-0000 | AF3: =IF(AG3="Rejected",0,IF(R3="Corporate Card",0,V3)) -> 81.90408 | AG3: Approved | AH3: 45667 | AI3: 45672 | AJ3: 45686 | AK3: =IF(AJ3="","",AJ3-AH3) -> 19
A4: EXP-00003 | B4: EMP-1103 | C4: Rohit Malhotra | D4: Sales | E4: Account Executive | F4: Ananya Sengupta | G4: TRP-2025-061 | H4: Client Meeting | I4: London | J4: United Kingdom | K4: 45658 | L4: 45661 | M4: 45658 | N4: 2025-01 | O4: Meals - Breakfast | P4: Individual meal | Q4: Cafe Nero | R4: Corporate Card | S4: GBP | T4: 24.22 | U4: 1.272 | V4: =T4*U4 -> 30.80784 | W4: 0.2 | X4: =V4-(V4/(1+W4)) -> 5.13464 | Y4: =V4-X4 -> 25.6732 | Z4: 25 | AA4: =IF(V4>Z4,"Yes","No") -> Yes | AB4: =V4-Z4 -> 5.80784 | AC4: Yes | AD4: No | AE4: INTERNAL-0000 | AF4: =IF(AG4="Rejected",0,IF(R4="Corporate Card",0,V4)) -> 0 | AG4: Approved | AH4: 45667 | AI4: 45672 | AJ4: 45686 | AK4: =IF(AJ4="","",AJ4-AH4) -> 19
A5: EXP-00004 | B5: EMP-1103 | C5: Rohit Malhotra | D5: Sales | E5: Account Executive | F5: Ananya Sengupta | G5: TRP-2025-061 | H5: Client Meeting | I5: London | J5: United Kingdom | K5: 45658 | L5: 45661 | M5: 45659 | N5: 2025-01 | O5: Ground Transport - Taxi | P5: Airport / client site transfer | Q5: Local Taxi | R5: Personal Card (Reimbursable) | S5: GBP | T5: 28 | U5: 1.272 | V5: =T5*U5 -> 35.616 | W5: 0.2 | X5: =V5-(V5/(1+W5)) -> 5.936 | Y5: =V5-X5 -> 29.68 | Z5: 60 | AA5: =IF(V5>Z5,"Yes","No") -> No | AB5: =V5-Z5 -> -24.384 | AC5: Yes | AD5: No | AE5: INTERNAL-0000 | AF5: =IF(AG5="Rejected",0,IF(R5="Corporate Card",0,V5)) -> 35.616 | AG5: Approved | AH5: 45667 | AI5: 45672 | AJ5: 45686 | AK5: =IF(AJ5="","",AJ5-AH5) -> 19
A6: EXP-00005 | B6: EMP-1103 | C6: Rohit Malhotra | D6: Sales | E6: Account Executive | F6: Ananya Sengupta | G6: TRP-2025-061 | H6: Client Meeting | I6: London | J6: United Kingdom | K6: 45658 | L6: 45661 | M6: 45659 | N6: 2025-01 | O6: Hotel / Lodging | P6: 3 night(s) @ standard rate | Q6: Marriott | R6: Corporate Card | S6: GBP | T6: 574.25 | U6: 1.272 | V6: =T6*U6 -> 730.446 | W6: 0.2 | X6: =V6-(V6/(1+W6)) -> 121.741 | Y6: =V6-X6 -> 608.705 | Z6: 840 | AA6: =IF(V6>Z6,"Yes","No") -> No | AB6: =V6-Z6 -> -109.554 | AC6: Yes | AD6: No | AE6: INTERNAL-0000 | AF6: =IF(AG6="Rejected",0,IF(R6="Corporate Card",0,V6)) -> 0 | AG6: Approved | AH6: 45667 | AI6: 45672 | AJ6: 45686 | AK6: =IF(AJ6="","",AJ6-AH6) -> 19
A7: EXP-00006 | B7: EMP-1103 | C7: Rohit Malhotra | D7: Sales | E7: Account Executive | F7: Ananya Sengupta | G7: TRP-2025-061 | H7: Client Meeting | I7: London | J7: United Kingdom | K7: 45658 | L7: 45661 | M7: 45659 | N7: 2025-01 | O7: Meals - Breakfast | P7: Individual meal | Q7: Hotel Restaurant | R7: Cash (Reimbursable) | S7: GBP | T7: 11.21 | U7: 1.272 | V7: =T7*U7 -> 14.25912 | W7: 0.2 | X7: =V7-(V7/(1+W7)) -> 2.37652 | Y7: =V7-X7 -> 11.8826 | Z7: 25 | AA7: =IF(V7>Z7,"Yes","No") -> No | AB7: =V7-Z7 -> -10.74088 | AC7: Yes | AD7: No | AE7: INTERNAL-0000 | AF7: =IF(AG7="Rejected",0,IF(R7="Corporate Card",0,V7)) -> 14.25912 | AG7: Approved | AH7: 45667 | AI7: 45672 | AJ7: 45686 | AK7: =IF(AJ7="","",AJ7-AH7) -> 19
A8: EXP-00007 | B8: EMP-1103 | C8: Rohit Malhotra | D8: Sales | E8: Account Executive | F8: Ananya Sengupta | G8: TRP-2025-061 | H8: Client Meeting | I8: London | J8: United Kingdom | K8: 45658 | L8: 45661 | M8: 45659 | N8: 2025-01 | O8: Meals - Dinner | P8: Party of 4 | Q8: Brasserie Lyon | R8: Corporate Card | S8: GBP | T8: 41.88 | U8: 1.272 | V8: =T8*U8 -> 53.27136 | W8: 0.2 | X8: =V8-(V8/(1+W8)) -> 8.87856 | Y8: =V8-X8 -> 44.3928 | Z8: 75 | AA8: =IF(V8>Z8,"Yes","No") -> No | AB8: =V8-Z8 -> -21.72864 | AC8: Yes | AD8: No | AE8: INTERNAL-0000 | AF8: =IF(AG8="Rejected",0,IF(R8="Corporate Card",0,V8)) -> 0 | AG8: Approved | AH8: 45667 | AI8: 45672 | AJ8: 45686 | AK8: =IF(AJ8="","",AJ8-AH8) -> 19
A9: EXP-00008 | B9: EMP-1103 | C9: Rohit Malhotra | D9: Sales | E9: Account Executive | F9: Ananya Sengupta | G9: TRP-2025-061 | H9: Client Meeting | I9: London | J9: United Kingdom | K9: 45658 | L9: 45661 | M9: 45659 | N9: 2025-01 | O9: Meals - Lunch | P9: Individual meal | Q9: Local Bistro | R9: Personal Card (Reimbursable) | S9: GBP | T9: 10.06 | U9: 1.272 | V9: =T9*U9 -> 12.79632 | W9: 0.2 | X9: =V9-(V9/(1+W9)) -> 2.13272 | Y9: =V9-X9 -> 10.6636 | Z9: 35 | AA9: =IF(V9>Z9,"Yes","No") -> No | AB9: =V9-Z9 -> -22.20368 | AC9: Yes | AD9: No | AE9: INTERNAL-0000 | AF9: =IF(AG9="Rejected",0,IF(R9="Corporate Card",0,V9)) -> 12.79632 | AG9: Approved | AH9: 45667 | AI9: 45672 | AJ9: 45686 | AK9: =IF(AJ9="","",AJ9-AH9) -> 19
A10: EXP-00009 | B10: EMP-1103 | C10: Rohit Malhotra | D10: Sales | E10: Account Executive | F10: Ananya Sengupta | G10: TRP-2025-061 | H10: Client Meeting | I10: London | J10: United Kingdom | K10: 45658 | L10: 45661 | M10: 45660 | N10: 2025-01 | O10: Ground Transport - Taxi | P10: Airport / client site transfer | Q10: Grab | R10: Corporate Card | S10: GBP | T10: 40.46 | U10: 1.272 | V10: =T10*U10 -> 51.46512 | W10: 0.2 | X10: =V10-(V10/(1+W10)) -> 8.57752 | Y10: =V10-X10 -> 42.8876 | Z10: 60 | AA10: =IF(V10>Z10,"Yes","No") -> No | AB10: =V10-Z10 -> -8.53488 | AC10: Yes | AD10: No | AE10: INTERNAL-0000 | AF10: =IF(AG10="Rejected",0,IF(R10="Corporate Card",0,V10)) -> 0 | AG10: Approved | AH10: 45667 | AI10: 45672 | AJ10: 45686 | AK10: =IF(AJ10="","",AJ10-AH10) -> 19
A11: EXP-00010 | B11: EMP-1103 | C11: Rohit Malhotra | D11: Sales | E11: Account Executive | F11: Ananya Sengupta | G11: TRP-2025-061 | H11: Client Meeting | I11: London | J11: United Kingdom | K11: 45658 | L11: 45661 | M11: 45660 | N11: 2025-01 | O11: Meals - Breakfast | P11: Individual meal | Q11: Hotel Restaurant | R11: Corporate Card | S11: GBP | T11: 18.83 | U11: 1.272 | V11: =T11*U11 -> 23.95176 | W11: 0.2 | X11: =V11-(V11/(1+W11)) -> 3.99196 | Y11: =V11-X11 -> 19.9598 | Z11: 25 | AA11: =IF(V11>Z11,"Yes","No") -> No | AB11: =V11-Z11 -> -1.04824 | AC11: Yes | AD11: No | AE11: INTERNAL-0000 | AF11: =IF(AG11="Rejected",0,IF(R11="Corporate Card",0,V11)) -> 0 | AG11: Approved | AH11: 45667 | AI11: 45672 | AJ11: 45686 | AK11: =IF(AJ11="","",AJ11-AH11) -> 19
A12: EXP-00011 | B12: EMP-1103 | C12: Rohit Malhotra | D12: Sales | E12: Account Executive | F12: Ananya Sengupta | G12: TRP-2025-061 | H12: Client Meeting | I12: London | J12: United Kingdom | K12: 45658 | L12: 45661 | M12: 45660 | N12: 2025-01 | O12: Meals - Dinner | P12: Party of 4 | Q12: The Grill House | R12: Personal Card (Reimbursable) | S12: GBP | T12: 38.94 | U12: 1.272 | V12: =T12*U12 -> 49.53168 | W12: 0.2 | X12: =V12-(V12/(1+W12)) -> 8.25528 | Y12: =V12-X12 -> 41.2764 | Z12: 75 | AA12: =IF(V12>Z12,"Yes","No") -> No | AB12: =V12-Z12 -> -25.46832 | AC12: Yes | AD12: No | AE12: INTERNAL-0000 | AF12: =IF(AG12="Rejected",0,IF(R12="Corporate Card",0,V12)) -> 49.53168 | AG12: Approved | AH12: 45667 | AI12: 45672 | AJ12: 45686 | AK12: =IF(AJ12="","",AJ12-AH12) -> 19
A13: EXP-00012 | B13: EMP-1103 | C13: Rohit Malhotra | D13: Sales | E13: Account Executive | F13: Ananya Sengupta | G13: TRP-2025-061 | H13: Client Meeting | I13: London | J13: United Kingdom | K13: 45658 | L13: 45661 | M13: 45660 | N13: 2025-01 | O13: Meals - Lunch | P13: Individual meal | Q13: Sweetgreen | R13: Corporate Card | S13: GBP | T13: 35.53 | U13: 1.272 | V13: =T13*U13 -> 45.19416 | W13: 0.2 | X13: =V13-(V13/(1+W13)) -> 7.53236 | Y13: =V13-X13 -> 37.6618 | Z13: 35 | AA13: =IF(V13>Z13,"Yes","No") -> Yes | AB13: =V13-Z13 -> 10.19416 | AC13: Yes | AD13: No | AE13: INTERNAL-0000 | AF13: =IF(AG13="Rejected",0,IF(R13="Corporate Card",0,V13)) -> 0 | AG13: Approved | AH13: 45667 | AI13: 45672 | AJ13: 45686 | AK13: =IF(AJ13="","",AJ13-AH13) -> 19
... A16: EXP-00015 | B16: EMP-1103 | C16: Rohit Malhotra | D16: Sales | E16: Account Executive | F16: Ananya Sengupta | G16: TRP-2025-061 | H16: Client Meeting | I16: London | J16: United Kingdom | K16: 45658 | L16: 45661 | M16: 45661 | N16: 2025-01 | O16: Meals - Lunch | P16: Individual meal | Q16: Local Bistro | R16: Personal Card (Reimbursable) | S16: GBP | T16: 24.13 | U16: 1.272 | V16: =T16*U16 -> 30.69336 | W16: 0.2 | X16: =V16-(V16/(1+W16)) -> 5.11556 | Y16: =V16-X16 -> 25.5778 | Z16: 35 | AA16: =IF(V16>Z16,"Yes","No") -> No | AB16: =V16-Z16 -> -4.30664 | AC16: No | AD16: No | AE16: INTERNAL-0000 | AF16: =IF(AG16="Rejected",0,IF(R16="Corporate Card",0,V16)) -> 30.69336 | AG16: Approved | AH16: 45667 | AI16: 45672 | AJ16: 45686 | AK16: =IF(AJ16="","",AJ16-AH16) -> 19
A17: EXP-00016 | B17: EMP-1229 | C17: Samuel Adeyemi | D17: Field Engineering | E17: Field Engineer | F17: Tomas Kovac | G17: TRP-2025-116 | H17: Client Meeting | I17: Sao Paulo | J17: Brazil | K17: 45661 | L17: 45668 | M17: 45661 | N17: 2025-01 | O17: Airfare | P17: Round trip HQ - Sao Paulo, economy | Q17: Delta Air Lines | R17: Corporate Card | S17: BRL | T17: 6071.89 | U17: 0.181 | V17: =T17*U17 -> 1099.0121 | W17: 0 | X17: =V17-(V17/(1+W17)) -> 0 | Y17: =V17-X17 -> 1099.0121 | Z17: 1400 | AA17: =IF(V17>Z17,"Yes","No") -> No | AB17: =V17-Z17 -> -300.98791 | AC17: Yes | AD17: Yes | AE17: BLUEPEAK-7702 | AF17: =IF(AG17="Rejected",0,IF(R17="Corporate Card",0,V17)) -> 0 | AG17: Pending Approval | AH17: 45677 | AK17: =IF(AJ17="","",AJ17-AH17)
A18: EXP-00017 | B18: EMP-1229 | C18: Samuel Adeyemi | D18: Field Engineering | E18: Field Engineer | F18: Tomas Kovac | G18: TRP-2025-116 | H18: Client Meeting | I18: Sao Paulo | J18: Brazil | K18: 45661 | L18: 45668 | M18: 45661 | N18: 2025-01 | O18: Baggage & Excess Fees | P18: Checked demo equipment | Q18: Emirates | R18: Personal Card (Reimbursable) | S18: BRL | T18: 341.6 | U18: 0.181 | V18: =T18*U18 -> 61.8296 | W18: 0 | X18: =V18-(V18/(1+W18)) -> 0 | Y18: =V18-X18 -> 61.8296 | Z18: 120 | AA18: =IF(V18>Z18,"Yes","No") -> No | AB18: =V18-Z18 -> -58.1704 | AC18: Yes | AD18: Yes | AE18: BLUEPEAK-7702 | AF18: =IF(AG18="Rejected",0,IF(R18="Corporate Card",0,V18)) -> 61.8296 | AG18: Pending Approval | AH18: 45677 | AK18: =IF(AJ18="","",AJ18-AH18)
A19: EXP-00018 | B19: EMP-1229 | C19: Samuel Adeyemi | D19: Field Engineering | E19: Field Engineer | F19: Tomas Kovac | G19: TRP-2025-116 | H19: Client Meeting | I19: Sao Paulo | J19: Brazil | K19: 45661 | L19: 45668 | M19: 45661 | N19: 2025-01 | O19: Ground Transport - Taxi | P19: Airport / client site transfer | Q19: Grab | R19: Corporate Card | S19: BRL | T19: 254.57 | U19: 0.181 | V19: =T19*U19 -> 46.07717 | W19: 0.17 | X19: =V19-(V19/(1+W19)) -> 6.6949734 | Y19: =V19-X19 -> 39.382197 | Z19: 60 | AA19: =IF(V19>Z19,"Yes","No") -> No | AB19: =V19-Z19 -> -13.92283 | AC19: Yes | AD19: Yes | AE19: BLUEPEAK-7702 | AF19: =IF(AG19="Rejected",0,IF(R19="Corporate Card",0,V19)) -> 0 | AG19: Pending Approval | AH19: 45677 | AK19: =IF(AJ19="","",AJ19-AH19)
A20: EXP-00019 | B20: EMP-1229 | C20: Samuel Adeyemi | D20: Field Engineering | E20: Field Engineer | F20: Tomas Kovac | G20: TRP-2025-116 | H20: Client Meeting | I20: Sao Paulo | J20: Brazil | K20: 45661 | L20: 45668 | M20: 45661 | N20: 2025-01 | O20: Meals - Dinner | P20: Party of 2 | Q20: Osteria Vela | R20: Corporate Card | S20: BRL | T20: 324.01 | U20: 0.181 | V20: =T20*U20 -> 58.64581 | W20: 0.17 | X20: =V20-(V20/(1+W20)) -> 8.5211861 | Y20: =V20-X20 -> 50.124624 | Z20: 75 | AA20: =IF(V20>Z20,"Yes","No") -> No | AB20: =V20-Z20 -> -16.35419 | AC20: No | AD20: Yes | AE20: BLUEPEAK-7702 | AF20: =IF(AG20="Rejected",0,IF(R20="Corporate Card",0,V20)) -> 0 | AG20: Pending Approval | AH20: 45677 | AK20: =IF(AJ20="","",AJ20-AH20)
A21: EXP-00020 | B21: EMP-1229 | C21: Samuel Adeyemi | D21: Field Engineering | E21: Field Engineer | F21: Tomas Kovac | G21: TRP-2025-116 | H21: Client Meeting | I21: Sao Paulo | J21: Brazil | K21: 45661 | L21: 45668 | M21: 45661 | N21: 2025-01 | O21: Meals - Lunch | P21: Individual meal | Q21: Pret A Manger | R21: Personal Card (Reimbursable) | S21: BRL | T21: 88.32 | U21: 0.181 | V21: =T21*U21 -> 15.98592 | W21: 0.17 | X21: =V21-(V21/(1+W21)) -> 2.3227405 | Y21: =V21-X21 -> 13.663179 | Z21: 35 | AA21: =IF(V21>Z21,"Yes","No") -> No | AB21: =V21-Z21 -> -19.01408 | AC21: Yes | AD21: Yes | AE21: BLUEPEAK-7702 | AF21: =IF(AG21="Rejected",0,IF(R21="Corporate Card",0,V21)) -> 15.98592 | AG21: Pending Approval | AH21: 45677 | AK21: =IF(AJ21="","",AJ21-AH21)
A22: EXP-00021 | B22: EMP-1204 | C22: Priya Nair | D22: Field Engineering | E22: Senior Field Engineer | F22: Tomas Kovac | G22: TRP-2025-109 | H22: Product Launch Event | I22: Paris | J22: France | K22: 45662 | L22: 45665 | M22: 45662 | N22: 2025-01 | O22: Airfare | P22: Round trip HQ - Paris, economy | Q22: Singapore Airlines | R22: Corporate Card | S22: EUR | T22: 1221.22 | U22: 1.085 | V22: =T22*U22 -> 1325.0237 | W22: 0 | X22: =V22-(V22/(1+W22)) -> 0 | Y22: =V22-X22 -> 1325.0237 | Z22: 1400 | AA22: =IF(V22>Z22,"Yes","No") -> No | AB22: =V22-Z22 -> -74.9763 | AC22: Yes | AD22: No | AE22: INTERNAL-0000 | AF22: =IF(AG22="Rejected",0,IF(R22="Corporate Card",0,V22)) -> 0 | AG22: Approved | AH22: 45670 | AI22: 45678 | AJ22: 45685 | AK22: =IF(AJ22="","",AJ22-AH22) -> 15
A23: EXP-00022 | B23: EMP-1204 | C23: Priya Nair | D23: Field Engineering | E23: Senior Field Engineer | F23: Tomas Kovac | G23: TRP-2025-109 | H23: Product Launch Event | I23: Paris | J23: France | K23: 45662 | L23: 45665 | M23: 45662 | N23: 2025-01 | O23: Conference / Event Fee | P23: Delegate registration | Q23: SensorTech Summit | R23: Corporate Card | S23: EUR | T23: 1058.38 | U23: 1.085 | V23: =T23*U23 -> 1148.3423 | W23: 0 | X23: =V23-(V23/(1+W23)) -> 0 | Y23: =V23-X23 -> 1148.3423 | Z23: 1200 | AA23: =IF(V23>Z23,"Yes","No") -> No | AB23: =V23-Z23 -> -51.6577 | AC23: Yes | AD23: No | AE23: INTERNAL-0000 | AF23: =IF(AG23="Rejected",0,IF(R23="Corporate Card",0,V23)) -> 0 | AG23: Approved | AH23: 45670 | AI23: 45678 | AJ23: 45685 | AK23: =IF(AJ23="","",AJ23-AH23) -> 15
A24: EXP-00023 | B24: EMP-1204 | C24: Priya Nair | D24: Field Engineering | E24: Senior Field Engineer | F24: Tomas Kovac | G24: TRP-2025-109 | H24: Product Launch Event | I24: Paris | J24: France | K24: 45662 | L24: 45665 | M24: 45662 | N24: 2025-01 | O24: Ground Transport - Taxi | P24: Airport / client site transfer | Q24: Ola Cabs | R24: Corporate Card | S24: EUR | T24: 33.06 | U24: 1.085 | V24: =T24*U24 -> 35.8701 | W24: 0.19 | X24: =V24-(V24/(1+W24)) -> 5.7271588 | Y24: =V24-X24 -> 30.142941 | Z24: 60 | AA24: =IF(V24>Z24,"Yes","No") -> No | AB24: =V24-Z24 -> -24.1299 | AC24: Yes | AD24: No | AE24: INTERNAL-0000 | AF24: =IF(AG24="Rejected",0,IF(R24="Corporate Card",0,V24)) -> 0 | AG24: Approved | AH24: 45670 | AI24: 45678 | AJ24: 45685 | AK24: =IF(AJ24="","",AJ24-AH24) -> 15
A25: EXP-00024 | B25: EMP-1204 | C25: Priya Nair | D25: Field Engineering | E25: Senior Field Engineer | F25: Tomas Kovac | G25: TRP-2025-109 | H25: Product Launch Event | I25: Paris | J25: France | K25: 45662 | L25: 45665 | M25: 45662 | N25: 2025-01 | O25: Meals - Breakfast | P25: Individual meal | Q25: Starbucks | R25: Corporate Card | S25: EUR | T25: 21.52 | U25: 1.085 | V25: =T25*U25 -> 23.3492 | W25: 0.19 | X25: =V25-(V25/(1+W25)) -> 3.7280235 | Y25: =V25-X25 -> 19.621176 | Z25: 25 | AA25: =IF(V25>Z25,"Yes","No") -> No | AB25: =V25-Z25 -> -1.6508 | AC25: Yes | AD25: No | AE25: INTERNAL-0000 | AF25: =IF(AG25="Rejected",0,IF(R25="Corporate Card",0,V25)) -> 0 | AG25: Approved | AH25: 45670 | AI25: 45678 | AJ25: 45685 | AK25: =IF(AJ25="","",AJ25-AH25) -> 15
A26: EXP-00025 | B26: EMP-1204 | C26: Priya Nair | D26: Field Engineering | E26: Senior Field Engineer | F26: Tomas Kovac | G26: TRP-2025-109 | H26: Product Launch Event | I26: Paris | J26: France | K26: 45662 | L26: 45665 | M26: 45662 | N26: 2025-01 | O26: Meals - Dinner | P26: Party of 4 | Q26: Osteria Vela | R26: Corporate Card | S26: EUR | T26: 33.22 | U26: 1.085 | V26: =T26*U26 -> 36.0437 | W26: 0.19 | X26: =V26-(V26/(1+W26)) -> 5.7548765 | Y26: =V26-X26 -> 30.288824 | Z26: 75 | AA26: =IF(V26>Z26,"Yes","No") -> No | AB26: =V26-Z26 -> -38.9563 | AC26: Yes | AD26: No | AE26: INTERNAL-0000 | AF26: =IF(AG26="Rejected",0,IF(R26="Corporate Card",0,V26)) -> 0 | AG26: Approved | AH26: 45670 | AI26: 45678 | AJ26: 45685 | AK26: =IF(AJ26="","",AJ26-AH26) -> 15
A27: EXP-00026 | B27: EMP-1204 | C27: Priya Nair | D27: Field Engineering | E27: Senior Field Engineer | F27: Tomas Kovac | G27: TRP-2025-109 | H27: Product Launch Event | I27: Paris | J27: France | K27: 45662 | L27: 45665 | M27: 45662 | N27: 2025-01 | O27: Meals - Lunch | P27: Individual meal | Q27: Local Bistro | R27: Corporate Card | S27: EUR | T27: 40.7 | U27: 1.085 | V27: =T27*U27 -> 44.1595 | W27: 0.19 | X27: =V27-(V27/(1+W27)) -> 7.0506765 | Y27: =V27-X27 -> 37.108824 | Z27: 35 | AA27: =IF(V27>Z27,"Yes","No") -> Yes | AB27: =V27-Z27 -> 9.1595 | AC27: Yes | AD27: No | AE27: INTERNAL-0000 | AF27: =IF(AG27="Rejected",0,IF(R27="Corporate Card",0,V27)) -> 0 | AG27: Approved | AH27: 45670 | AI27: 45678 | AJ27: 45685 | AK27: =IF(AJ27="","",AJ27-AH27) -> 15
A28: EXP-00027 | B28: EMP-1229 | C28: Samuel Adeyemi | D28: Field Engineering | E28: Field Engineer | F28: Tomas Kovac | G28: TRP-2025-116 | H28: Client Meeting | I28: Sao Paulo | J28: Brazil | K28: 45661 | L28: 45668 | M28: 45662 | N28: 2025-01 | O28: Hotel / Lodging | P28: 7 night(s) @ standard rate | Q28: Premier Inn | R28: Corporate Card | S28: BRL | T28: 9806.12 | U28: 0.181 | V28: =T28*U28 -> 1774.9077 | W28: 0.17 | X28: =V28-(V28/(1+W28)) -> 257.89257 | Y28: =V28-X28 -> 1517.0151 | Z28: 1960 | AA28: =IF(V28>Z28,"Yes","No") -> No | AB28: =V28-Z28 -> -185.09228 | AC28: Yes | AD28: Yes | AE28: BLUEPEAK-7702 | AF28: =IF(AG28="Rejected",0,IF(R28="Corporate Card",0,V28)) -> 0 | AG28: Pending Approval | AH28: 45677 | AK28: =IF(AJ28="","",AJ28-AH28)
A29: EXP-00028 | B29: EMP-1229 | C29: Samuel Adeyemi | D29: Field Engineering | E29: Field Engineer | F29: Tomas Kovac | G29: TRP-2025-116 | H29: Client Meeting | I29: Sao Paulo | J29: Brazil | K29: 45661 | L29: 45668 | M29: 45662 | N29: 2025-01 | O29: Internet / Roaming | P29: International data pack | Q29: Vodafone Roaming | R29: Corporate Card | S29: BRL | T29: 303.2 | U29: 0.181 | V29: =T29*U29 -> 54.8792 | W29: 0.17 | X29: =V29-(V29/(1+W29)) -> 7.9739009 | Y29: =V29-X29 -> 46.905299 | Z29: 55 | AA29: =IF(V29>Z29,"Yes","No") -> No | AB29: =V29-Z29 -> -0.1208 | AC29: Yes | AD29: Yes | AE29: BLUEPEAK-7702 | AF29: =IF(AG29="Rejected",0,IF(R29="Corporate Card",0,V29)) -> 0 | AG29: Pending Approval | AH29: 45677 | AK29: =IF(AJ29="","",AJ29-AH29)
A30: EXP-00029 | B30: EMP-1229 | C30: Samuel Adeyemi | D30: Field Engineering | E30: Field Engineer | F30: Tomas Kovac | G30: TRP-2025-116 | H30: Client Meeting | I30: Sao Paulo | J30: Brazil | K30: 45661 | L30: 45668 | M30: 45662 | N30: 2025-01 | O30: Meals - Breakfast | P30: Individual meal | Q30: Local Bakery | R30: Corporate Card | S30: BRL | T30: 55.76 | U30: 0.181 | V30: =T30*U30 -> 10.09256 | W30: 0.17 | X30: =V30-(V30/(1+W30)) -> 1.4664403 | Y30: =V30-X30 -> 8.6261197 | Z30: 25 | AA30: =IF(V30>Z30,"Yes","No") -> No | AB30: =V30-Z30 -> -14.90744 | AC30: Yes | AD30: Yes | AE30: BLUEPEAK-7702 | AF30: =IF(AG30="Rejected",0,IF(R30="Corporate Card",0,V30)) -> 0 | AG30: Pending Approval | AH30: 45677 | AK30: =IF(AJ30="","",AJ30-AH30)
A31: EXP-00030 | B31: EMP-1229 | C31: Samuel Adeyemi | D31: Field Engineering | E31: Field Engineer | F31: Tomas Kovac | G31: TRP-2025-116 | H31: Client Meeting | I31: Sao Paulo | J31: Brazil | K31: 45661 | L31: 45668 | M31: 45662 | N31: 2025-01 | O31: Meals - Dinner | P31: Party of 4 | Q31: The Grill House | R31: Cash (Reimbursable) | S31: BRL | T31: 206.42 | U31: 0.181 | V31: =T31*U31 -> 37.36202 | W31: 0.17 | X31: =V31-(V31/(1+W31)) -> 5.4286696 | Y31: =V31-X31 -> 31.93335 | Z31: 75 | AA31: =IF(V31>Z31,"Yes","No") -> No | AB31: =V31-Z31 -> -37.63798 | AC31: No | AD31: Yes | AE31: BLUEPEAK-7702 | AF31: =IF(AG31="Rejected",0,IF(R31="Corporate Card",0,V31)) -> 37.36202 | AG31: Pending Approval | AH31: 45677 | AK31: =IF(AJ31="","",AJ31-AH31)
A32: EXP-00031 | B32: EMP-1229 | C32: Samuel Adeyemi | D32: Field Engineering | E32: Field Engineer | F32: Tomas Kovac | G32: TRP-2025-116 | H32: Client Meeting | I32: Sao Paulo | J32: Brazil | K32: 45661 | L32: 45668 | M32: 45662 | N32: 2025-01 | O32: Meals - Lunch | P32: Individual meal | Q32: Food Court | R32: Corporate Card | S32: BRL | T32: 87.67 | U32: 0.181 | V32: =T32*U32 -> 15.86827 | W32: 0.17 | X32: =V32-(V32/(1+W32)) -> 2.3056461 | Y32: =V32-X32 -> 13.562624 | Z32: 35 | AA32: =IF(V32>Z32,"Yes","No") -> No | AB32: =V32-Z32 -> -19.13173 | AC32: Yes | AD32: Yes | AE32: BLUEPEAK-7702 | AF32: =IF(AG32="Rejected",0,IF(R32="Corporate Card",0,V32)) -> 0 | AG32: Pending Approval | AH32: 45677 | AK32: =IF(AJ32="","",AJ32-AH32)
A33: EXP-00032 | B33: EMP-1204 | C33: Priya Nair | D33: Field Engineering | E33: Senior Field Engineer | F33: Tomas Kovac | G33: TRP-2025-109 | H33: Product Launch Event | I33: Paris | J33: France | K33: 45662 | L33: 45665 | M33: 45663 | N33: 2025-01 | O33: Ground Transport - Taxi | P33: Airport / client site transfer | Q33: Grab | R33: Corporate Card | S33: EUR | T33: 26.45 | U33: 1.085 | V33: =T33*U33 -> 28.69825 | W33: 0.19 | X33: =V33-(V33/(1+W33)) -> 4.5820735 | Y33: =V33-X33 -> 24.116176 | Z33: 60 | AA33: =IF(V33>Z33,"Yes","No") -> No | AB33: =V33-Z33 -> -31.30175 | AC33: Yes | AD33: No | AE33: INTERNAL-0000 | AF33: =IF(AG33="Rejected",0,IF(R33="Corporate Card",0,V33)) -> 0 | AG33: Approved | AH33: 45670 | AI33: 45678 | AJ33: 45685 | AK33: =IF(AJ33="","",AJ33-AH33) -> 15
A34: EXP-00033 | B34: EMP-1204 | C34: Priya Nair | D34: Field Engineering | E34: Senior Field Engineer | F34: Tomas Kovac | G34: TRP-2025-109 | H34: Product Launch Event | I34: Paris | J34: France | K34: 45662 | L34: 45665 | M34: 45663 | N34: 2025-01 | O34: Hotel / Lodging | P34: 3 night(s) @ standard rate | Q34: Hilton Garden Inn | R34: Cash (Reimbursable) | S34: EUR | T34: 489.02 | U34: 1.085 | V34: =T34*U34 -> 530.5867 | W34: 0.19 | X34: =V34-(V34/(1+W34)) -> 84.715524 | Y34: =V34-X34 -> 445.87118 | Z34: 840 | AA34: =IF(V34>Z34,"Yes","No") -> No | AB34: =V34-Z34 -> -309.4133 | AC34: Yes | AD34: No | AE34: INTERNAL-0000 | AF34: =IF(AG34="Rejected",0,IF(R34="Corporate Card",0,V34)) -> 530.5867 | AG34: Approved | AH34: 45670 | AI34: 45678 | AJ34: 45685 | AK34: =IF(AJ34="","",AJ34-AH34) -> 15
A35: EXP-00034 | B35: EMP-1204 | C35: Priya Nair | D35: Field Engineering | E35: Senior Field Engineer | F35: Tomas Kovac | G35: TRP-2025-109 | H35: Product Launch Event | I35: Paris | J35: France | K35: 45662 | L35: 45665 | M35: 45663 | N35: 2025-01 | O35: Meals - Dinner | P35: Party of 2 | Q35: The Grill House | R35: Personal Card (Reimbursable) | S35: EUR | T35: 48.81 | U35: 1.085 | V35: =T35*U35 -> 52.95885 | W35: 0.19 | X35: =V35-(V35/(1+W35)) -> 8.4556147 | Y35: =V35-X35 -> 44.503235 | Z35: 75 | AA35: =IF(V35>Z35,"Yes","No") -> No | AB35: =V35-Z35 -> -22.04115 | AC35: No | AD35: No | AE35: INTERNAL-0000 | AF35: =IF(AG35="Rejected",0,IF(R35="Corporate Card",0,V35)) -> 52.95885 | AG35: Approved | AH35: 45670 | AI35: 45678 | AJ35: 45685 | AK35: =IF(AJ35="","",AJ35-AH35) -> 15
A36: EXP-00035 | B36: EMP-1204 | C36: Priya Nair | D36: Field Engineering | E36: Senior Field Engineer | F36: Tomas Kovac | G36: TRP-2025-109 | H36: Product Launch Event | I36: Paris | J36: France | K36: 45662 | L36: 45665 | M36: 45663 | N36: 2025-01 | O36: Meals - Lunch | P36: Individual meal | Q36: Food Court | R36: Corporate Card | S36: EUR | T36: 29.38 | U36: 1.085 | V36: =T36*U36 -> 31.8773 | W36: 0.19 | X36: =V36-(V36/(1+W36)) -> 5.0896529 | Y36: =V36-X36 -> 26.787647 | Z36: 35 | AA36: =IF(V36>Z36,"Yes","No") -> No | AB36: =V36-Z36 -> -3.1227 | AC36: Yes | AD36: No | AE36: INTERNAL-0000 | AF36: =IF(AG36="Rejected",0,IF(R36="Corporate Card",0,V36)) -> 0 | AG36: Approved | AH36: 45670 | AI36: 45678 | AJ36: 45685 | AK36: =IF(AJ36="","",AJ36-AH36) -> 15
A37: EXP-00036 | B37: EMP-1229 | C37: Samuel Adeyemi | D37: Field Engineering | E37: Field Engineer | F37: Tomas Kovac | G37: TRP-2025-116 | H37: Client Meeting | I37: Sao Paulo | J37: Brazil | K37: 45661 | L37: 45668 | M37: 45663 | N37: 2025-01 | O37: Ground Transport - Taxi | P37: Airport / client site transfer | Q37: Lyft | R37: Corporate Card | S37: BRL | T37: 237.13 | U37: 0.181 | V37: =T37*U37 -> 42.92053 | W37: 0.17 | X37: =V37-(V37/(1+W37)) -> 6.2363163 | Y37: =V37-X37 -> 36.684214 | Z37: 60 | AA37: =IF(V37>Z37,"Yes","No") -> No | AB37: =V37-Z37 -> -17.07947 | AC37: Yes | AD37: Yes | AE37: BLUEPEAK-7702 | AF37: =IF(AG37="Rejected",0,IF(R37="Corporate Card",0,V37)) -> 0 | AG37: Pending Approval | AH37: 45677 | AK37: =IF(AJ37="","",AJ37-AH37)
A38: EXP-00037 | B38: EMP-1229 | C38: Samuel Adeyemi | D38: Field Engineering | E38: Field Engineer | F38: Tomas Kovac | G38: TRP-2025-116 | H38: Client Meeting | I38: Sao Paulo | J38: Brazil | K38: 45661 | L38: 45668 | M38: 45663 | N38: 2025-01 | O38: Meals - Breakfast | P38: Individual meal | Q38: Cafe Nero | R38: Corporate Card | S38: BRL | T38: 91.17 | U38: 0.181 | V38: =T38*U38 -> 16.50177 | W38: 0.17 | X38: =V38-(V38/(1+W38)) -> 2.3976931 | Y38: =V38-X38 -> 14.104077 | Z38: 25 | AA38: =IF(V38>Z38,"Yes","No") -> No | AB38: =V38-Z38 -> -8.49823 | AC38: Yes | AD38: Yes | AE38: BLUEPEAK-7702 | AF38: =IF(AG38="Rejected",0,IF(R38="Corporate Card",0,V38)) -> 0 | AG38: Pending Approval | AH38: 45677 | AK38: =IF(AJ38="","",AJ38-AH38)
A39: EXP-00038 | B39: EMP-1229 | C39: Samuel Adeyemi | D39: Field Engineering | E39: Field Engineer | F39: Tomas Kovac | G39: TRP-2025-116 | H39: Client Meeting | I39: Sao Paulo | J39: Brazil | K39: 45661 | L39: 45668 | M39: 45663 | N39: 2025-01 | O39: Meals - Dinner | P39: Party of 2 | Q39: Sakura Izakaya | R39: Cash (Reimbursable) | S39: BRL | T39: 297.49 | U39: 0.181 | V39: =T39*U39 -> 53.84569 | W39: 0.17 | X39: =V39-(V39/(1+W39)) -> 7.8237327 | Y39: =V39-X39 -> 46.021957 | Z39: 75 | AA39: =IF(V39>Z39,"Yes","No") -> No | AB39: =V39-Z39 -> -21.15431 | AC39: Yes | AD39: Yes | AE39: BLUEPEAK-7702 | AF39: =IF(AG39="Rejected",0,IF(R39="Corporate Card",0,V39)) -> 53.84569 | AG39: Pending Approval | AH39: 45677 | AK39: =IF(AJ39="","",AJ39-AH39)
A40: EXP-00039 | B40: EMP-1229 | C40: Samuel Adeyemi | D40: Field Engineering | E40: Field Engineer | F40: Tomas Kovac | G40: TRP-2025-116 | H40: Client Meeting | I40: Sao Paulo | J40: Brazil | K40: 45661 | L40: 45668 | M40: 45663 | N40: 2025-01 | O40: Meals - Lunch | P40: Individual meal | Q40: Food Court | R40: Personal Card (Reimbursable) | S40: BRL | T40: 88.32 | U40: 0.181 | V40: =T40*U40 -> 15.98592 | W40: 0.17 | X40: =V40-(V40/(1+W40)) -> 2.3227405 | Y40: =V40-X40 -> 13.663179 | Z40: 35 | AA40: =IF(V40>Z40,"Yes","No") -> No | AB40: =V40-Z40 -> -19.01408 | AC40: Yes | AD40: Yes | AE40: BLUEPEAK-7702 | AF40: =IF(AG40="Rejected",0,IF(R40="Corporate Card",0,V40)) -> 15.98592 | AG40: Pending Approval | AH40: 45677 | AK40: =IF(AJ40="","",AJ40-AH40)
A41: EXP-00040 | B41: EMP-1204 | C41: Priya Nair | D41: Field Engineering | E41: Senior Field Engineer | F41: Tomas Kovac | G41: TRP-2025-109 | H41: Product Launch Event | I41: Paris | J41: France | K41: 45662 | L41: 45665 | M41: 45664 | N41: 2025-01 | O41: Meals - Breakfast | P41: Individual meal | Q41: Local Bakery | R41: Personal Card (Reimbursable) | S41: EUR | T41: 16.25 | U41: 1.085 | V41: =T41*U41 -> 17.63125 | W41: 0.19 | X41: =V41-(V41/(1+W41)) -> 2.8150735 | Y41: =V41-X41 -> 14.816176 | Z41: 25 | AA41: =IF(V41>Z41,"Yes","No") -> No | AB41: =V41-Z41 -> -7.36875 | AC41: Yes | AD41: No | AE41: INTERNAL-0000 | AF41: =IF(AG41="Rejected",0,IF(R41="Corporate Card",0,V41)) -> 17.63125 | AG41: Approved | AH41: 45670 | AI41: 45678 | AJ41: 45685 | AK41: =IF(AJ41="","",AJ41-AH41) -> 15
A42: EXP-00041 | B42: EMP-1204 | C42: Priya Nair | D42: Field Engineering | E42: Senior Field Engineer | F42: Tomas Kovac | G42: TRP-2025-109 | H42: Product Launch Event | I42: Paris | J42: France | K42: 45662 | L42: 45665 | M42: 45664 | N42: 2025-01 | O42: Meals - Dinner | P42: Party of 1 | Q42: Sakura Izakaya | R42: Corporate Card | S42: EUR | T42: 63.82 | U42: 1.085 | V42: =T42*U42 -> 69.2447 | W42: 0.19 | X42: =V42-(V42/(1+W42)) -> 11.055876 | Y42: =V42-X42 -> 58.188824 | Z42: 75 | AA42: =IF(V42>Z42,"Yes","No") -> No | AB42: =V42-Z42 -> -5.7553 | AC42: Yes | AD42: No | AE42: INTERNAL-0000 | AF42: =IF(AG42="Rejected",0,IF(R42="Corporate Card",0,V42)) -> 0 | AG42: Approved | AH42: 45670 | AI42: 45678 | AJ42: 45685 | AK42: =IF(AJ42="","",AJ42-AH42) -> 15
A43: EXP-00042 | B43: EMP-1204 | C43: Priya Nair | D43: Field Engineering | E43: Senior Field Engineer | F43: Tomas Kovac | G43: TRP-2025-109 | H43: Product Launch Event | I43: Paris | J43: France | K43: 45662 | L43: 45665 | M43: 45664 | N43: 2025-01 | O43: Meals - Lunch | P43: Individual meal | Q43: Sweetgreen | R43: Corporate Card | S43: EUR | T43: 21.24 | U43: 1.085 | V43: =T43*U43 -> 23.0454 | W43: 0.19 | X43: =V43-(V43/(1+W43)) -> 3.6795176 | Y43: =V43-X43 -> 19.365882 | Z43: 35 | AA43: =IF(V43>Z43,"Yes","No") -> No | AB43: =V43-Z43 -> -11.9546 | AC43: Yes | AD43: No | AE43: INTERNAL-0000 | AF43: =IF(AG43="Rejected",0,IF(R43="Corporate Card",0,V43)) -> 0 | AG43: Approved | AH43: 45670 | AI43: 45678 | AJ43: 45685 | AK43: =IF(AJ43="","",AJ43-AH43) -> 15
A44: EXP-00043 | B44: EMP-1229 | C44: Samuel Adeyemi | D44: Field Engineering | E44: Field Engineer | F44: Tomas Kovac | G44: TRP-2025-116 | H44: Client Meeting | I44: Sao Paulo | J44: Brazil | K44: 45661 | L44: 45668 | M44: 45664 | N44: 2025-01 | O44: Ground Transport - Taxi | P44: Airport / client site transfer | Q44: Grab | R44: Corporate Card | S44: BRL | T44: 276.84 | U44: 0.181 | V44: =T44*U44 -> 50.10804 | W44: 0.17 | X44: =V44-(V44/(1+W44)) -> 7.2806554 | Y44: =V44-X44 -> 42.827385 | Z44: 60 | AA44: =IF(V44>Z44,"Yes","No") -> No | AB44: =V44-Z44 -> -9.89196 | AC44: Yes | AD44: Yes | AE44: BLUEPEAK-7702 | AF44: =IF(AG44="Rejected",0,IF(R44="Corporate Card",0,V44)) -> 0 | AG44: Pending Approval | AH44: 45677 | AK44: =IF(AJ44="","",AJ44-AH44)
A45: EXP-00044 | B45: EMP-1229 | C45: Samuel Adeyemi | D45: Field Engineering | E45: Field Engineer | F45: Tomas Kovac | G45: TRP-2025-116 | H45: Client Meeting | I45: Sao Paulo | J45: Brazil | K45: 45661 | L45: 45668 | M45: 45664 | N45: 2025-01 | O45: Meals - Breakfast | P45: Individual meal | Q45: Cafe Nero | R45: Personal Card (Reimbursable) | S45: BRL | T45: 113.07 | U45: 0.181 | V45: =T45*U45 -> 20.46567 | W45: 0.17 | X45: =V45-(V45/(1+W45)) -> 2.9736444 | Y45: =V45-X45 -> 17.492026 | Z45: 25 | AA45: =IF(V45>Z45,"Yes","No") -> No | AB45: =V45-Z45 -> -4.53433 | AC45: Yes | AD45: Yes | AE45: BLUEPEAK-7702 | AF45: =IF(AG45="Rejected",0,IF(R45="Corporate Card",0,V45)) -> 20.46567 | AG45: Pending Approval | AH45: 45677 | AK45: =IF(AJ45="","",AJ45-AH45)
A46: EXP-00045 | B46: EMP-1229 | C46: Samuel Adeyemi | D46: Field Engineering | E46: Field Engineer | F46: Tomas Kovac | G46: TRP-2025-116 | H46: Client Meeting | I46: Sao Paulo | J46: Brazil | K46: 45661 | L46: 45668 | M46: 45664 | N46: 2025-01 | O46: Meals - Lunch | P46: Individual meal | Q46: Food Court | R46: Cash (Reimbursable) | S46: BRL | T46: 116.51 | U46: 0.181 | V46: =T46*U46 -> 21.08831 | W46: 0.17 | X46: =V46-(V46/(1+W46)) -> 3.0641134 | Y46: =V46-X46 -> 18.024197 | Z46: 35 | AA46: =IF(V46>Z46,"Yes","No") -> No | AB46: =V46-Z46 -> -13.91169 | AC46: Yes | AD46: Yes | AE46: BLUEPEAK-7702 | AF46: =IF(AG46="Rejected",0,IF(R46="Corporate Card",0,V46)) -> 21.08831 | AG46: Pending Approval | AH46: 45677 | AK46: =IF(AJ46="","",AJ46-AH46)
A47: EXP-00046 | B47: EMP-1204 | C47: Priya Nair | D47: Field Engineering | E47: Senior Field Engineer | F47: Tomas Kovac | G47: TRP-2025-109 | H47: Product Launch Event | I47: Paris | J47: France | K47: 45662 | L47: 45665 | M47: 45665 | N47: 2025-01 | O47: Meals - Breakfast | P47: Individual meal | Q47: Local Bakery | R47: Personal Card (Reimbursable) | S47: EUR | T47: 16.99 | U47: 1.085 | V47: =T47*U47 -> 18.43415 | W47: 0.19 | X47: =V47-(V47/(1+W47)) -> 2.9432676 | Y47: =V47-X47 -> 15.490882 | Z47: 25 | AA47: =IF(V47>Z47,"Yes","No") -> No | AB47: =V47-Z47 -> -6.56585 | AC47: Yes | AD47: No | AE47: INTERNAL-0000 | AF47: =IF(AG47="Rejected",0,IF(R47="Corporate Card",0,V47)) -> 18.43415 | AG47: Approved | AH47: 45670 | AI47: 45678 | AJ47: 45685 | AK47: =IF(AJ47="","",AJ47-AH47) -> 15
A48: EXP-00047 | B48: EMP-1204 | C48: Priya Nair | D48: Field Engineering | E48: Senior Field Engineer | F48: Tomas Kovac | G48: TRP-2025-109 | H48: Product Launch Event | I48: Paris | J48: France | K48: 45662 | L48: 45665 | M48: 45665 | N48: 2025-01 | O48: Meals - Dinner | P48: Party of 1 | Q48: Sakura Izakaya | R48: Corporate Card | S48: EUR | T48: 27.22 | U48: 1.085 | V48: =T48*U48 -> 29.5337 | W48: 0.19 | X48: =V48-(V48/(1+W48)) -> 4.7154647 | Y48: =V48-X48 -> 24.818235 | Z48: 75 | AA48: =IF(V48>Z48,"Yes","No") -> No | AB48: =V48-Z48 -> -45.4663 | AC48: Yes | AD48: No | AE48: INTERNAL-0000 | AF48: =IF(AG48="Rejected",0,IF(R48="Corporate Card",0,V48)) -> 0 | AG48: Approved | AH48: 45670 | AI48: 45678 | AJ48: 45685 | AK48: =IF(AJ48="","",AJ48-AH48) -> 15
A49: EXP-00048 | B49: EMP-1204 | C49: Priya Nair | D49: Field Engineering | E49: Senior Field Engineer | F49: Tomas Kovac | G49: TRP-2025-109 | H49: Product Launch Event | I49: Paris | J49: France | K49: 45662 | L49: 45665 | M49: 45665 | N49: 2025-01 | O49: Meals - Lunch | P49: Individual meal | Q49: Food Court | R49: Cash (Reimbursable) | S49: EUR | T49: 13.84 | U49: 1.085 | V49: =T49*U49 -> 15.0164 | W49: 0.19 | X49: =V49-(V49/(1+W49)) -> 2.3975765 | Y49: =V49-X49 -> 12.618824 | Z49: 35 | AA49: =IF(V49>Z49,"Yes","No") -> No | AB49: =V49-Z49 -> -19.9836 | AC49: Yes | AD49: No | AE49: INTERNAL-0000 | AF49: =IF(AG49="Rejected",0,IF(R49="Corporate Card",0,V49)) -> 15.0164 | AG49: Approved | AH49: 45670 | AI49: 45678 | AJ49: 45685 | AK49: =IF(AJ49="","",AJ49-AH49) -> 15
A50: EXP-00049 | B50: EMP-1229 | C50: Samuel Adeyemi | D50: Field Engineering | E50: Field Engineer | F50: Tomas Kovac | G50: TRP-2025-116 | H50: Client Meeting | I50: Sao Paulo | J50: Brazil | K50: 45661 | L50: 45668 | M50: 45665 | N50: 2025-01 | O50: Ground Transport - Taxi | P50: Airport / client site transfer | Q50: Lyft | R50: Corporate Card | S50: BRL | T50: 414.42 | U50: 0.181 | V50: =T50*U50 -> 75.01002 | W50: 0.17 | X50: =V50-(V50/(1+W50)) -> 10.898892 | Y50: =V50-X50 -> 64.111128 | Z50: 60 | AA50: =IF(V50>Z50,"Yes","No") -> Yes | AB50: =V50-Z50 -> 15.01002 | AC50: Yes | AD50: Yes | AE50: BLUEPEAK-7702 | AF50: =IF(AG50="Rejected",0,IF(R50="Corporate Card",0,V50)) -> 0 | AG50: Pending Approval | AH50: 45677 | AK50: =IF(AJ50="","",AJ50-AH50)
A51: EXP-00050 | B51: EMP-1229 | C51: Samuel Adeyemi | D51: Field Engineering | E51: Field Engineer | F51: Tomas Kovac | G51: TRP-2025-116 | H51: Client Meeting | I51: Sao Paulo | J51: Brazil | K51: 45661 | L51: 45668 | M51: 45665 | N51: 2025-01 | O51: Meals - Dinner | P51: Party of 2 | Q51: Spice Route | R51: Corporate Card | S51: BRL | T51: 171.11 | U51: 0.181 | V51: =T51*U51 -> 30.97091 | W51: 0.17 | X51: =V51-(V51/(1+W51)) -> 4.5000468 | Y51: =V51-X51 -> 26.470863 | Z51: 75 | AA51: =IF(V51>Z51,"Yes","No") -> No | AB51: =V51-Z51 -> -44.02909 | AC51: Yes | AD51: Yes | AE51: BLUEPEAK-7702 | AF51: =IF(AG51="Rejected",0,IF(R51="Corporate Card",0,V51)) -> 0 | AG51: Pending Approval | AH51: 45677 | AK51: =IF(AJ51="","",AJ51-AH51)
A52: EXP-00051 | B52: EMP-1229 | C52: Samuel Adeyemi | D52: Field Engineering | E52: Field Engineer | F52: Tomas Kovac | G52: TRP-2025-116 | H52: Client Meeting | I52: Sao Paulo | J52: Brazil | K52: 45661 | L52: 45668 | M52: 45666 | N52: 2025-01 | O52: Meals - Breakfast | P52: Individual meal | Q52: Starbucks | R52: Corporate Card | S52: BRL | T52: 73.86 | U52: 0.181 | V52: =T52*U52 -> 13.36866 | W52: 0.17 | X52: =V52-(V52/(1+W52)) -> 1.9424549 | Y52: =V52-X52 -> 11.426205 | Z52: 25 | AA52: =IF(V52>Z52,"Yes","No") -> No | AB52: =V52-Z52 -> -11.63134 | AC52: Yes | AD52: Yes | AE52: BLUEPEAK-7702 | AF52: =IF(AG52="Rejected",0,IF(R52="Corporate Card",0,V52)) -> 0 | AG52: Pending Approval | AH52: 45677 | AK52: =IF(AJ52="","",AJ52-AH52)
A53: EXP-00052 | B53: EMP-1229 | C53: Samuel Adeyemi | D53: Field Engineering | E53: Field Engineer | F53: Tomas Kovac | G53: TRP-2025-116 | H53: Client Meeting | I53: Sao Paulo | J53: Brazil | K53: 45661 | L53: 45668 | M53: 45666 | N53: 2025-01 | O53: Meals - Dinner | P53: Party of 1 | Q53: The Grill House | R53: Cash (Reimbursable) | S53: BRL | T53: 403.1 | U53: 0.181 | V53: =T53*U53 -> 72.9611 | W53: 0.17 | X53: =V53-(V53/(1+W53)) -> 10.601185 | Y53: =V53-X53 -> 62.359915 | Z53: 75 | AA53: =IF(V53>Z53,"Yes","No") -> No | AB53: =V53-Z53 -> -2.0389 | AC53: Yes | AD53: Yes | AE53: BLUEPEAK-7702 | AF53: =IF(AG53="Rejected",0,IF(R53="Corporate Card",0,V53)) -> 72.9611 | AG53: Pending Approval | AH53: 45677 | AK53: =IF(AJ53="","",AJ53-AH53)
A54: EXP-00053 | B54: EMP-1229 | C54: Samuel Adeyemi | D54: Field Engineering | E54: Field Engineer | F54: Tomas Kovac | G54: TRP-2025-116 | H54: Client Meeting | I54: Sao Paulo | J54: Brazil | K54: 45661 | L54: 45668 | M54: 45667 | N54: 2025-01 | O54: Meals - Breakfast | P54: Individual meal | Q54: Starbucks | R54: Corporate Card | S54: BRL | T54: 84.1 | U54: 0.181 | V54: =T54*U54 -> 15.2221 | W54: 0.17 | X54: =V54-(V54/(1+W54)) -> 2.2117581 | Y54: =V54-X54 -> 13.010342 | Z54: 25 | AA54: =IF(V54>Z54,"Yes","No") -> No | AB54: =V54-Z54 -> -9.7779 | AC54: Yes | AD54: Yes | AE54: BLUEPEAK-7702 | AF54: =IF(AG54="Rejected",0,IF(R54="Corporate Card",0,V54)) -> 0 | AG54: Pending Approval | AH54: 45677 | AK54: =IF(AJ54="","",AJ54-AH54)
A55: EXP-00054 | B55: EMP-1229 | C55: Samuel Adeyemi | D55: Field Engineering | E55: Field Engineer | F55: Tomas Kovac | G55: TRP-2025-116 | H55: Client Meeting | I55: Sao Paulo | J55: Brazil | K55: 45661 | L55: 45668 | M55: 45667 | N55: 2025-01 | O55: Meals - Dinner | P55: Party of 3 | Q55: Brasserie Lyon | R55: Corporate Card | S55: BRL | T55: 217.22 | U55: 0.181 | V55: =T55*U55 -> 39.31682 | W55: 0.17 | X55: =V55-(V55/(1+W55)) -> 5.7127003 | Y55: =V55-X55 -> 33.60412 | Z55: 75 | AA55: =IF(V55>Z55,"Yes","No") -> No | AB55: =V55-Z55 -> -35.68318 | AC55: Yes | AD55: Yes | AE55: BLUEPEAK-7702 | AF55: =IF(AG55="Rejected",0,IF(R55="Corporate Card",0,V55)) -> 0 | AG55: Pending Approval | AH55: 45677 | AK55: =IF(AJ55="","",AJ55-AH55)
A56: EXP-00055 | B56: EMP-1229 | C56: Samuel Adeyemi | D56: Field Engineering | E56: Field Engineer | F56: Tomas Kovac | G56: TRP-2025-116 | H56: Client Meeting | I56: Sao Paulo | J56: Brazil | K56: 45661 | L56: 45668 | M56: 45667 | N56: 2025-01 | O56: Meals - Lunch | P56: Individual meal | Q56: Sweetgreen | R56: Cash (Reimbursable) | S56: BRL | T56: 96.72 | U56: 0.181 | V56: =T56*U56 -> 17.50632 | W56: 0.17 | X56: =V56-(V56/(1+W56)) -> 2.5436533 | Y56: =V56-X56 -> 14.962667 | Z56: 35 | AA56: =IF(V56>Z56,"Yes","No") -> No | AB56: =V56-Z56 -> -17.49368 | AC56: Yes | AD56: Yes | AE56: BLUEPEAK-7702 | AF56: =IF(AG56="Rejected",0,IF(R56="Corporate Card",0,V56)) -> 17.50632 | AG56: Pending Approval | AH56: 45677 | AK56: =IF(AJ56="","",AJ56-AH56)
A57: EXP-00056 | B57: EMP-1523 | C57: Laura Bianchi | D57: Customer Success | E57: CS Specialist | F57: Sneha Iyer | G57: TRP-2025-117 | H57: Trade Show / Conference | I57: Tokyo | J57: Japan | K57: 45667 | L57: 45672 | M57: 45667 | N57: 2025-01 | O57: Airfare | P57: Round trip HQ - Tokyo, economy | Q57: British Airways | R57: Personal Card (Reimbursable) | S57: JPY | T57: 182829 | U57: 0.00655 | V57: =T57*U57 -> 1197.53 | W57: 0 | X57: =V57-(V57/(1+W57)) -> 0 | Y57: =V57-X57 -> 1197.53 | Z57: 1400 | AA57: =IF(V57>Z57,"Yes","No") -> No | AB57: =V57-Z57 -> -202.47005 | AC57: Yes | AD57: Yes | AE57: ORBITAL-8834 | AF57: =IF(AG57="Rejected",0,IF(R57="Corporate Card",0,V57)) -> 1197.53 | AG57: Approved | AH57: 45680 | AI57: 45687 | AJ57: 45691 | AK57: =IF(AJ57="","",AJ57-AH57) -> 11
A58: EXP-00057 | B58: EMP-1523 | C58: Laura Bianchi | D58: Customer Success | E58: CS Specialist | F58: Sneha Iyer | G58: TRP-2025-117 | H58: Trade Show / Conference | I58: Tokyo | J58: Japan | K58: 45667 | L58: 45672 | M58: 45667 | N58: 2025-01 | O58: Conference / Event Fee | P58: Delegate registration | Q58: SensorTech Summit | R58: Corporate Card | S58: JPY | T58: 182172 | U58: 0.00655 | V58: =T58*U58 -> 1193.2266 | W58: 0 | X58: =V58-(V58/(1+W58)) -> 0 | Y58: =V58-X58 -> 1193.2266 | Z58: 1200 | AA58: =IF(V58>Z58,"Yes","No") -> No | AB58: =V58-Z58 -> -6.7734 | AC58: Yes | AD58: Yes | AE58: ORBITAL-8834 | AF58: =IF(AG58="Rejected",0,IF(R58="Corporate Card",0,V58)) -> 0 | AG58: Approved | AH58: 45680 | AI58: 45687 | AJ58: 45691 | AK58: =IF(AJ58="","",AJ58-AH58) -> 11
A59: EXP-00058 | B59: EMP-1523 | C59: Laura Bianchi | D59: Customer Success | E59: CS Specialist | F59: Sneha Iyer | G59: TRP-2025-117 | H59: Trade Show / Conference | I59: Tokyo | J59: Japan | K59: 45667 | L59: 45672 | M59: 45667 | N59: 2025-01 | O59: Ground Transport - Taxi | P59: Airport / client site transfer | Q59: Ola Cabs | R59: Corporate Card | S59: JPY | T59: 4118 | U59: 0.00655 | V59: =T59*U59 -> 26.9729 | W59: 0.1 | X59: =V59-(V59/(1+W59)) -> 2.4520818 | Y59: =V59-X59 -> 24.520818 | Z59: 60 | AA59: =IF(V59>Z59,"Yes","No") -> No | AB59: =V59-Z59 -> -33.0271 | AC59: Yes | AD59: Yes | AE59: ORBITAL-8834 | AF59: =IF(AG59="Rejected",0,IF(R59="Corporate Card",0,V59)) -> 0 | AG59: Approved | AH59: 45680 | AI59: 45687 | AJ59: 45691 | AK59: =IF(AJ59="","",AJ59-AH59) -> 11
A60: EXP-00059 | B60: EMP-1523 | C60: Laura Bianchi | D60: Customer Success | E60: CS Specialist | F60: Sneha Iyer | G60: TRP-2025-117 | H60: Trade Show / Conference | I60: Tokyo | J60: Japan | K60: 45667 | L60: 45672 | M60: 45667 | N60: 2025-01 | O60: Meals - Breakfast | P60: Individual meal | Q60: Starbucks | R60: Cash (Reimbursable) | S60: JPY | T60: 1501 | U60: 0.00655 | V60: =T60*U60 -> 9.83155 | W60: 0.1 | X60: =V60-(V60/(1+W60)) -> 0.89377727 | Y60: =V60-X60 -> 8.9377727 | Z60: 25 | AA60: =IF(V60>Z60,"Yes","No") -> No | AB60: =V60-Z60 -> -15.16845 | AC60: Yes | AD60: Yes | AE60: ORBITAL-8834 | AF60: =IF(AG60="Rejected",0,IF(R60="Corporate Card",0,V60)) -> 9.83155 | AG60: Approved | AH60: 45680 | AI60: 45687 | AJ60: 45691 | AK60: =IF(AJ60="","",AJ60-AH60) -> 11
A61: EXP-00060 | B61: EMP-1523 | C61: Laura Bianchi | D61: Customer Success | E61: CS Specialist | F61: Sneha Iyer | G61: TRP-2025-117 | H61: Trade Show / Conference | I61: Tokyo | J61: Japan | K61: 45667 | L61: 45672 | M61: 45667 | N61: 2025-01 | O61: Meals - Dinner | P61: Party of 4 | Q61: Osteria Vela | R61: Cash (Reimbursable) | S61: JPY | T61: 6614 | U61: 0.00655 | V61: =T61*U61 -> 43.3217 | W61: 0.1 | X61: =V61-(V61/(1+W61)) -> 3.9383364 | Y61: =V61-X61 -> 39.383364 | Z61: 75 | AA61: =IF(V61>Z61,"Yes","No") -> No | AB61: =V61-Z61 -> -31.6783 | AC61: No | AD61: Yes | AE61: ORBITAL-8834 | AF61: =IF(AG61="Rejected",0,IF(R61="Corporate Card",0,V61)) -> 43.3217 | AG61: Approved | AH61: 45680 | AI61: 45687 | AJ61: 45691 | AK61: =IF(AJ61="","",AJ61-AH61) -> 11
A62: EXP-00061 | B62: EMP-1523 | C62: Laura Bianchi | D62: Customer Success | E62: CS Specialist | F62: Sneha Iyer | G62: TRP-2025-117 | H62: Trade Show / Conference | I62: Tokyo | J62: Japan | K62: 45667 | L62: 45672 | M62: 45667 | N62: 2025-01 | O62: Meals - Lunch | P62: Individual meal | Q62: Pret A Manger | R62: Corporate Card | S62: JPY | T62: 3218 | U62: 0.00655 | V62: =T62*U62 -> 21.0779 | W62: 0.1 | X62: =V62-(V62/(1+W62)) -> 1.9161727 | Y62: =V62-X62 -> 19.161727 | Z62: 35 | AA62: =IF(V62>Z62,"Yes","No") -> No | AB62: =V62-Z62 -> -13.9221 | AC62: Yes | AD62: Yes | AE62: ORBITAL-8834 | AF62: =IF(AG62="Rejected",0,IF(R62="Corporate Card",0,V62)) -> 0 | AG62: Approved | AH62: 45680 | AI62: 45687 | AJ62: 45691 | AK62: =IF(AJ62="","",AJ62-AH62) -> 11
A63: EXP-00062 | B63: EMP-1229 | C63: Samuel Adeyemi | D63: Field Engineering | E63: Field Engineer | F63: Tomas Kovac | G63: TRP-2025-116 | H63: Client Meeting | I63: Sao Paulo | J63: Brazil | K63: 45661 | L63: 45668 | M63: 45668 | N63: 2025-01 | O63: Ground Transport - Taxi | P63: Airport / client site transfer | Q63: Lyft | R63: Corporate Card | S63: BRL | T63: 267.27 | U63: 0.181 | V63: =T63*U63 -> 48.37587 | W63: 0.17 | X63: =V63-(V63/(1+W63)) -> 7.0289726 | Y63: =V63-X63 -> 41.346897 | Z63: 60 | AA63: =IF(V63>Z63,"Yes","No") -> No | AB63: =V63-Z63 -> -11.62413 | AC63: Yes | AD63: Yes | AE63: BLUEPEAK-7702 | AF63: =IF(AG63="Rejected",0,IF(R63="Corporate Card",0,V63)) -> 0 | AG63: Pending Approval | AH63: 45677 | AK63: =IF(AJ63="","",AJ63-AH63)
A64: EXP-00063 | B64: EMP-1229 | C64: Samuel Adeyemi | D64: Field Engineering | E64: Field Engineer | F64: Tomas Kovac | G64: TRP-2025-116 | H64: Client Meeting | I64: Sao Paulo | J64: Brazil | K64: 45661 | L64: 45668 | M64: 45668 | N64: 2025-01 | O64: Meals - Dinner | P64: Party of 4 | Q64: The Grill House | R64: Personal Card (Reimbursable) | S64: BRL | T64: 256.42 | U64: 0.181 | V64: =T64*U64 -> 46.41202 | W64: 0.17 | X64: =V64-(V64/(1+W64)) -> 6.7436268 | Y64: =V64-X64 -> 39.668393 | Z64: 75 | AA64: =IF(V64>Z64,"Yes","No") -> No | AB64: =V64-Z64 -> -28.58798 | AC64: Yes | AD64: Yes | AE64: BLUEPEAK-7702 | AF64: =IF(AG64="Rejected",0,IF(R64="Corporate Card",0,V64)) -> 46.41202 | AG64: Pending Approval | AH64: 45677 | AK64: =IF(AJ64="","",AJ64-AH64)
A65: EXP-00064 | B65: EMP-1229 | C65: Samuel Adeyemi | D65: Field Engineering | E65: Field Engineer | F65: Tomas Kovac | G65: TRP-2025-116 | H65: Client Meeting | I65: Sao Paulo | J65: Brazil | K65: 45661 | L65: 45668 | M65: 45668 | N65: 2025-01 | O65: Meals - Lunch | P65: Individual meal | Q65: Local Bistro | R65: Corporate Card | S65: BRL | T65: 179.15 | U65: 0.181 | V65: =T65*U65 -> 32.42615 | W65: 0.17 | X65: =V65-(V65/(1+W65)) -> 4.7114919 | Y65: =V65-X65 -> 27.714658 | Z65: 35 | AA65: =IF(V65>Z65,"Yes","No") -> No | AB65: =V65-Z65 -> -2.57385 | AC65: Yes | AD65: Yes | AE65: BLUEPEAK-7702 | AF65: =IF(AG65="Rejected",0,IF(R65="Corporate Card",0,V65)) -> 0 | AG65: Pending Approval | AH65: 45677 | AK65: =IF(AJ65="","",AJ65-AH65)
A66: EXP-00065 | B66: EMP-1523 | C66: Laura Bianchi | D66: Customer Success | E66: CS Specialist | F66: Sneha Iyer | G66: TRP-2025-117 | H66: Trade Show / Conference | I66: Tokyo | J66: Japan | K66: 45667 | L66: 45672 | M66: 45668 | N66: 2025-01 | O66: Ground Transport - Taxi | P66: Airport / client site transfer | Q66: Ola Cabs | R66: Corporate Card | S66: JPY | T66: 5910 | U66: 0.00655 | V66: =T66*U66 -> 38.7105 | W66: 0.1 | X66: =V66-(V66/(1+W66)) -> 3.5191364 | Y66: =V66-X66 -> 35.191364 | Z66: 60 | AA66: =IF(V66>Z66,"Yes","No") -> No | AB66: =V66-Z66 -> -21.2895 | AC66: Yes | AD66: Yes | AE66: ORBITAL-8834 | AF66: =IF(AG66="Rejected",0,IF(R66="Corporate Card",0,V66)) -> 0 | AG66: Approved | AH66: 45680 | AI66: 45687 | AJ66: 45691 | AK66: =IF(AJ66="","",AJ66-AH66) -> 11
A67: EXP-00066 | B67: EMP-1523 | C67: Laura Bianchi | D67: Customer Success | E67: CS Specialist | F67: Sneha Iyer | G67: TRP-2025-117 | H67: Trade Show / Conference | I67: Tokyo | J67: Japan | K67: 45667 | L67: 45672 | M67: 45668 | N67: 2025-01 | O67: Hotel / Lodging | P67: 5 night(s) @ standard rate | Q67: Novotel | R67: Corporate Card | S67: JPY | T67: 149348 | U67: 0.00655 | V67: =T67*U67 -> 978.2294 | W67: 0.1 | X67: =V67-(V67/(1+W67)) -> 88.929945 | Y67: =V67-X67 -> 889.29945 | Z67: 1400 | AA67: =IF(V67>Z67,"Yes","No") -> No | AB67: =V67-Z67 -> -421.7706 | AC67: Yes | AD67: Yes | AE67: ORBITAL-8834 | AF67: =IF(AG67="Rejected",0,IF(R67="Corporate Card",0,V67)) -> 0 | AG67: Approved | AH67: 45680 | AI67: 45687 | AJ67: 45691 | AK67: =IF(AJ67="","",AJ67-AH67) -> 11
A68: EXP-00067 | B68: EMP-1523 | C68: Laura Bianchi | D68: Customer Success | E68: CS Specialist | F68: Sneha Iyer | G68: TRP-2025-117 | H68: Trade Show / Conference | I68: Tokyo | J68: Japan | K68: 45667 | L68: 45672 | M68: 45668 | N68: 2025-01 | O68: Meals - Breakfast | P68: Individual meal | Q68: Cafe Nero | R68: Cash (Reimbursable) | S68: JPY | T68: 4616 | U68: 0.00655 | V68: =T68*U68 -> 30.2348 | W68: 0.1 | X68: =V68-(V68/(1+W68)) -> 2.7486182 | Y68: =V68-X68 -> 27.486182 | Z68: 25 | AA68: =IF(V68>Z68,"Yes","No") -> Yes | AB68: =V68-Z68 -> 5.2348 | AC68: Yes | AD68: Yes | AE68: ORBITAL-8834 | AF68: =IF(AG68="Rejected",0,IF(R68="Corporate Card",0,V68)) -> 30.2348 | AG68: Approved | AH68: 45680 | AI68: 45687 | AJ68: 45691 | AK68: =IF(AJ68="","",AJ68-AH68) -> 11
A69: EXP-00068 | B69: EMP-1523 | C69: Laura Bianchi | D69: Customer Success | E69: CS Specialist | F69: Sneha Iyer | G69: TRP-2025-117 | H69: Trade Show / Conference | I69: Tokyo | J69: Japan | K69: 45667 | L69: 45672 | M69: 45668 | N69: 2025-01 | O69: Meals - Dinner | P69: Party of 1 | Q69: Sakura Izakaya | R69: Corporate Card | S69: JPY | T69: 6703 | U69: 0.00655 | V69: =T69*U69 -> 43.90465 | W69: 0.1 | X69: =V69-(V69/(1+W69)) -> 3.9913318 | Y69: =V69-X69 -> 39.913318 | Z69: 75 | AA69: =IF(V69>Z69,"Yes","No") -> No | AB69: =V69-Z69 -> -31.09535 | AC69: Yes | AD69: Yes | AE69: ORBITAL-8834 | AF69: =IF(AG69="Rejected",0,IF(R69="Corporate Card",0,V69)) -> 0 | AG69: Approved | AH69: 45680 | AI69: 45687 | AJ69: 45691 | AK69: =IF(AJ69="","",AJ69-AH69) -> 11
A70: EXP-00069 | B70: EMP-1523 | C70: Laura Bianchi | D70: Customer Success | E70: CS Specialist | F70: Sneha Iyer | G70: TRP-2025-117 | H70: Trade Show / Conference | I70: Tokyo | J70: Japan | K70: 45667 | L70: 45672 | M70: 45668 | N70: 2025-01 | O70: Meals - Lunch | P70: Individual meal | Q70: Local Bistro | R70: Personal Card (Reimbursable) | S70: JPY | T70: 4059 | U70: 0.00655 | V70: =T70*U70 -> 26.58645 | W70: 0.1 | X70: =V70-(V70/(1+W70)) -> 2.41695 | Y70: =V70-X70 -> 24.1695 | Z70: 35 | AA70: =IF(V70>Z70,"Yes","No") -> No | AB70: =V70-Z70 -> -8.41355 | AC70: Yes | AD70: Yes | AE70: ORBITAL-8834 | AF70: =IF(AG70="Rejected",0,IF(R70="Corporate Card",0,V70)) -> 26.58645 | AG70: Approved | AH70: 45680 | AI70: 45687 | AJ70: 45691 | AK70: =IF(AJ70="","",AJ70-AH70) -> 11
A71: EXP-00070 | B71: EMP-1523 | C71: Laura Bianchi | D71: Customer Success | E71: CS Specialist | F71: Sneha Iyer | G71: TRP-2025-117 | H71: Trade Show / Conference | I71: Tokyo | J71: Japan | K71: 45667 | L71: 45672 | M71: 45669 | N71: 2025-01 | O71: Ground Transport - Taxi | P71: Airport / client site transfer | Q71: Lyft | R71: Corporate Card | S71: JPY | T71: 4054 | U71: 0.00655 | V71: =T71*U71 -> 26.5537 | W71: 0.1 | X71: =V71-(V71/(1+W71)) -> 2.4139727 | Y71: =V71-X71 -> 24.139727 | Z71: 60 | AA71: =IF(V71>Z71,"Yes","No") -> No | AB71: =V71-Z71 -> -33.4463 | AC71: Yes | AD71: Yes | AE71: ORBITAL-8834 | AF71: =IF(AG71="Rejected",0,IF(R71="Corporate Card",0,V71)) -> 0 | AG71: Approved | AH71: 45680 | AI71: 45687 | AJ71: 45691 | AK71: =IF(AJ71="","",AJ71-AH71) -> 11
A72: EXP-00071 | B72: EMP-1523 | C72: Laura Bianchi | D72: Customer Success | E72: CS Specialist | F72: Sneha Iyer | G72: TRP-2025-117 | H72: Trade Show / Conference | I72: Tokyo | J72: Japan | K72: 45667 | L72: 45672 | M72: 45669 | N72: 2025-01 | O72: Meals - Breakfast | P72: Individual meal | Q72: Hotel Restaurant | R72: Corporate Card | S72: JPY | T72: 4333 | U72: 0.00655 | V72: =T72*U72 -> 28.38115 | W72: 0.1 | X72: =V72-(V72/(1+W72)) -> 2.5801045 | Y72: =V72-X72 -> 25.801045 | Z72: 25 | AA72: =IF(V72>Z72,"Yes","No") -> Yes | AB72: =V72-Z72 -> 3.38115 | AC72: Yes | AD72: Yes | AE72: ORBITAL-8834 | AF72: =IF(AG72="Rejected",0,IF(R72="Corporate Card",0,V72)) -> 0 | AG72: Approved | AH72: 45680 | AI72: 45687 | AJ72: 45691 | AK72: =IF(AJ72="","",AJ72-AH72) -> 11
A73: EXP-00072 | B73: EMP-1523 | C73: Laura Bianchi | D73: Customer Success | E73: CS Specialist | F73: Sneha Iyer | G73: TRP-2025-117 | H73: Trade Show / Conference | I73: Tokyo | J73: Japan | K73: 45667 | L73: 45672 | M73: 45669 | N73: 2025-01 | O73: Meals - Dinner | P73: Party of 2 | Q73: Sakura Izakaya | R73: Corporate Card | S73: JPY | T73: 10357 | U73: 0.00655 | V73: =T73*U73 -> 67.83835 | W73: 0.1 | X73: =V73-(V73/(1+W73)) -> 6.1671227 | Y73: =V73-X73 -> 61.671227 | Z73: 75 | AA73: =IF(V73>Z73,"Yes","No") -> No | AB73: =V73-Z73 -> -7.16165 | AC73: Yes | AD73: Yes | AE73: ORBITAL-8834 | AF73: =IF(AG73="Rejected",0,IF(R73="Corporate Card",0,V73)) -> 0 | AG73: Approved | AH73: 45680 | AI73: 45687 | AJ73: 45691 | AK73: =IF(AJ73="","",AJ73-AH73) -> 11
A74: EXP-00073 | B74: EMP-1523 | C74: Laura Bianchi | D74: Customer Success | E74: CS Specialist | F74: Sneha Iyer | G74: TRP-2025-117 | H74: Trade Show / Conference | I74: Tokyo | J74: Japan | K74: 45667 | L74: 45672 | M74: 45669 | N74: 2025-01 | O74: Meals - Lunch | P74: Individual meal | Q74: Pret A Manger | R74: Corporate Card | S74: JPY | T74: 2146 | U74: 0.00655 | V74: =T74*U74 -> 14.0563 | W74: 0.1 | X74: =V74-(V74/(1+W74)) -> 1.2778455 | Y74: =V74-X74 -> 12.778455 | Z74: 35 | AA74: =IF(V74>Z74,"Yes","No") -> No | AB74: =V74-Z74 -> -20.9437 | AC74: Yes | AD74: Yes | AE74: ORBITAL-8834 | AF74: =IF(AG74="Rejected",0,IF(R74="Corporate Card",0,V74)) -> 0 | AG74: Approved | AH74: 45680 | AI74: 45687 | AJ74: 45691 | AK74: =IF(AJ74="","",AJ74-AH74) -> 11
A75: EXP-00074 | B75: EMP-1523 | C75: Laura Bianchi | D75: Customer Success | E75: CS Specialist | F75: Sneha Iyer | G75: TRP-2025-117 | H75: Trade Show / Conference | I75: Tokyo | J75: Japan | K75: 45667 | L75: 45672 | M75: 45670 | N75: 2025-01 | O75: Ground Transport - Taxi | P75: Airport / client site transfer | Q75: Ola Cabs | R75: Cash (Reimbursable) | S75: JPY | T75: 4164 | U75: 0.00655 | V75: =T75*U75 -> 27.2742 | W75: 0.1 | X75: =V75-(V75/(1+W75)) -> 2.4794727 | Y75: =V75-X75 -> 24.794727 | Z75: 60 | AA75: =IF(V75>Z75,"Yes","No") -> No | AB75: =V75-Z75 -> -32.7258 | AC75: Yes | AD75: Yes | AE75: ORBITAL-8834 | AF75: =IF(AG75="Rejected",0,IF(R75="Corporate Card",0,V75)) -> 27.2742 | AG75: Approved | AH75: 45680 | AI75: 45687 | AJ75: 45691 | AK75: =IF(AJ75="","",AJ75-AH75) -> 11
A76: EXP-00075 | B76: EMP-1523 | C76: Laura Bianchi | D76: Customer Success | E76: CS Specialist | F76: Sneha Iyer | G76: TRP-2025-117 | H76: Trade Show / Conference | I76: Tokyo | J76: Japan | K76: 45667 | L76: 45672 | M76: 45670 | N76: 2025-01 | O76: Laundry | P76: Hotel laundry | Q76: Hotel Laundry Service | R76: Corporate Card | S76: JPY | T76: 3299 | U76: 0.00655 | V76: =T76*U76 -> 21.60845 | W76: 0.1 | X76: =V76-(V76/(1+W76)) -> 1.9644045 | Y76: =V76-X76 -> 19.644045 | Z76: 30 | AA76: =IF(V76>Z76,"Yes","No") -> No | AB76: =V76-Z76 -> -8.39155 | AC76: Yes | AD76: Yes | AE76: ORBITAL-8834 | AF76: =IF(AG76="Rejected",0,IF(R76="Corporate Card",0,V76)) -> 0 | AG76: Approved | AH76: 45680 | AI76: 45687 | AJ76: 45691 | AK76: =IF(AJ76="","",AJ76-AH76) -> 11
A77: EXP-00076 | B77: EMP-1523 | C77: Laura Bianchi | D77: Customer Success | E77: CS Specialist | F77: Sneha Iyer | G77: TRP-2025-117 | H77: Trade Show / Conference | I77: Tokyo | J77: Japan | K77: 45667 | L77: 45672 | M77: 45670 | N77: 2025-01 | O77: Meals - Dinner | P77: Party of 4 | Q77: Spice Route | R77: Cash (Reimbursable) | S77: JPY | T77: 6924 | U77: 0.00655 | V77: =T77*U77 -> 45.3522 | W77: 0.1 | X77: =V77-(V77/(1+W77)) -> 4.1229273 | Y77: =V77-X77 -> 41.229273 | Z77: 75 | AA77: =IF(V77>Z77,"Yes","No") -> No | AB77: =V77-Z77 -> -29.6478 | AC77: Yes | AD77: Yes | AE77: ORBITAL-8834 | AF77: =IF(AG77="Rejected",0,IF(R77="Corporate Card",0,V77)) -> 45.3522 | AG77: Approved | AH77: 45680 | AI77: 45687 | AJ77: 45691 | AK77: =IF(AJ77="","",AJ77-AH77) -> 11
... A293: EXP-00292 | B293: EMP-1077 | C293: Marcus Bell | D293: Sales | E293: VP Sales | F293: Diane Okafor | G293: TRP-2025-039 | H293: Trade Show / Conference | I293: Tokyo | J293: Japan | K293: 45680 | L293: 45684 | M293: 45684 | N293: 2025-01 | O293: Meals - Lunch | P293: Individual meal | Q293: Local Bistro | R293: Corporate Card | S293: JPY | T293: 2208 | U293: 0.00655 | V293: =T293*U293 -> 14.4624 | W293: 0.1 | X293: =V293-(V293/(1+W293)) -> 1.3147636 | Y293: =V293-X293 -> 13.147636 | Z293: 35 | AA293: =IF(V293>Z293,"Yes","No") -> No | AB293: =V293-Z293 -> -20.5376 | AC293: Yes | AD293: Yes | AE293: NORDIC-1180 | AF293: =IF(AG293="Rejected",0,IF(R293="Corporate Card",0,V293)) -> 0 | AG293: Approved | AH293: 45695 | AI293: 45696 | AJ293: 45708 | AK293: =IF(AJ293="","",AJ293-AH293) -> 13
A294: EXP-00293 | B294: EMP-1502 | C294: Sneha Iyer | D294: Customer Success | E294: CS Manager | F294: Paul Nkemelu | G294: TRP-2025-081 | H294: Supplier Audit | I294: San Jose | J294: United States | K294: 45684 | L294: 45688 | M294: 45684 | N294: 2025-01 | O294: Airfare | P294: Round trip HQ - San Jose, economy | Q294: Delta Air Lines | R294: Cash (Reimbursable) | S294: USD | T294: 884.95 | U294: 1 | V294: =T294*U294 -> 884.95 | W294: 0 | X294: =V294-(V294/(1+W294)) -> 0 | Y294: =V294-X294 -> 884.95 | Z294: 1400 | AA294: =IF(V294>Z294,"Yes","No") -> No | AB294: =V294-Z294 -> -515.05 | AC294: Yes | AD294: No | AE294: BLUEPEAK-7702 | AF294: =IF(AG294="Rejected",0,IF(R294="Corporate Card",0,V294)) -> 884.95 | AG294: Pending Approval | AH294: 45698 | AK294: =IF(AJ294="","",AJ294-AH294)
A295: EXP-00294 | B295: EMP-1502 | C295: Sneha Iyer | D295: Customer Success | E295: CS Manager | F295: Paul Nkemelu | G295: TRP-2025-081 | H295: Supplier Audit | I295: San Jose | J295: United States | K295: 45684 | L295: 45688 | M295: 45684 | N295: 2025-01 | O295: Baggage & Excess Fees | P295: Checked demo equipment | Q295: Emirates | R295: Corporate Card | S295: USD | T295: 68.41 | U295: 1 | V295: =T295*U295 -> 68.41 | W295: 0 | X295: =V295-(V295/(1+W295)) -> 0 | Y295: =V295-X295 -> 68.41 | Z295: 120 | AA295: =IF(V295>Z295,"Yes","No") -> No | AB295: =V295-Z295 -> -51.59 | AC295: Yes | AD295: No | AE295: BLUEPEAK-7702 | AF295: =IF(AG295="Rejected",0,IF(R295="Corporate Card",0,V295)) -> 0 | AG295: Pending Approval | AH295: 45698 | AK295: =IF(AJ295="","",AJ295-AH295)
A296: EXP-00295 | B296: EMP-1502 | C296: Sneha Iyer | D296: Customer Success | E296: CS Manager | F296: Paul Nkemelu | G296: TRP-2025-081 | H296: Supplier Audit | I296: San Jose | J296: United States | K296: 45684 | L296: 45688 | M296: 45684 | N296: 2025-01 | O296: Meals - Breakfast | P296: Individual meal | Q296: Local Bakery | R296: Personal Card (Reimbursable) | S296: USD | T296: 27.43 | U296: 1 | V296: =T296*U296 -> 27.43 | W296: 0 | X296: =V296-(V296/(1+W296)) -> 0 | Y296: =V296-X296 -> 27.43 | Z296: 25 | AA296: =IF(V296>Z296,"Yes","No") -> Yes | AB296: =V296-Z296 -> 2.43 | AC296: No | AD296: No | AE296: BLUEPEAK-7702 | AF296: =IF(AG296="Rejected",0,IF(R296="Corporate Card",0,V296)) -> 27.43 | AG296: Pending Approval | AH296: 45698 | AK296: =IF(AJ296="","",AJ296-AH296)
A297: EXP-00296 | B297: EMP-1502 | C297: Sneha Iyer | D297: Customer Success | E297: CS Manager | F297: Paul Nkemelu | G297: TRP-2025-081 | H297: Supplier Audit | I297: San Jose | J297: United States | K297: 45684 | L297: 45688 | M297: 45684 | N297: 2025-01 | O297: Meals - Lunch | P297: Individual meal | Q297: Pret A Manger | R297: Personal Card (Reimbursable) | S297: USD | T297: 16.35 | U297: 1 | V297: =T297*U297 -> 16.35 | W297: 0 | X297: =V297-(V297/(1+W297)) -> 0 | Y297: =V297-X297 -> 16.35 | Z297: 35 | AA297: =IF(V297>Z297,"Yes","No") -> No | AB297: =V297-Z297 -> -18.65 | AC297: Yes | AD297: No | AE297: BLUEPEAK-7702 | AF297: =IF(AG297="Rejected",0,IF(R297="Corporate Card",0,V297)) -> 16.35 | AG297: Pending Approval | AH297: 45698 | AK297: =IF(AJ297="","",AJ297-AH297)
A298: EXP-00297 | B298: EMP-1236 | C298: Hannah Weiss | D298: Field Engineering | E298: Field Engineer | F298: Tomas Kovac | G298: TRP-2025-091 | H298: Trade Show / Conference | I298: Singapore | J298: Singapore | K298: 45682 | L298: 45684 | M298: 45684 | N298: 2025-01 | O298: Ground Transport - Taxi | P298: Airport / client site transfer | Q298: Grab | R298: Personal Card (Reimbursable) | S298: SGD | T298: 59.47 | U298: 0.743 | V298: =T298*U298 -> 44.18621 | W298: 0.09 | X298: =V298-(V298/(1+W298)) -> 3.6484027 | Y298: =V298-X298 -> 40.537807 | Z298: 60 | AA298: =IF(V298>Z298,"Yes","No") -> No | AB298: =V298-Z298 -> -15.81379 | AC298: Yes | AD298: Yes | AE298: ORBITAL-8834 | AF298: =IF(AG298="Rejected",0,IF(R298="Corporate Card",0,V298)) -> 44.18621 | AG298: Approved | AH298: 45694 | AI298: 45697 | AJ298: 45707 | AK298: =IF(AJ298="","",AJ298-AH298) -> 13
A299: EXP-00298 | B299: EMP-1236 | C299: Hannah Weiss | D299: Field Engineering | E299: Field Engineer | F299: Tomas Kovac | G299: TRP-2025-091 | H299: Trade Show / Conference | I299: Singapore | J299: Singapore | K299: 45682 | L299: 45684 | M299: 45684 | N299: 2025-01 | O299: Meals - Dinner | P299: Party of 1 | Q299: The Grill House | R299: Corporate Card | S299: SGD | T299: 45.95 | U299: 0.743 | V299: =T299*U299 -> 34.14085 | W299: 0.09 | X299: =V299-(V299/(1+W299)) -> 2.8189693 | Y299: =V299-X299 -> 31.321881 | Z299: 75 | AA299: =IF(V299>Z299,"Yes","No") -> No | AB299: =V299-Z299 -> -40.85915 | AC299: Yes | AD299: Yes | AE299: ORBITAL-8834 | AF299: =IF(AG299="Rejected",0,IF(R299="Corporate Card",0,V299)) -> 0 | AG299: Approved | AH299: 45694 | AI299: 45697 | AJ299: 45707 | AK299: =IF(AJ299="","",AJ299-AH299) -> 13
A300: EXP-00299 | B300: EMP-1409 | C300: Grace Lin | D300: Marketing | E300: Head of Marketing | F300: Diane Okafor | G300: TRP-2025-096 | H300: Supplier Audit | I300: Austin | J300: United States | K300: 45677 | L300: 45684 | M300: 45684 | N300: 2025-01 | O300: Meals - Breakfast | P300: Individual meal | Q300: Starbucks | R300: Cash (Reimbursable) | S300: USD | T300: 9.9 | U300: 1 | V300: =T300*U300 -> 9.9 | W300: 0 | X300: =V300-(V300/(1+W300)) -> 0 | Y300: =V300-X300 -> 9.9 | Z300: 25 | AA300: =IF(V300>Z300,"Yes","No") -> No | AB300: =V300-Z300 -> -15.1 | AC300: Yes | AD300: Yes | AE300: MERIDIAN-4415 | AF300: =IF(AG300="Rejected",0,IF(R300="Corporate Card",0,V300)) -> 9.9 | AG300: Approved | AH300: 45696 | AI300: 45702 | AJ300: 45712 | AK300: =IF(AJ300="","",AJ300-AH300) -> 16
A301: EXP-00300 | B301: EMP-1409 | C301: Grace Lin | D301: Marketing | E301: Head of Marketing | F301: Diane Okafor | G301: TRP-2025-096 | H301: Supplier Audit | I301: Austin | J301: United States | K301: 45677 | L301: 45684 | M301: 45684 | N301: 2025-01 | O301: Meals - Dinner | P301: Party of 4 | Q301: The Grill House | R301: Cash (Reimbursable) | S301: USD | T301: 68.9 | U301: 1 | V301: =T301*U301 -> 68.9 | W301: 0 | X301: =V301-(V301/(1+W301)) -> 0 | Y301: =V301-X301 -> 68.9 | Z301: 75 | AA301: =IF(V301>Z301,"Yes","No") -> No | AB301: =V301-Z301 -> -6.1 | AC301: Yes | AD301: Yes | AE301: MERIDIAN-4415 | AF301: =IF(AG301="Rejected",0,IF(R301="Corporate Card",0,V301)) -> 68.9 | AG301: Approved | AH301: 45696 | AI301: 45702 | AJ301: 45712 | AK301: =IF(AJ301="","",AJ301-AH301) -> 16
A302: EXP-00301 | B302: EMP-1409 | C302: Grace Lin | D302: Marketing | E302: Head of Marketing | F302: Diane Okafor | G302: TRP-2025-096 | H302: Supplier Audit | I302: Austin | J302: United States | K302: 45677 | L302: 45684 | M302: 45684 | N302: 2025-01 | O302: Meals - Lunch | P302: Individual meal | Q302: Pret A Manger | R302: Corporate Card | S302: USD | T302: 22.91 | U302: 1 | V302: =T302*U302 -> 22.91 | W302: 0 | X302: =V302-(V302/(1+W302)) -> 0 | Y302: =V302-X302 -> 22.91 | Z302: 35 | AA302: =IF(V302>Z302,"Yes","No") -> No | AB302: =V302-Z302 -> -12.09 | AC302: Yes | AD302: Yes | AE302: MERIDIAN-4415 | AF302: =IF(AG302="Rejected",0,IF(R302="Corporate Card",0,V302)) -> 0 | AG302: Approved | AH302: 45696 | AI302: 45702 | AJ302: 45712 | AK302: =IF(AJ302="","",AJ302-AH302) -> 16
A303: EXP-00302 | B303: EMP-1401 | C303: Fatima Al-Rashid | D303: Marketing | E303: Marketing Manager | F303: Grace Lin | G303: TRP-2025-005 | H303: Sales Pitch / RFP Presentation | I303: Atlanta | J303: United States | K303: 45684 | L303: 45691 | M303: 45685 | N303: 2025-01 | O303: Ground Transport - Rail | P303: Intercity transfer | Q303: JR East | R303: Personal Card (Reimbursable) | S303: USD | T303: 127.81 | U303: 1 | V303: =T303*U303 -> 127.81 | W303: 0 | X303: =V303-(V303/(1+W303)) -> 0 | Y303: =V303-X303 -> 127.81 | Z303: 150 | AA303: =IF(V303>Z303,"Yes","No") -> No | AB303: =V303-Z303 -> -22.19 | AC303: Yes | AD303: Yes | AE303: NORDIC-1180 | AF303: =IF(AG303="Rejected",0,IF(R303="Corporate Card",0,V303)) -> 127.81 | AG303: Approved | AH303: 45702 | AI303: 45704 | AJ303: 45711 | AK303: =IF(AJ303="","",AJ303-AH303) -> 9
A304: EXP-00303 | B304: EMP-1401 | C304: Fatima Al-Rashid | D304: Marketing | E304: Marketing Manager | F304: Grace Lin | G304: TRP-2025-005 | H304: Sales Pitch / RFP Presentation | I304: Atlanta | J304: United States | K304: 45684 | L304: 45691 | M304: 45685 | N304: 2025-01 | O304: Ground Transport - Taxi | P304: Airport / client site transfer | Q304: Lyft | R304: Personal Card (Reimbursable) | S304: USD | T304: 75.36 | U304: 1 | V304: =T304*U304 -> 75.36 | W304: 0 | X304: =V304-(V304/(1+W304)) -> 0 | Y304: =V304-X304 -> 75.36 | Z304: 60 | AA304: =IF(V304>Z304,"Yes","No") -> Yes | AB304: =V304-Z304 -> 15.36 | AC304: Yes | AD304: Yes | AE304: NORDIC-1180 | AF304: =IF(AG304="Rejected",0,IF(R304="Corporate Card",0,V304)) -> 75.36 | AG304: Approved | AH304: 45702 | AI304: 45704 | AJ304: 45711 | AK304: =IF(AJ304="","",AJ304-AH304) -> 9
A305: EXP-00304 | B305: EMP-1401 | C305: Fatima Al-Rashid | D305: Marketing | E305: Marketing Manager | F305: Grace Lin | G305: TRP-2025-005 | H305: Sales Pitch / RFP Presentation | I305: Atlanta | J305: United States | K305: 45684 | L305: 45691 | M305: 45685 | N305: 2025-01 | O305: Hotel / Lodging | P305: 7 night(s) @ standard rate | Q305: Hyatt Place | R305: Corporate Card | S305: USD | T305: 1574.97 | U305: 1 | V305: =T305*U305 -> 1574.97 | W305: 0 | X305: =V305-(V305/(1+W305)) -> 0 | Y305: =V305-X305 -> 1574.97 | Z305: 1960 | AA305: =IF(V305>Z305,"Yes","No") -> No | AB305: =V305-Z305 -> -385.03 | AC305: No | AD305: Yes | AE305: NORDIC-1180 | AF305: =IF(AG305="Rejected",0,IF(R305="Corporate Card",0,V305)) -> 0 | AG305: Approved | AH305: 45702 | AI305: 45704 | AJ305: 45711 | AK305: =IF(AJ305="","",AJ305-AH305) -> 9
A306: EXP-00305 | B306: EMP-1401 | C306: Fatima Al-Rashid | D306: Marketing | E306: Marketing Manager | F306: Grace Lin | G306: TRP-2025-005 | H306: Sales Pitch / RFP Presentation | I306: Atlanta | J306: United States | K306: 45684 | L306: 45691 | M306: 45685 | N306: 2025-01 | O306: Meals - Breakfast | P306: Individual meal | Q306: Hotel Restaurant | R306: Cash (Reimbursable) | S306: USD | T306: 17.77 | U306: 1 | V306: =T306*U306 -> 17.77 | W306: 0 | X306: =V306-(V306/(1+W306)) -> 0 | Y306: =V306-X306 -> 17.77 | Z306: 25 | AA306: =IF(V306>Z306,"Yes","No") -> No | AB306: =V306-Z306 -> -7.23 | AC306: Yes | AD306: Yes | AE306: NORDIC-1180 | AF306: =IF(AG306="Rejected",0,IF(R306="Corporate Card",0,V306)) -> 17.77 | AG306: Approved | AH306: 45702 | AI306: 45704 | AJ306: 45711 | AK306: =IF(AJ306="","",AJ306-AH306) -> 9
A307: EXP-00306 | B307: EMP-1401 | C307: Fatima Al-Rashid | D307: Marketing | E307: Marketing Manager | F307: Grace Lin | G307: TRP-2025-005 | H307: Sales Pitch / RFP Presentation | I307: Atlanta | J307: United States | K307: 45684 | L307: 45691 | M307: 45685 | N307: 2025-01 | O307: Meals - Dinner | P307: Party of 4 | Q307: Brasserie Lyon | R307: Corporate Card | S307: USD | T307: 102.51 | U307: 1 | V307: =T307*U307 -> 102.51 | W307: 0 | X307: =V307-(V307/(1+W307)) -> 0 | Y307: =V307-X307 -> 102.51 | Z307: 75 | AA307: =IF(V307>Z307,"Yes","No") -> Yes | AB307: =V307-Z307 -> 27.51 | AC307: Yes | AD307: Yes | AE307: NORDIC-1180 | AF307: =IF(AG307="Rejected",0,IF(R307="Corporate Card",0,V307)) -> 0 | AG307: Approved | AH307: 45702 | AI307: 45704 | AJ307: 45711 | AK307: =IF(AJ307="","",AJ307-AH307) -> 9
A308: EXP-00307 | B308: EMP-1401 | C308: Fatima Al-Rashid | D308: Marketing | E308: Marketing Manager | F308: Grace Lin | G308: TRP-2025-005 | H308: Sales Pitch / RFP Presentation | I308: Atlanta | J308: United States | K308: 45684 | L308: 45691 | M308: 45685 | N308: 2025-01 | O308: Meals - Lunch | P308: Individual meal | Q308: Sweetgreen | R308: Corporate Card | S308: USD | T308: 28.59 | U308: 1 | V308: =T308*U308 -> 28.59 | W308: 0 | X308: =V308-(V308/(1+W308)) -> 0 | Y308: =V308-X308 -> 28.59 | Z308: 35 | AA308: =IF(V308>Z308,"Yes","No") -> No | AB308: =V308-Z308 -> -6.41 | AC308: No | AD308: Yes | AE308: NORDIC-1180 | AF308: =IF(AG308="Rejected",0,IF(R308="Corporate Card",0,V308)) -> 0 | AG308: Approved | AH308: 45702 | AI308: 45704 | AJ308: 45711 | AK308: =IF(AJ308="","",AJ308-AH308) -> 9
A309: EXP-00308 | B309: EMP-1510 | C309: Paul Nkemelu | D309: Customer Success | E309: Director of CS | F309: Diane Okafor | G309: TRP-2025-037 | H309: Product Launch Event | I309: Bengaluru | J309: India | K309: 45683 | L309: 45688 | M309: 45685 | N309: 2025-01 | O309: Meals - Breakfast | P309: Individual meal | Q309: Cafe Nero | R309: Personal Card (Reimbursable) | S309: INR | T309: 1030 | U309: 0.01178 | V309: =T309*U309 -> 12.1334 | W309: 0.18 | X309: =V309-(V309/(1+W309)) -> 1.8508576 | Y309: =V309-X309 -> 10.282542 | Z309: 25 | AA309: =IF(V309>Z309,"Yes","No") -> No | AB309: =V309-Z309 -> -12.8666 | AC309: Yes | AD309: No | AE309: MERIDIAN-4415 | AF309: =IF(AG309="Rejected",0,IF(R309="Corporate Card",0,V309)) -> 12.1334 | AG309: Approved | AH309: 45695 | AI309: 45699 | AJ309: 45704 | AK309: =IF(AJ309="","",AJ309-AH309) -> 9
... A311: EXP-00310 | B311: EMP-1510 | C311: Paul Nkemelu | D311: Customer Success | E311: Director of CS | F311: Diane Okafor | G311: TRP-2025-037 | H311: Product Launch Event | I311: Bengaluru | J311: India | K311: 45683 | L311: 45688 | M311: 45685 | N311: 2025-01 | O311: Meals - Lunch | P311: Individual meal | Q311: Food Court | R311: Cash (Reimbursable) | S311: INR | T311: 1596 | U311: 0.01178 | V311: =T311*U311 -> 18.80088 | W311: 0.18 | X311: =V311-(V311/(1+W311)) -> 2.8679308 | Y311: =V311-X311 -> 15.932949 | Z311: 35 | AA311: =IF(V311>Z311,"Yes","No") -> No | AB311: =V311-Z311 -> -16.19912 | AC311: Yes | AD311: No | AE311: MERIDIAN-4415 | AF311: =IF(AG311="Rejected",0,IF(R311="Corporate Card",0,V311)) -> 18.80088 | AG311: Approved | AH311: 45695 | AI311: 45699 | AJ311: 45704 | AK311: =IF(AJ311="","",AJ311-AH311) -> 9
A312: EXP-00311 | B312: EMP-1502 | C312: Sneha Iyer | D312: Customer Success | E312: CS Manager | F312: Paul Nkemelu | G312: TRP-2025-081 | H312: Supplier Audit | I312: San Jose | J312: United States | K312: 45684 | L312: 45688 | M312: 45685 | N312: 2025-01 | O312: Hotel / Lodging | P312: 4 night(s) @ standard rate | Q312: Hyatt Place | R312: Personal Card (Reimbursable) | S312: USD | T312: 1011.06 | U312: 1 | V312: =T312*U312 -> 1011.06 | W312: 0 | X312: =V312-(V312/(1+W312)) -> 0 | Y312: =V312-X312 -> 1011.06 | Z312: 1120 | AA312: =IF(V312>Z312,"Yes","No") -> No | AB312: =V312-Z312 -> -108.94 | AC312: Yes | AD312: No | AE312: BLUEPEAK-7702 | AF312: =IF(AG312="Rejected",0,IF(R312="Corporate Card",0,V312)) -> 1011.06 | AG312: Pending Approval | AH312: 45698 | AK312: =IF(AJ312="","",AJ312-AH312)
A313: EXP-00312 | B313: EMP-1502 | C313: Sneha Iyer | D313: Customer Success | E313: CS Manager | F313: Paul Nkemelu | G313: TRP-2025-081 | H313: Supplier Audit | I313: San Jose | J313: United States | K313: 45684 | L313: 45688 | M313: 45685 | N313: 2025-01 | O313: Meals - Breakfast | P313: Individual meal | Q313: Cafe Nero | R313: Corporate Card | S313: USD | T313: 17.13 | U313: 1 | V313: =T313*U313 -> 17.13 | W313: 0 | X313: =V313-(V313/(1+W313)) -> 0 | Y313: =V313-X313 -> 17.13 | Z313: 25 | AA313: =IF(V313>Z313,"Yes","No") -> No | AB313: =V313-Z313 -> -7.87 | AC313: Yes | AD313: No | AE313: BLUEPEAK-7702 | AF313: =IF(AG313="Rejected",0,IF(R313="Corporate Card",0,V313)) -> 0 | AG313: Pending Approval | AH313: 45698 | AK313: =IF(AJ313="","",AJ313-AH313)
A314: EXP-00313 | B314: EMP-1502 | C314: Sneha Iyer | D314: Customer Success | E314: CS Manager | F314: Paul Nkemelu | G314: TRP-2025-081 | H314: Supplier Audit | I314: San Jose | J314: United States | K314: 45684 | L314: 45688 | M314: 45685 | N314: 2025-01 | O314: Meals - Lunch | P314: Individual meal | Q314: Local Bistro | R314: Cash (Reimbursable) | S314: USD | T314: 20.97 | U314: 1 | V314: =T314*U314 -> 20.97 | W314: 0 | X314: =V314-(V314/(1+W314)) -> 0 | Y314: =V314-X314 -> 20.97 | Z314: 35 | AA314: =IF(V314>Z314,"Yes","No") -> No | AB314: =V314-Z314 -> -14.03 | AC314: Yes | AD314: No | AE314: BLUEPEAK-7702 | AF314: =IF(AG314="Rejected",0,IF(R314="Corporate Card",0,V314)) -> 20.97 | AG314: Pending Approval | AH314: 45698 | AK314: =IF(AJ314="","",AJ314-AH314)
A315: EXP-00314 | B315: EMP-1401 | C315: Fatima Al-Rashid | D315: Marketing | E315: Marketing Manager | F315: Grace Lin | G315: TRP-2025-005 | H315: Sales Pitch / RFP Presentation | I315: Atlanta | J315: United States | K315: 45684 | L315: 45691 | M315: 45686 | N315: 2025-01 | O315: Ground Transport - Taxi | P315: Airport / client site transfer | Q315: Local Taxi | R315: Corporate Card | S315: USD | T315: 32.39 | U315: 1 | V315: =T315*U315 -> 32.39 | W315: 0 | X315: =V315-(V315/(1+W315)) -> 0 | Y315: =V315-X315 -> 32.39 | Z315: 60 | AA315: =IF(V315>Z315,"Yes","No") -> No | AB315: =V315-Z315 -> -27.61 | AC315: Yes | AD315: Yes | AE315: NORDIC-1180 | AF315: =IF(AG315="Rejected",0,IF(R315="Corporate Card",0,V315)) -> 0 | AG315: Approved | AH315: 45702 | AI315: 45704 | AJ315: 45711 | AK315: =IF(AJ315="","",AJ315-AH315) -> 9
A316: EXP-00315 | B316: EMP-1401 | C316: Fatima Al-Rashid | D316: Marketing | E316: Marketing Manager | F316: Grace Lin | G316: TRP-2025-005 | H316: Sales Pitch / RFP Presentation | I316: Atlanta | J316: United States | K316: 45684 | L316: 45691 | M316: 45686 | N316: 2025-01 | O316: Meals - Breakfast | P316: Individual meal | Q316: Hotel Restaurant | R316: Corporate Card | S316: USD | T316: 12.22 | U316: 1 | V316: =T316*U316 -> 12.22 | W316: 0 | X316: =V316-(V316/(1+W316)) -> 0 | Y316: =V316-X316 -> 12.22 | Z316: 25 | AA316: =IF(V316>Z316,"Yes","No") -> No | AB316: =V316-Z316 -> -12.78 | AC316: Yes | AD316: Yes | AE316: NORDIC-1180 | AF316: =IF(AG316="Rejected",0,IF(R316="Corporate Card",0,V316)) -> 0 | AG316: Approved | AH316: 45702 | AI316: 45704 | AJ316: 45711 | AK316: =IF(AJ316="","",AJ316-AH316) -> 9
A317: EXP-00316 | B317: EMP-1401 | C317: Fatima Al-Rashid | D317: Marketing | E317: Marketing Manager | F317: Grace Lin | G317: TRP-2025-005 | H317: Sales Pitch / RFP Presentation | I317: Atlanta | J317: United States | K317: 45684 | L317: 45691 | M317: 45686 | N317: 2025-01 | O317: Meals - Dinner | P317: Party of 3 | Q317: Spice Route | R317: Corporate Card | S317: USD | T317: 73.9 | U317: 1 | V317: =T317*U317 -> 73.9 | W317: 0 | X317: =V317-(V317/(1+W317)) -> 0 | Y317: =V317-X317 -> 73.9 | Z317: 75 | AA317: =IF(V317>Z317,"Yes","No") -> No | AB317: =V317-Z317 -> -1.1 | AC317: Yes | AD317: Yes | AE317: NORDIC-1180 | AF317: =IF(AG317="Rejected",0,IF(R317="Corporate Card",0,V317)) -> 0 | AG317: Approved | AH317: 45702 | AI317: 45704 | AJ317: 45711 | AK317: =IF(AJ317="","",AJ317-AH317) -> 9
A318: EXP-00317 | B318: EMP-1510 | C318: Paul Nkemelu | D318: Customer Success | E318: Director of CS | F318: Diane Okafor | G318: TRP-2025-037 | H318: Product Launch Event | I318: Bengaluru | J318: India | K318: 45683 | L318: 45688 | M318: 45686 | N318: 2025-01 | O318: Ground Transport - Taxi | P318: Airport / client site transfer | Q318: Lyft | R318: Corporate Card | S318: INR | T318: 7889 | U318: 0.01178 | V318: =T318*U318 -> 92.93242 | W318: 0.18 | X318: =V318-(V318/(1+W318)) -> 14.176132 | Y318: =V318-X318 -> 78.756288 | Z318: 60 | AA318: =IF(V318>Z318,"Yes","No") -> Yes | AB318: =V318-Z318 -> 32.93242 | AC318: Yes | AD318: No | AE318: MERIDIAN-4415 | AF318: =IF(AG318="Rejected",0,IF(R318="Corporate Card",0,V318)) -> 0 | AG318: Approved | AH318: 45695 | AI318: 45699 | AJ318: 45704 | AK318: =IF(AJ318="","",AJ318-AH318) -> 9
...

Sheet Trip Summary
A1: Helios Instruments Pvt. Ltd. — Business Travel: Trip Summary, 2025
A3: Trip ID | B3: Employee Name | C3: Department | D3: Destination City | E3: Country | F3: Trip Purpose | G3: Trip Start | H3: Trip End | I3: Duration (days) | J3: Line Items | K3: Total Spend (USD) | L3: Cost per Day (USD) | M3: Items Over Policy | N3: Reimbursable (USD) | O3: Client / Project | P3: Billable | Q3: Approval Status
A4: TRP-2025-001 | B4: Samuel Adeyemi | C4: Field Engineering | D4: London | E4: United Kingdom | F4: Contract Negotiation | G4: 45773 | H4: 45776 | I4: =H4-G4+1 -> 4 | J4: =COUNTIFS('Expense Details'!$G$2:$G$2955,$A4) -> 17 | K4: =SUMIFS('Expense Details'!$V$2:$V$2955,'Expense Details'!$G$2:$G$2955,$A4) -> 3530.0671 | L4: =IFERROR(K4/I4,0) -> 882.51678 | M4: =COUNTIFS('Expense Details'!$G$2:$G$2955,$A4,'Expense Details'!$AA$2:$AA$2955,"Yes") -> 1 | N4: =SUMIFS('Expense Details'!$AF$2:$AF$2955,'Expense Details'!$G$2:$G$2955,$A4) -> 3181.5391 | O4: BLUEPEAK-7702 | P4: Yes | Q4: Approved
A5: TRP-2025-002 | B5: Aisha Bello | C5: Operations | D5: Sao Paulo | E5: Brazil | F5: Internal Training | G5: 45713 | H5: 45714 | I5: =H5-G5+1 -> 2 | J5: =COUNTIFS('Expense Details'!$G$2:$G$2955,$A5) -> 10 | K5: =SUMIFS('Expense Details'!$V$2:$V$2955,'Expense Details'!$G$2:$G$2955,$A5) -> 3491.0103 | L5: =IFERROR(K5/I5,0) -> 1745.5052 | M5: =COUNTIFS('Expense Details'!$G$2:$G$2955,$A5,'Expense Details'!$AA$2:$AA$2955,"Yes") -> 5 | N5: =SUMIFS('Expense Details'!$AF$2:$AF$2955,'Expense Details'!$G$2:$G$2955,$A5) -> 85.29263 | O5: KAIZEN-6620 | P5: Yes | Q5: Approved
A6: TRP-2025-003 | B6: Sneha Iyer | C6: Customer Success | D6: Dubai | E6: UAE | F6: Product Launch Event | G6: 45843 | H6: 45846 | I6: =H6-G6+1 -> 4 | J6: =COUNTIFS('Expense Details'!$G$2:$G$2955,$A6) -> 15 | K6: =SUMIFS('Expense Details'!$V$2:$V$2955,'Expense Details'!$G$2:$G$2955,$A6) -> 2997.9713 | L6: =IFERROR(K6/I6,0) -> 749.49282 | M6: =COUNTIFS('Expense Details'!$G$2:$G$2955,$A6,'Expense Details'!$AA$2:$AA$2955,"Yes") -> 4 | N6: =SUMIFS('Expense Details'!$AF$2:$AF$2955,'Expense Details'!$G$2:$G$2955,$A6) -> 658.75361 | O6: KAIZEN-6620 | P6: Yes | Q6: Approved
A7: TRP-2025-004 | B7: Rohit Malhotra | C7: Sales | D7: Paris | E7: France | F7: Internal Training | G7: 45953 | H7: 45956 | I7: =H7-G7+1 -> 4 | J7: =COUNTIFS('Expense Details'!$G$2:$G$2955,$A7) -> 15 | K7: =SUMIFS('Expense Details'!$V$2:$V$2955,'Expense Details'!$G$2:$G$2955,$A7) -> 4850.0042 | L7: =IFERROR(K7/I7,0) -> 1212.5011 | M7: =COUNTIFS('Expense Details'!$G$2:$G$2955,$A7,'Expense Details'!$AA$2:$AA$2955,"Yes") -> 1 | N7: =SUMIFS('Expense Details'!$AF$2:$AF$2955,'Expense Details'!$G$2:$G$2955,$A7) -> 3811.9305 | O7: TATRA-3390 | P7: No | Q7: Approved
A8: TRP-2025-005 | B8: Fatima Al-Rashid | C8: Marketing | D8: Atlanta | E8: United States | F8: Sales Pitch / RFP Presentation | G8: 45684 | H8: 45691 | I8: =H8-G8+1 -> 8 | J8: =COUNTIFS('Expense Details'!$G$2:$G$2955,$A8) -> 29 | K8: =SUMIFS('Expense Details'!$V$2:$V$2955,'Expense Details'!$G$2:$G$2955,$A8) -> 4237.37 | L8: =IFERROR(K8/I8,0) -> 529.67125 | M8: =COUNTIFS('Expense Details'!$G$2:$G$2955,$A8,'Expense Details'!$AA$2:$AA$2955,"Yes") -> 3 | N8: =SUMIFS('Expense Details'!$AF$2:$AF$2955,'Expense Details'!$G$2:$G$2955,$A8) -> 1949.6 | O8: NORDIC-1180 | P8: Yes | Q8: Approved
A9: TRP-2025-006 | B9: Tomas Kovac | C9: Field Engineering | D9: Berlin | E9: Germany | F9: Trade Show / Conference | G9: 45798 | H9: 45804 | I9: =H9-G9+1 -> 7 | J9: =COUNTIFS('Expense Details'!$G$2:$G$2955,$A9) -> 25 | K9: =SUMIFS('Expense Details'!$V$2:$V$2955,'Expense Details'!$G$2:$G$2955,$A9) -> 5031.6658 | L9: =IFERROR(K9/I9,0) -> 718.8094 | M9: =COUNTIFS('Expense Details'!$G$2:$G$2955,$A9,'Expense Details'!$AA$2:$AA$2955,"Yes") -> 2 | N9: =SUMIFS('Expense Details'!$AF$2:$AF$2955,'Expense Details'!$G$2:$G$2955,$A9) -> 2701.65 | O9: MERIDIAN-4415 | P9: No | Q9: Approved
A10: TRP-2025-007 | B10: Clara Jensen | C10: Sales | D10: Atlanta | E10: United States | F10: Customer Site Installation | G10: 45927 | H10: 45930 | I10: =H10-G10+1 -> 4 | J10: =COUNTIFS('Expense Details'!$G$2:$G$2955,$A10) -> 14 | K10: =SUMIFS('Expense Details'!$V$2:$V$2955,'Expense Details'!$G$2:$G$2955,$A10) -> 2135.75 | L10: =IFERROR(K10/I10,0) -> 533.9375 | M10: =COUNTIFS('Expense Details'!$G$2:$G$2955,$A10,'Expense Details'!$AA$2:$AA$2955,"Yes") -> 0 | N10: =SUMIFS('Expense Details'!$AF$2:$AF$2955,'Expense Details'!$G$2:$G$2955,$A10) -> 151.88 | O10: BLUEPEAK-7702 | P10: No | Q10: Pending Approval
A11: TRP-2025-008 | B11: Oliver Brandt | C11: Marketing | D11: Bengaluru | E11: India | F11: Client Meeting | G11: 46003 | H11: 46005 | I11: =H11-G11+1 -> 3 | J11: =COUNTIFS('Expense Details'!$G$2:$G$2955,$A11) -> 13 | K11: =SUMIFS('Expense Details'!$V$2:$V$2955,'Expense Details'!$G$2:$G$2955,$A11) -> 1721.647 | L11: =IFERROR(K11/I11,0) -> 573.88233 | M11: =COUNTIFS('Expense Details'!$G$2:$G$2955,$A11,'Expense Details'!$AA$2:$AA$2955,"Yes") -> 1 | N11: =SUMIFS('Expense Details'!$AF$2:$AF$2955,'Expense Details'!$G$2:$G$2955,$A11) -> 516.80038 | O11: NORDIC-1180 | P11: Yes | Q11: Approved
A12: TRP-2025-009 | B12: Meera Krishnan | C12: Finance | D12: Munich | E12: Germany | F12: Product Launch Event | G12: 45871 | H12: 45877 | I12: =H12-G12+1 -> 7 | J12: =COUNTIFS('Expense Details'!$G$2:$G$2955,$A12) -> 27 | K12: =SUMIFS('Expense Details'!$V$2:$V$2955,'Expense Details'!$G$2:$G$2955,$A12) -> 7610.4178 | L12: =IFERROR(K12/I12,0) -> 1087.2025 | M12: =COUNTIFS('Expense Details'!$G$2:$G$2955,$A12,'Expense Details'!$AA$2:$AA$2955,"Yes") -> 3 | N12: =SUMIFS('Expense Details'!$AF$2:$AF$2955,'Expense Details'!$G$2:$G$2955,$A12) -> 2757.7553 | O12: MERIDIAN-4415 | P12: Yes | Q12: Approved
A13: TRP-2025-010 | B13: Oliver Brandt | C13: Marketing | D13: Munich | E13: Germany | F13: Internal Training | G13: 45816 | H13: 45820 | I13: =H13-G13+1 -> 5 | J13: =COUNTIFS('Expense Details'!$G$2:$G$2955,$A13) -> 17 | K13: =SUMIFS('Expense Details'!$V$2:$V$2955,'Expense Details'!$G$2:$G$2955,$A13) -> 3311.3874 | L13: =IFERROR(K13/I13,0) -> 662.27749 | M13: =COUNTIFS('Expense Details'!$G$2:$G$2955,$A13,'Expense Details'!$AA$2:$AA$2955,"Yes") -> 3 | N13: =SUMIFS('Expense Details'!$AF$2:$AF$2955,'Expense Details'!$G$2:$G$2955,$A13) -> 2080.238 | O13: INTERNAL-0000 | P13: No | Q13: Approved
A14: TRP-2025-011 | B14: Aisha Bello | C14: Operations | D14: Boston | E14: United States | F14: Customer Site Installation | G14: 45959 | H14: 45961 | I14: =H14-G14+1 -> 3 | J14: =COUNTIFS('Expense Details'!$G$2:$G$2955,$A14) -> 11 | K14: =SUMIFS('Expense Details'!$V$2:$V$2955,'Expense Details'!$G$2:$G$2955,$A14) -> 1756.43 | L14: =IFERROR(K14/I14,0) -> 585.47667 | M14: =COUNTIFS('Expense Details'!$G$2:$G$2955,$A14,'Expense Details'!$AA$2:$AA$2955,"Yes") -> 1 | N14: =SUMIFS('Expense Details'!$AF$2:$AF$2955,'Expense Details'!$G$2:$G$2955,$A14) -> 107.83 | O14: BLUEPEAK-7702 | P14: Yes | Q14: Approved
A15: TRP-2025-012 | B15: Diane Okafor | C15: Executive | D15: San Jose | E15: United States | F15: Client Meeting | G15: 45908 | H15: 45914 | I15: =H15-G15+1 -> 7 | J15: =COUNTIFS('Expense Details'!$G$2:$G$2955,$A15) -> 25 | K15: =SUMIFS('Expense Details'!$V$2:$V$2955,'Expense Details'!$G$2:$G$2955,$A15) -> 3302.63 | L15: =IFERROR(K15/I15,0) -> 471.80429 | M15: =COUNTIFS('Expense Details'!$G$2:$G$2955,$A15,'Expense Details'!$AA$2:$AA$2955,"Yes") -> 4 | N15: =SUMIFS('Expense Details'!$AF$2:$AF$2955,'Expense Details'!$G$2:$G$2955,$A15) -> 357.2 | O15: ORBITAL-8834 | P15: Yes | Q15: Pending Approval
... A141: TRP-2025-138 | B141: Hannah Weiss | C141: Field Engineering | D141: Tokyo | E141: Japan | F141: Trade Show / Conference | G141: 45897 | H141: 45901 | I141: =H141-G141+1 -> 5 | J141: =COUNTIFS('Expense Details'!$G$2:$G$2955,$A141) -> 20 | K141: =SUMIFS('Expense Details'!$V$2:$V$2955,'Expense Details'!$G$2:$G$2955,$A141) -> 4567.5639 | L141: =IFERROR(K141/I141,0) -> 913.51278 | M141: =COUNTIFS('Expense Details'!$G$2:$G$2955,$A141,'Expense Details'!$AA$2:$AA$2955,"Yes") -> 3 | N141: =SUMIFS('Expense Details'!$AF$2:$AF$2955,'Expense Details'!$G$2:$G$2955,$A141) -> 2616.725 | O141: MERIDIAN-4415 | P141: Yes | Q141: Approved
A142: TOTAL | J142: =SUM(J4:J141) -> 2954 | K142: =SUM(K4:K141) -> 476910.79 | M142: =SUM(M4:M141) -> 318 | N142: =SUM(N4:N141) -> 191871.42

Sheet Employee Summary
A1: Helios Instruments Pvt. Ltd. — Travel Spend by Employee, 2025
A3: Employee ID | B3: Employee Name | C3: Department | D3: Job Title | E3: Manager / Approver | F3: Trips Taken | G3: Expense Line Items | H3: Total Spend (USD) | I3: Airfare (USD) | J3: Lodging (USD) | K3: Meals (USD) | L3: Ground Transport (USD) | M3: Other (USD) | N3: Items Over Policy | O3: Missing Receipts | P3: Reimbursable (USD) | Q3: Avg Spend per Trip (USD) | R3: % of Company Travel Spend
A4: EMP-1712 | B4: Aisha Bello | C4: Operations | D4: Logistics Analyst | E4: Viktor Petrov | F4: 10 | G4: =COUNTIFS('Expense Details'!$B$2:$B$2955,$A4) -> 177 | H4: =SUMIFS('Expense Details'!$V$2:$V$2955,'Expense Details'!$B$2:$B$2955,$A4) -> 28793.899 | I4: =SUMIFS('Expense Details'!$V$2:$V$2955,'Expense Details'!$B$2:$B$2955,$A4,'Expense Details'!$O$2:$O$2955,"Airfare") -> 14167.041 | J4: =SUMIFS('Expense Details'!$V$2:$V$2955,'Expense Details'!$B$2:$B$2955,$A4,'Expense Details'!$O$2:$O$2955,"Hotel / Lodging") -> 6455.3002 | K4: =SUMIFS('Expense Details'!$V$2:$V$2955,'Expense Details'!$B$2:$B$2955,$A4,'Expense Details'!$O$2:$O$2955,"Meals*") -> 3451.1471 | L4: =SUMIFS('Expense Details'!$V$2:$V$2955,'Expense Details'!$B$2:$B$2955,$A4,'Expense Details'!$O$2:$O$2955,"Ground Transport*")+SUMIFS('Expense Details'!$V$2:$V$2955,'Expense Details'!$B$2:$B$2955,$A4,'Expense Details'!$O$2:$O$2955,"Car Rental") -> 2696.8145 | M4: =H4-I4-J4-K4-L4 -> 2023.5964 | N4: =COUNTIFS('Expense Details'!$B$2:$B$2955,$A4,'Expense Details'!$AA$2:$AA$2955,"Yes") -> 29 | O4: =COUNTIFS('Expense Details'!$B$2:$B$2955,$A4,'Expense Details'!$AC$2:$AC$2955,"No") -> 16 | P4: =SUMIFS('Expense Details'!$AF$2:$AF$2955,'Expense Details'!$B$2:$B$2955,$A4) -> 4785.29 | Q4: =IFERROR(H4/F4,0) -> 2879.3899 | R4: =IFERROR(H4/H$28,0) -> 0.06037586
A5: EMP-1042 | B5: Ananya Sengupta | C5: Sales | D5: Regional Sales Director | E5: Marcus Bell | F5: 2 | G5: =COUNTIFS('Expense Details'!$B$2:$B$2955,$A5) -> 52 | H5: =SUMIFS('Expense Details'!$V$2:$V$2955,'Expense Details'!$B$2:$B$2955,$A5) -> 9779.0616 | I5: =SUMIFS('Expense Details'!$V$2:$V$2955,'Expense Details'!$B$2:$B$2955,$A5,'Expense Details'!$O$2:$O$2955,"Airfare") -> 3982.7963 | J5: =SUMIFS('Expense Details'!$V$2:$V$2955,'Expense Details'!$B$2:$B$2955,$A5,'Expense Details'!$O$2:$O$2955,"Hotel / Lodging") -> 3082.6695 | K5: =SUMIFS('Expense Details'!$V$2:$V$2955,'Expense Details'!$B$2:$B$2955,$A5,'Expense Details'!$O$2:$O$2955,"Meals*") -> 1251.8188 | L5: =SUMIFS('Expense Details'!$V$2:$V$2955,'Expense Details'!$B$2:$B$2955,$A5,'Expense Details'!$O$2:$O$2955,"Ground Transport*")+SUMIFS('Expense Details'!$V$2:$V$2955,'Expense Details'!$B$2:$B$2955,$A5,'Expense Details'!$O$2:$O$2955,"Car Rental") -> 995.97575 | M5: =H5-I5-J5-K5-L5 -> 465.80135 | N5: =COUNTIFS('Expense Details'!$B$2:$B$2955,$A5,'Expense Details'!$AA$2:$AA$2955,"Yes") -> 6 | O5: =COUNTIFS('Expense Details'!$B$2:$B$2955,$A5,'Expense Details'!$AC$2:$AC$2955,"No") -> 3 | P5: =SUMIFS('Expense Details'!$AF$2:$AF$2955,'Expense Details'!$B$2:$B$2955,$A5) -> 6680.8983 | Q5: =IFERROR(H5/F5,0) -> 4889.5308 | R5: =IFERROR(H5/H$28,0) -> 0.020505012
A6: EMP-1328 | B6: Arjun Deshpande | C6: Product | D6: Product Analyst | E6: Elena Duarte | F6: 8 | G6: =COUNTIFS('Expense Details'!$B$2:$B$2955,$A6) -> 184 | H6: =SUMIFS('Expense Details'!$V$2:$V$2955,'Expense Details'!$B$2:$B$2955,$A6) -> 26987.58 | I6: =SUMIFS('Expense Details'!$V$2:$V$2955,'Expense Details'!$B$2:$B$2955,$A6,'Expense Details'!$O$2:$O$2955,"Airfare") -> 13234.589 | J6: =SUMIFS('Expense Details'!$V$2:$V$2955,'Expense Details'!$B$2:$B$2955,$A6,'Expense Details'!$O$2:$O$2955,"Hotel / Lodging") -> 6798.8229 | K6: =SUMIFS('Expense Details'!$V$2:$V$2955,'Expense Details'!$B$2:$B$2955,$A6,'Expense Details'!$O$2:$O$2955,"Meals*") -> 3773.7168 | L6: =SUMIFS('Expense Details'!$V$2:$V$2955,'Expense Details'!$B$2:$B$2955,$A6,'Expense Details'!$O$2:$O$2955,"Ground Transport*")+SUMIFS('Expense Details'!$V$2:$V$2955,'Expense Details'!$B$2:$B$2955,$A6,'Expense Details'!$O$2:$O$2955,"Car Rental") -> 2117.3822 | M6: =H6-I6-J6-K6-L6 -> 1063.0684 | N6: =COUNTIFS('Expense Details'!$B$2:$B$2955,$A6,'Expense Details'!$AA$2:$AA$2955,"Yes") -> 22 | O6: =COUNTIFS('Expense Details'!$B$2:$B$2955,$A6,'Expense Details'!$AC$2:$AC$2955,"No") -> 20 | P6: =SUMIFS('Expense Details'!$AF$2:$AF$2955,'Expense Details'!$B$2:$B$2955,$A6) -> 11749.822 | Q6: =IFERROR(H6/F6,0) -> 3373.4475 | R6: =IFERROR(H6/H$28,0) -> 0.056588318
A7: EMP-1118 | B7: Clara Jensen | C7: Sales | D7: Account Executive | E7: Ananya Sengupta | F7: 3 | G7: =COUNTIFS('Expense Details'!$B$2:$B$2955,$A7) -> 60 | H7: =SUMIFS('Expense Details'!$V$2:$V$2955,'Expense Details'!$B$2:$B$2955,$A7) -> 10124.951 | I7: =SUMIFS('Expense Details'!$V$2:$V$2955,'Expense Details'!$B$2:$B$2955,$A7,'Expense Details'!$O$2:$O$2955,"Airfare") -> 5574.2693 | J7: =SUMIFS('Expense Details'!$V$2:$V$2955,'Expense Details'!$B$2:$B$2955,$A7,'Expense Details'!$O$2:$O$2955,"Hotel / Lodging") -> 2035.477 | K7: =SUMIFS('Expense Details'!$V$2:$V$2955,'Expense Details'!$B$2:$B$2955,$A7,'Expense Details'!$O$2:$O$2955,"Meals*") -> 1195.5374 | L7: =SUMIFS('Expense Details'!$V$2:$V$2955,'Expense Details'!$B$2:$B$2955,$A7,'Expense Details'!$O$2:$O$2955,"Ground Transport*")+SUMIFS('Expense Details'!$V$2:$V$2955,'Expense Details'!$B$2:$B$2955,$A7,'Expense Details'!$O$2:$O$2955,"Car Rental") -> 856.47886 | M7: =H7-I7-J7-K7-L7 -> 463.18805 | N7: =COUNTIFS('Expense Details'!$B$2:$B$2955,$A7,'Expense Details'!$AA$2:$AA$2955,"Yes") -> 4 | O7: =COUNTIFS('Expense Details'!$B$2:$B$2955,$A7,'Expense Details'!$AC$2:$AC$2955,"No") -> 5 | P7: =SUMIFS('Expense Details'!$AF$2:$AF$2955,'Expense Details'!$B$2:$B$2955,$A7) -> 1358.0296 | Q7: =IFERROR(H7/F7,0) -> 3374.9835 | R7: =IFERROR(H7/H$28,0) -> 0.021230282
A8: EMP-1601 | B8: David Chen | C8: Finance | D8: Financial Controller | E8: Diane Okafor | F8: 8 | G8: =COUNTIFS('Expense Details'!$B$2:$B$2955,$A8) -> 158 | H8: =SUMIFS('Expense Details'!$V$2:$V$2955,'Expense Details'!$B$2:$B$2955,$A8) -> 27893.451 | I8: =SUMIFS('Expense Details'!$V$2:$V$2955,'Expense Details'!$B$2:$B$2955,$A8,'Expense Details'!$O$2:$O$2955,"Airfare") -> 13592.045 | J8: =SUMIFS('Expense Details'!$V$2:$V$2955,'Expense Details'!$B$2:$B$2955,$A8,'Expense Details'!$O$2:$O$2955,"Hotel / Lodging") -> 6582.9584 | K8: =SUMIFS('Expense Details'!$V$2:$V$2955,'Expense Details'!$B$2:$B$2955,$A8,'Expense Details'!$O$2:$O$2955,"Meals*") -> 3075.1555 | L8: =SUMIFS('Expense Details'!$V$2:$V$2955,'Expense Details'!$B$2:$B$2955,$A8,'Expense Details'!$O$2:$O$2955,"Ground Transport*")+SUMIFS('Expense Details'!$V$2:$V$2955,'Expense Details'!$B$2:$B$2955,$A8,'Expense Details'!$O$2:$O$2955,"Car Rental") -> 1387.1194 | M8: =H8-I8-J8-K8-L8 -> 3256.1732 | N8: =COUNTIFS('Expense Details'!$B$2:$B$2955,$A8,'Expense Details'!$AA$2:$AA$2955,"Yes") -> 20 | O8: =COUNTIFS('Expense Details'!$B$2:$B$2955,$A8,'Expense Details'!$AC$2:$AC$2955,"No") -> 18 | P8: =SUMIFS('Expense Details'!$AF$2:$AF$2955,'Expense Details'!$B$2:$B$2955,$A8) -> 13608.104 | Q8: =IFERROR(H8/F8,0) -> 3486.6814 | R8: =IFERROR(H8/H$28,0) -> 0.058487775
A9: EMP-1701 | B9: Diane Okafor | C9: Executive | D9: Chief Operating Officer | E9: Board | F9: 3 | G9: =COUNTIFS('Expense Details'!$B$2:$B$2955,$A9) -> 49 | H9: =SUMIFS('Expense Details'!$V$2:$V$2955,'Expense Details'!$B$2:$B$2955,$A9) -> 7241.4838 | I9: =SUMIFS('Expense Details'!$V$2:$V$2955,'Expense Details'!$B$2:$B$2955,$A9,'Expense Details'!$O$2:$O$2955,"Airfare") -> 3388.3818 | J9: =SUMIFS('Expense Details'!$V$2:$V$2955,'Expense Details'!$B$2:$B$2955,$A9,'Expense Details'!$O$2:$O$2955,"Hotel / Lodging") -> 2044.1078 | K9: =SUMIFS('Expense Details'!$V$2:$V$2955,'Expense Details'!$B$2:$B$2955,$A9,'Expense Details'!$O$2:$O$2955,"Meals*") -> 1140.0866 | L9: =SUMIFS('Expense Details'!$V$2:$V$2955,'Expense Details'!$B$2:$B$2955,$A9,'Expense Details'!$O$2:$O$2955,"Ground Transport*")+SUMIFS('Expense Details'!$V$2:$V$2955,'Expense Details'!$B$2:$B$2955,$A9,'Expense Details'!$O$2:$O$2955,"Car Rental") -> 300.0728 | M9: =H9-I9-J9-K9-L9 -> 368.8349 | N9: =COUNTIFS('Expense Details'!$B$2:$B$2955,$A9,'Expense Details'!$AA$2:$AA$2955,"Yes") -> 5 | O9: =COUNTIFS('Expense Details'!$B$2:$B$2955,$A9,'Expense Details'!$AC$2:$AC$2955,"No") -> 3 | P9: =SUMIFS('Expense Details'!$AF$2:$AF$2955,'Expense Details'!$B$2:$B$2955,$A9) -> 2717.2594 | Q9: =IFERROR(H9/F9,0) -> 2413.8279 | R9: =IFERROR(H9/H$28,0) -> 0.015184148
A10: EMP-1125 | B10: Diego Ramirez | C10: Sales | D10: Account Executive | E10: Marcus Bell | F10: 2 | G10: =COUNTIFS('Expense Details'!$B$2:$B$2955,$A10) -> 27 | H10: =SUMIFS('Expense Details'!$V$2:$V$2955,'Expense Details'!$B$2:$B$2955,$A10) -> 3379.1106 | I10: =SUMIFS('Expense Details'!$V$2:$V$2955,'Expense Details'!$B$2:$B$2955,$A10,'Expense Details'!$O$2:$O$2955,"Airfare") -> 1848.2821 | J10: =SUMIFS('Expense Details'!$V$2:$V$2955,'Expense Details'!$B$2:$B$2955,$A10,'Expense Details'!$O$2:$O$2955,"Hotel / Lodging") -> 579.04661 | K10: =SUMIFS('Expense Details'!$V$2:$V$2955,'Expense Details'!$B$2:$B$2955,$A10,'Expense Details'!$O$2:$O$2955,"Meals*") -> 613.2382 | L10: =SUMIFS('Expense Details'!$V$2:$V$2955,'Expense Details'!$B$2:$B$2955,$A10,'Expense Details'!$O$2:$O$2955,"Ground Transport*")+SUMIFS('Expense Details'!$V$2:$V$2955,'Expense Details'!$B$2:$B$2955,$A10,'Expense Details'!$O$2:$O$2955,"Car Rental") -> 195.52465 | M10: =H10-I10-J10-K10-L10 -> 143.01896 | N10: =COUNTIFS('Expense Details'!$B$2:$B$2955,$A10,'Expense Details'!$AA$2:$AA$2955,"Yes") -> 3 | O10: =COUNTIFS('Expense Details'!$B$2:$B$2955,$A10,'Expense Details'!$AC$2:$AC$2955,"No") -> 2 | P10: =SUMIFS('Expense Details'!$AF$2:$AF$2955,'Expense Details'!$B$2:$B$2955,$A10) -> 1466.8698 | Q10: =IFERROR(H10/F10,0) -> 1689.5553 | R10: =IFERROR(H10/H$28,0) -> 0.0070854143
A11: EMP-1315 | B11: Elena Duarte | C11: Product | D11: Director of Product | E11: Diane Okafor | F11: 7 | G11: =COUNTIFS('Expense Details'!$B$2:$B$2955,$A11) -> 165 | H11: =SUMIFS('Expense Details'!$V$2:$V$2955,'Expense Details'!$B$2:$B$2955,$A11) -> 20673.856 | I11: =SUMIFS('Expense Details'!$V$2:$V$2955,'Expense Details'!$B$2:$B$2955,$A11,'Expense Details'!$O$2:$O$2955,"Airfare") -> 6876.663 | J11: =SUMIFS('Expense Details'!$V$2:$V$2955,'Expense Details'!$B$2:$B$2955,$A11,'Expense Details'!$O$2:$O$2955,"Hotel / Lodging") -> 5333.8525 | K11: =SUMIFS('Expense Details'!$V$2:$V$2955,'Expense Details'!$B$2:$B$2955,$A11,'Expense Details'!$O$2:$O$2955,"Meals*") -> 3288.6768 | L11: =SUMIFS('Expense Details'!$V$2:$V$2955,'Expense Details'!$B$2:$B$2955,$A11,'Expense Details'!$O$2:$O$2955,"Ground Transport*")+SUMIFS('Expense Details'!$V$2:$V$2955,'Expense Details'!$B$2:$B$2955,$A11,'Expense Details'!$O$2:$O$2955,"Car Rental") -> 3364.0694 | M11: =H11-I11-J11-K11-L11 -> 1810.5942 | N11: =COUNTIFS('Expense Details'!$B$2:$B$2955,$A11,'Expense Details'!$AA$2:$AA$2955,"Yes") -> 14 | O11: =COUNTIFS('Expense Details'!$B$2:$B$2955,$A11,'Expense Details'!$AC$2:$AC$2955,"No") -> 13 | P11: =SUMIFS('Expense Details'!$AF$2:$AF$2955,'Expense Details'!$B$2:$B$2955,$A11) -> 5258.2279 | Q11: =IFERROR(H11/F11,0) -> 2953.408 | R11: =IFERROR(H11/H$28,0) -> 0.043349525
A12: EMP-1401 | B12: Fatima Al-Rashid | C12: Marketing | D12: Marketing Manager | E12: Grace Lin | F12: 3 | G12: =COUNTIFS('Expense Details'!$B$2:$B$2955,$A12) -> 52 | H12: =SUMIFS('Expense Details'!$V$2:$V$2955,'Expense Details'!$B$2:$B$2955,$A12) -> 8421.8617 | I12: =SUMIFS('Expense Details'!$V$2:$V$2955,'Expense Details'!$B$2:$B$2955,$A12,'Expense Details'!$O$2:$O$2955,"Airfare") -> 3929.0908 | J12: =SUMIFS('Expense Details'!$V$2:$V$2955,'Expense Details'!$B$2:$B$2955,$A12,'Expense Details'!$O$2:$O$2955,"Hotel / Lodging") -> 1928.3655 | K12: =SUMIFS('Expense Details'!$V$2:$V$2955,'Expense Details'!$B$2:$B$2955,$A12,'Expense Details'!$O$2:$O$2955,"Meals*") -> 1004.3143 | L12: =SUMIFS('Expense Details'!$V$2:$V$2955,'Expense Details'!$B$2:$B$2955,$A12,'Expense Details'!$O$2:$O$2955,"Ground Transport*")+SUMIFS('Expense Details'!$V$2:$V$2955,'Expense Details'!$B$2:$B$2955,$A12,'Expense Details'!$O$2:$O$2955,"Car Rental") -> 613.02197 | M12: =H12-I12-J12-K12-L12 -> 947.06921 | N12: =COUNTIFS('Expense Details'!$B$2:$B$2955,$A12,'Expense Details'!$AA$2:$AA$2955,"Yes") -> 6 | O12: =COUNTIFS('Expense Details'!$B$2:$B$2955,$A12,'Expense Details'!$AC$2:$AC$2955,"No") -> 6 | P12: =SUMIFS('Expense Details'!$AF$2:$AF$2955,'Expense Details'!$B$2:$B$2955,$A12) -> 4661.6606 | Q12: =IFERROR(H12/F12,0) -> 2807.2872 | R12: =IFERROR(H12/H$28,0) -> 0.017659197
A13: EMP-1409 | B13: Grace Lin | C13: Marketing | D13: Head of Marketing | E13: Diane Okafor | F13: 5 | G13: =COUNTIFS('Expense Details'!$B$2:$B$2955,$A13) -> 92 | H13: =SUMIFS('Expense Details'!$V$2:$V$2955,'Expense Details'!$B$2:$B$2955,$A13) -> 16402.288 | I13: =SUMIFS('Expense Details'!$V$2:$V$2955,'Expense Details'!$B$2:$B$2955,$A13,'Expense Details'!$O$2:$O$2955,"Airfare") -> 9156.1619 | J13: =SUMIFS('Expense Details'!$V$2:$V$2955,'Expense Details'!$B$2:$B$2955,$A13,'Expense Details'!$O$2:$O$2955,"Hotel / Lodging") -> 3058.0002 | K13: =SUMIFS('Expense Details'!$V$2:$V$2955,'Expense Details'!$B$2:$B$2955,$A13,'Expense Details'!$O$2:$O$2955,"Meals*") -> 1734.3755 | L13: =SUMIFS('Expense Details'!$V$2:$V$2955,'Expense Details'!$B$2:$B$2955,$A13,'Expense Details'!$O$2:$O$2955,"Ground Transport*")+SUMIFS('Expense Details'!$V$2:$V$2955,'Expense Details'!$B$2:$B$2955,$A13,'Expense Details'!$O$2:$O$2955,"Car Rental") -> 938.56961 | M13: =H13-I13-J13-K13-L13 -> 1515.1806 | N13: =COUNTIFS('Expense Details'!$B$2:$B$2955,$A13,'Expense Details'!$AA$2:$AA$2955,"Yes") -> 14 | O13: =COUNTIFS('Expense Details'!$B$2:$B$2955,$A13,'Expense Details'!$AC$2:$AC$2955,"No") -> 10 | P13: =SUMIFS('Expense Details'!$AF$2:$AF$2955,'Expense Details'!$B$2:$B$2955,$A13) -> 5189.985 | Q13: =IFERROR(H13/F13,0) -> 3280.4576 | R13: =IFERROR(H13/H$28,0) -> 0.03439278
A14: EMP-1236 | B14: Hannah Weiss | C14: Field Engineering | D14: Field Engineer | E14: Tomas Kovac | F14: 8 | G14: =COUNTIFS('Expense Details'!$B$2:$B$2955,$A14) -> 163 | H14: =SUMIFS('Expense Details'!$V$2:$V$2955,'Expense Details'!$B$2:$B$2955,$A14) -> 31010.728 | I14: =SUMIFS('Expense Details'!$V$2:$V$2955,'Expense Details'!$B$2:$B$2955,$A14,'Expense Details'!$O$2:$O$2955,"Airfare") -> 14829.36 | J14: =SUMIFS('Expense Details'!$V$2:$V$2955,'Expense Details'!$B$2:$B$2955,$A14,'Expense Details'!$O$2:$O$2955,"Hotel / Lodging") -> 6106.7777 | K14: =SUMIFS('Expense Details'!$V$2:$V$2955,'Expense Details'!$B$2:$B$2955,$A14,'Expense Details'!$O$2:$O$2955,"Meals*") -> 3619.6348 | L14: =SUMIFS('Expense Details'!$V$2:$V$2955,'Expense Details'!$B$2:$B$2955,$A14,'Expense Details'!$O$2:$O$2955,"Ground Transport*")+SUMIFS('Expense Details'!$V$2:$V$2955,'Expense Details'!$B$2:$B$2955,$A14,'Expense Details'!$O$2:$O$2955,"Car Rental") -> 1875.2455 | M14: =H14-I14-J14-K14-L14 -> 4579.7098 | N14: =COUNTIFS('Expense Details'!$B$2:$B$2955,$A14,'Expense Details'!$AA$2:$AA$2955,"Yes") -> 24 | O14: =COUNTIFS('Expense Details'!$B$2:$B$2955,$A14,'Expense Details'!$AC$2:$AC$2955,"No") -> 11 | P14: =SUMIFS('Expense Details'!$AF$2:$AF$2955,'Expense Details'!$B$2:$B$2955,$A14) -> 18000.695 | Q14: =IFERROR(H14/F14,0) -> 3876.341 | R14: =IFERROR(H14/H$28,0) -> 0.06502417
A15: EMP-1302 | B15: Kenji Watanabe | C15: Product | D15: Product Manager | E15: Elena Duarte | F15: 5 | G15: =COUNTIFS('Expense Details'!$B$2:$B$2955,$A15) -> 111 | H15: =SUMIFS('Expense Details'!$V$2:$V$2955,'Expense Details'!$B$2:$B$2955,$A15) -> 18037.077 | I15: =SUMIFS('Expense Details'!$V$2:$V$2955,'Expense Details'!$B$2:$B$2955,$A15,'Expense Details'!$O$2:$O$2955,"Airfare") -> 6454.8436 | J15: =SUMIFS('Expense Details'!$V$2:$V$2955,'Expense Details'!$B$2:$B$2955,$A15,'Expense Details'!$O$2:$O$2955,"Hotel / Lodging") -> 6604.9785 | K15: =SUMIFS('Expense Details'!$V$2:$V$2955,'Expense Details'!$B$2:$B$2955,$A15,'Expense Details'!$O$2:$O$2955,"Meals*") -> 2389.5842 | L15: =SUMIFS('Expense Details'!$V$2:$V$2955,'Expense Details'!$B$2:$B$2955,$A15,'Expense Details'!$O$2:$O$2955,"Ground Transport*")+SUMIFS('Expense Details'!$V$2:$V$2955,'Expense Details'!$B$2:$B$2955,$A15,'Expense Details'!$O$2:$O$2955,"Car Rental") -> 2367.2176 | M15: =H15-I15-J15-K15-L15 -> 220.45271 | N15: =COUNTIFS('Expense Details'!$B$2:$B$2955,$A15,'Expense Details'!$AA$2:$AA$2955,"Yes") -> 14 | O15: =COUNTIFS('Expense Details'!$B$2:$B$2955,$A15,'Expense Details'!$AC$2:$AC$2955,"No") -> 14 | P15: =SUMIFS('Expense Details'!$AF$2:$AF$2955,'Expense Details'!$B$2:$B$2955,$A15) -> 10842.149 | Q15: =IFERROR(H15/F15,0) -> 3607.4153 | R15: =IFERROR(H15/H$28,0) -> 0.037820651
... A27: EMP-1705 | B27: Viktor Petrov | C27: Operations | D27: Supply Chain Manager | E27: Diane Okafor | F27: 7 | G27: =COUNTIFS('Expense Details'!$B$2:$B$2955,$A27) -> 123 | H27: =SUMIFS('Expense Details'!$V$2:$V$2955,'Expense Details'!$B$2:$B$2955,$A27) -> 19907.486 | I27: =SUMIFS('Expense Details'!$V$2:$V$2955,'Expense Details'!$B$2:$B$2955,$A27,'Expense Details'!$O$2:$O$2955,"Airfare") -> 9130.0028 | J27: =SUMIFS('Expense Details'!$V$2:$V$2955,'Expense Details'!$B$2:$B$2955,$A27,'Expense Details'!$O$2:$O$2955,"Hotel / Lodging") -> 5215.6216 | K27: =SUMIFS('Expense Details'!$V$2:$V$2955,'Expense Details'!$B$2:$B$2955,$A27,'Expense Details'!$O$2:$O$2955,"Meals*") -> 2269.4788 | L27: =SUMIFS('Expense Details'!$V$2:$V$2955,'Expense Details'!$B$2:$B$2955,$A27,'Expense Details'!$O$2:$O$2955,"Ground Transport*")+SUMIFS('Expense Details'!$V$2:$V$2955,'Expense Details'!$B$2:$B$2955,$A27,'Expense Details'!$O$2:$O$2955,"Car Rental") -> 1349.1787 | M27: =H27-I27-J27-K27-L27 -> 1943.2041 | N27: =COUNTIFS('Expense Details'!$B$2:$B$2955,$A27,'Expense Details'!$AA$2:$AA$2955,"Yes") -> 13 | O27: =COUNTIFS('Expense Details'!$B$2:$B$2955,$A27,'Expense Details'!$AC$2:$AC$2955,"No") -> 10 | P27: =SUMIFS('Expense Details'!$AF$2:$AF$2955,'Expense Details'!$B$2:$B$2955,$A27) -> 6176.3175 | Q27: =IFERROR(H27/F27,0) -> 2843.9266 | R27: =IFERROR(H27/H$28,0) -> 0.041742578
A28: TOTAL | F28: =SUM(F4:F27) -> 138 | G28: =SUM(G4:G27) -> 2954 | H28: =SUM(H4:H27) -> 476910.79 | I28: =SUM(I4:I27) -> 214763.68 | J28: =SUM(J4:J27) -> 118139.44 | K28: =SUM(K4:K27) -> 60058.949 | L28: =SUM(L4:L27) -> 38733.811 | M28: =SUM(M4:M27) -> 45214.92 | ... P28: =SUM(P4:P27) -> 191871.42 | Q28: =IFERROR(H28/F28,0) -> 3455.8753 | R28: 1

Sheet Category by Month
A1: Helios Instruments Pvt. Ltd. — Travel Spend by Category and Month, 2025
A2: All amounts in USD. Live SUMIFS over the 'Expense Details' tab.
A4: Expense Category | B4: 2025-01 | C4: 2025-02 | D4: 2025-03 | E4: 2025-04 | F4: 2025-05 | G4: 2025-06 | H4: 2025-07 | I4: 2025-08 | J4: 2025-09 | K4: 2025-10 | L4: 2025-11 | M4: 2025-12 | N4: Total | O4: % of Spend | P4: Policy Limit (USD)
A5: Airfare | B5: =SUMIFS('Expense Details'!$V$2:$V$2955,'Expense Details'!$O$2:$O$2955,$A5,'Expense Details'!$N$2:$N$2955,B$4) -> 29043.984 | C5: =SUMIFS('Expense Details'!$V$2:$V$2955,'Expense Details'!$O$2:$O$2955,$A5,'Expense Details'!$N$2:$N$2955,C$4) -> 23908.967 | D5: =SUMIFS('Expense Details'!$V$2:$V$2955,'Expense Details'!$O$2:$O$2955,$A5,'Expense Details'!$N$2:$N$2955,D$4) -> 17774.913 | E5: =SUMIFS('Expense Details'!$V$2:$V$2955,'Expense Details'!$O$2:$O$2955,$A5,'Expense Details'!$N$2:$N$2955,E$4) -> 11662.551 | F5: =SUMIFS('Expense Details'!$V$2:$V$2955,'Expense Details'!$O$2:$O$2955,$A5,'Expense Details'!$N$2:$N$2955,F$4) -> 18201.883 | G5: =SUMIFS('Expense Details'!$V$2:$V$2955,'Expense Details'!$O$2:$O$2955,$A5,'Expense Details'!$N$2:$N$2955,G$4) -> 11381.979 | H5: =SUMIFS('Expense Details'!$V$2:$V$2955,'Expense Details'!$O$2:$O$2955,$A5,'Expense Details'!$N$2:$N$2955,H$4) -> 16960.942 | I5: =SUMIFS('Expense Details'!$V$2:$V$2955,'Expense Details'!$O$2:$O$2955,$A5,'Expense Details'!$N$2:$N$2955,I$4) -> 22088.682 | ... M5: =SUMIFS('Expense Details'!$V$2:$V$2955,'Expense Details'!$O$2:$O$2955,$A5,'Expense Details'!$N$2:$N$2955,M$4) -> 3998.2436 | N5: =SUM(B5:M5) -> 214763.68 | O5: =IFERROR(N5/N$23,0) -> 0.45032253 | P5: 1400
A6: Hotel / Lodging | B6: =SUMIFS('Expense Details'!$V$2:$V$2955,'Expense Details'!$O$2:$O$2955,$A6,'Expense Details'!$N$2:$N$2955,B$4) -> 16984.788 | C6: =SUMIFS('Expense Details'!$V$2:$V$2955,'Expense Details'!$O$2:$O$2955,$A6,'Expense Details'!$N$2:$N$2955,C$4) -> 10555.452 | D6: =SUMIFS('Expense Details'!$V$2:$V$2955,'Expense Details'!$O$2:$O$2955,$A6,'Expense Details'!$N$2:$N$2955,D$4) -> 11195.066 | E6: =SUMIFS('Expense Details'!$V$2:$V$2955,'Expense Details'!$O$2:$O$2955,$A6,'Expense Details'!$N$2:$N$2955,E$4) -> 8591.2616 | F6: =SUMIFS('Expense Details'!$V$2:$V$2955,'Expense Details'!$O$2:$O$2955,$A6,'Expense Details'!$N$2:$N$2955,F$4) -> 7343.4791 | G6: =SUMIFS('Expense Details'!$V$2:$V$2955,'Expense Details'!$O$2:$O$2955,$A6,'Expense Details'!$N$2:$N$2955,G$4) -> 7811.3238 | H6: =SUMIFS('Expense Details'!$V$2:$V$2955,'Expense Details'!$O$2:$O$2955,$A6,'Expense Details'!$N$2:$N$2955,H$4) -> 11049.745 | I6: =SUMIFS('Expense Details'!$V$2:$V$2955,'Expense Details'!$O$2:$O$2955,$A6,'Expense Details'!$N$2:$N$2955,I$4) -> 9857.5462 | ... M6: =SUMIFS('Expense Details'!$V$2:$V$2955,'Expense Details'!$O$2:$O$2955,$A6,'Expense Details'!$N$2:$N$2955,M$4) -> 1582.7301 | N6: =SUM(B6:M6) -> 118139.44 | O6: =IFERROR(N6/N$23,0) -> 0.2477181 | P6: 280
A7: Meals - Breakfast | B7: =SUMIFS('Expense Details'!$V$2:$V$2955,'Expense Details'!$O$2:$O$2955,$A7,'Expense Details'!$N$2:$N$2955,B$4) -> 1283.0471 | C7: =SUMIFS('Expense Details'!$V$2:$V$2955,'Expense Details'!$O$2:$O$2955,$A7,'Expense Details'!$N$2:$N$2955,C$4) -> 1040.3608 | D7: =SUMIFS('Expense Details'!$V$2:$V$2955,'Expense Details'!$O$2:$O$2955,$A7,'Expense Details'!$N$2:$N$2955,D$4) -> 949.56786 | E7: =SUMIFS('Expense Details'!$V$2:$V$2955,'Expense Details'!$O$2:$O$2955,$A7,'Expense Details'!$N$2:$N$2955,E$4) -> 1071.0766 | F7: =SUMIFS('Expense Details'!$V$2:$V$2955,'Expense Details'!$O$2:$O$2955,$A7,'Expense Details'!$N$2:$N$2955,F$4) -> 469.28599 | G7: =SUMIFS('Expense Details'!$V$2:$V$2955,'Expense Details'!$O$2:$O$2955,$A7,'Expense Details'!$N$2:$N$2955,G$4) -> 679.60546 | H7: =SUMIFS('Expense Details'!$V$2:$V$2955,'Expense Details'!$O$2:$O$2955,$A7,'Expense Details'!$N$2:$N$2955,H$4) -> 1253.8156 | I7: =SUMIFS('Expense Details'!$V$2:$V$2955,'Expense Details'!$O$2:$O$2955,$A7,'Expense Details'!$N$2:$N$2955,I$4) -> 734.26662 | ... M7: =SUMIFS('Expense Details'!$V$2:$V$2955,'Expense Details'!$O$2:$O$2955,$A7,'Expense Details'!$N$2:$N$2955,M$4) -> 317.53327 | N7: =SUM(B7:M7) -> 10689.938 | O7: =IFERROR(N7/N$23,0) -> 0.022414964 | P7: 25
A8: Meals - Lunch | B8: =SUMIFS('Expense Details'!$V$2:$V$2955,'Expense Details'!$O$2:$O$2955,$A8,'Expense Details'!$N$2:$N$2955,B$4) -> 1755.3317 | C8: =SUMIFS('Expense Details'!$V$2:$V$2955,'Expense Details'!$O$2:$O$2955,$A8,'Expense Details'!$N$2:$N$2955,C$4) -> 1755.3547 | D8: =SUMIFS('Expense Details'!$V$2:$V$2955,'Expense Details'!$O$2:$O$2955,$A8,'Expense Details'!$N$2:$N$2955,D$4) -> 1459.2512 | E8: =SUMIFS('Expense Details'!$V$2:$V$2955,'Expense Details'!$O$2:$O$2955,$A8,'Expense Details'!$N$2:$N$2955,E$4) -> 1402.478 | F8: =SUMIFS('Expense Details'!$V$2:$V$2955,'Expense Details'!$O$2:$O$2955,$A8,'Expense Details'!$N$2:$N$2955,F$4) -> 1054.1841 | G8: =SUMIFS('Expense Details'!$V$2:$V$2955,'Expense Details'!$O$2:$O$2955,$A8,'Expense Details'!$N$2:$N$2955,G$4) -> 1090.6673 | H8: =SUMIFS('Expense Details'!$V$2:$V$2955,'Expense Details'!$O$2:$O$2955,$A8,'Expense Details'!$N$2:$N$2955,H$4) -> 1948.2299 | I8: =SUMIFS('Expense Details'!$V$2:$V$2955,'Expense Details'!$O$2:$O$2955,$A8,'Expense Details'!$N$2:$N$2955,I$4) -> 1147.9359 | ... M8: =SUMIFS('Expense Details'!$V$2:$V$2955,'Expense Details'!$O$2:$O$2955,$A8,'Expense Details'!$N$2:$N$2955,M$4) -> 584.44761 | N8: =SUM(B8:M8) -> 16392.903 | O8: =IFERROR(N8/N$23,0) -> 0.034373102 | P8: 35
A9: Meals - Dinner | B9: =SUMIFS('Expense Details'!$V$2:$V$2955,'Expense Details'!$O$2:$O$2955,$A9,'Expense Details'!$N$2:$N$2955,B$4) -> 4080.4344 | C9: =SUMIFS('Expense Details'!$V$2:$V$2955,'Expense Details'!$O$2:$O$2955,$A9,'Expense Details'!$N$2:$N$2955,C$4) -> 3452.4657 | D9: =SUMIFS('Expense Details'!$V$2:$V$2955,'Expense Details'!$O$2:$O$2955,$A9,'Expense Details'!$N$2:$N$2955,D$4) -> 2878.0408 | E9: =SUMIFS('Expense Details'!$V$2:$V$2955,'Expense Details'!$O$2:$O$2955,$A9,'Expense Details'!$N$2:$N$2955,E$4) -> 2472.716 | F9: =SUMIFS('Expense Details'!$V$2:$V$2955,'Expense Details'!$O$2:$O$2955,$A9,'Expense Details'!$N$2:$N$2955,F$4) -> 1783.9569 | G9: =SUMIFS('Expense Details'!$V$2:$V$2955,'Expense Details'!$O$2:$O$2955,$A9,'Expense Details'!$N$2:$N$2955,G$4) -> 1898.0337 | H9: =SUMIFS('Expense Details'!$V$2:$V$2955,'Expense Details'!$O$2:$O$2955,$A9,'Expense Details'!$N$2:$N$2955,H$4) -> 3517.3921 | I9: =SUMIFS('Expense Details'!$V$2:$V$2955,'Expense Details'!$O$2:$O$2955,$A9,'Expense Details'!$N$2:$N$2955,I$4) -> 2700.2202 | ... M9: =SUMIFS('Expense Details'!$V$2:$V$2955,'Expense Details'!$O$2:$O$2955,$A9,'Expense Details'!$N$2:$N$2955,M$4) -> 1432.2621 | N9: =SUM(B9:M9) -> 32976.108 | O9: =IFERROR(N9/N$23,0) -> 0.069145233 | P9: 75
A10: Client Entertainment | B10: =SUMIFS('Expense Details'!$V$2:$V$2955,'Expense Details'!$O$2:$O$2955,$A10,'Expense Details'!$N$2:$N$2955,B$4) -> 542.08348 | C10: =SUMIFS('Expense Details'!$V$2:$V$2955,'Expense Details'!$O$2:$O$2955,$A10,'Expense Details'!$N$2:$N$2955,C$4) -> 667.46956 | D10: =SUMIFS('Expense Details'!$V$2:$V$2955,'Expense Details'!$O$2:$O$2955,$A10,'Expense Details'!$N$2:$N$2955,D$4) -> 388.76806 | E10: =SUMIFS('Expense Details'!$V$2:$V$2955,'Expense Details'!$O$2:$O$2955,$A10,'Expense Details'!$N$2:$N$2955,E$4) -> 191.98475 | F10: =SUMIFS('Expense Details'!$V$2:$V$2955,'Expense Details'!$O$2:$O$2955,$A10,'Expense Details'!$N$2:$N$2955,F$4) -> 423.16596 | G10: =SUMIFS('Expense Details'!$V$2:$V$2955,'Expense Details'!$O$2:$O$2955,$A10,'Expense Details'!$N$2:$N$2955,G$4) -> 512.22748 | H10: =SUMIFS('Expense Details'!$V$2:$V$2955,'Expense Details'!$O$2:$O$2955,$A10,'Expense Details'!$N$2:$N$2955,H$4) -> 983.26289 | I10: =SUMIFS('Expense Details'!$V$2:$V$2955,'Expense Details'!$O$2:$O$2955,$A10,'Expense Details'!$N$2:$N$2955,I$4) -> 368.14698 | ... M10: =SUMIFS('Expense Details'!$V$2:$V$2955,'Expense Details'!$O$2:$O$2955,$A10,'Expense Details'!$N$2:$N$2955,M$4) -> 152.81016 | N10: =SUM(B10:M10) -> 5549.6711 | O10: =IFERROR(N10/N$23,0) -> 0.011636707 | P10: 200
A11: Ground Transport - Taxi | B11: =SUMIFS('Expense Details'!$V$2:$V$2955,'Expense Details'!$O$2:$O$2955,$A11,'Expense Details'!$N$2:$N$2955,B$4) -> 2406.2387 | C11: =SUMIFS('Expense Details'!$V$2:$V$2955,'Expense Details'!$O$2:$O$2955,$A11,'Expense Details'!$N$2:$N$2955,C$4) -> 1938.5151 | D11: =SUMIFS('Expense Details'!$V$2:$V$2955,'Expense Details'!$O$2:$O$2955,$A11,'Expense Details'!$N$2:$N$2955,D$4) -> 1723.5512 | E11: =SUMIFS('Expense Details'!$V$2:$V$2955,'Expense Details'!$O$2:$O$2955,$A11,'Expense Details'!$N$2:$N$2955,E$4) -> 1900.3632 | F11: =SUMIFS('Expense Details'!$V$2:$V$2955,'Expense Details'!$O$2:$O$2955,$A11,'Expense Details'!$N$2:$N$2955,F$4) -> 930.68405 | G11: =SUMIFS('Expense Details'!$V$2:$V$2955,'Expense Details'!$O$2:$O$2955,$A11,'Expense Details'!$N$2:$N$2955,G$4) -> 1337.2164 | H11: =SUMIFS('Expense Details'!$V$2:$V$2955,'Expense Details'!$O$2:$O$2955,$A11,'Expense Details'!$N$2:$N$2955,H$4) -> 1990.4766 | I11: =SUMIFS('Expense Details'!$V$2:$V$2955,'Expense Details'!$O$2:$O$2955,$A11,'Expense Details'!$N$2:$N$2955,I$4) -> 1162.5982 | ... M11: =SUMIFS('Expense Details'!$V$2:$V$2955,'Expense Details'!$O$2:$O$2955,$A11,'Expense Details'!$N$2:$N$2955,M$4) -> 500.19314 | N11: =SUM(B11:M11) -> 18273.934 | O11: =IFERROR(N11/N$23,0) -> 0.038317301 | P11: 60
A12: Ground Transport - Rail | B12: =SUMIFS('Expense Details'!$V$2:$V$2955,'Expense Details'!$O$2:$O$2955,$A12,'Expense Details'!$N$2:$N$2955,B$4) -> 684.5987 | C12: =SUMIFS('Expense Details'!$V$2:$V$2955,'Expense Details'!$O$2:$O$2955,$A12,'Expense Details'!$N$2:$N$2955,C$4) -> 529.57346 | D12: =SUMIFS('Expense Details'!$V$2:$V$2955,'Expense Details'!$O$2:$O$2955,$A12,'Expense Details'!$N$2:$N$2955,D$4) -> 279.16814 | E12: =SUMIFS('Expense Details'!$V$2:$V$2955,'Expense Details'!$O$2:$O$2955,$A12,'Expense Details'!$N$2:$N$2955,E$4) -> 331.36226 | F12: =SUMIFS('Expense Details'!$V$2:$V$2955,'Expense Details'!$O$2:$O$2955,$A12,'Expense Details'!$N$2:$N$2955,F$4) -> 369.68603 | G12: =SUMIFS('Expense Details'!$V$2:$V$2955,'Expense Details'!$O$2:$O$2955,$A12,'Expense Details'!$N$2:$N$2955,G$4) -> 238.68144 | H12: =SUMIFS('Expense Details'!$V$2:$V$2955,'Expense Details'!$O$2:$O$2955,$A12,'Expense Details'!$N$2:$N$2955,H$4) -> 172.55 | I12: =SUMIFS('Expense Details'!$V$2:$V$2955,'Expense Details'!$O$2:$O$2955,$A12,'Expense Details'!$N$2:$N$2955,I$4) -> 89.13275 | ... M12: =SUMIFS('Expense Details'!$V$2:$V$2955,'Expense Details'!$O$2:$O$2955,$A12,'Expense Details'!$N$2:$N$2955,M$4) -> 146.75524 | N12: =SUM(B12:M12) -> 4176.0196 | O12: =IFERROR(N12/N$23,0) -> 0.0087563957 | P12: 150
A13: Car Rental | B13: =SUMIFS('Expense Details'!$V$2:$V$2955,'Expense Details'!$O$2:$O$2955,$A13,'Expense Details'!$N$2:$N$2955,B$4) -> 436.3343 | C13: =SUMIFS('Expense Details'!$V$2:$V$2955,'Expense Details'!$O$2:$O$2955,$A13,'Expense Details'!$N$2:$N$2955,C$4) -> 1211.8291 | D13: =SUMIFS('Expense Details'!$V$2:$V$2955,'Expense Details'!$O$2:$O$2955,$A13,'Expense Details'!$N$2:$N$2955,D$4) -> 1048.8087 | E13: =SUMIFS('Expense Details'!$V$2:$V$2955,'Expense Details'!$O$2:$O$2955,$A13,'Expense Details'!$N$2:$N$2955,E$4) -> 2065.8875 | F13: =SUMIFS('Expense Details'!$V$2:$V$2955,'Expense Details'!$O$2:$O$2955,$A13,'Expense Details'!$N$2:$N$2955,F$4) -> 903.05824 | G13: =SUMIFS('Expense Details'!$V$2:$V$2955,'Expense Details'!$O$2:$O$2955,$A13,'Expense Details'!$N$2:$N$2955,G$4) -> 532.48174 | H13: =SUMIFS('Expense Details'!$V$2:$V$2955,'Expense Details'!$O$2:$O$2955,$A13,'Expense Details'!$N$2:$N$2955,H$4) -> 2515.2683 | I13: =SUMIFS('Expense Details'!$V$2:$V$2955,'Expense Details'!$O$2:$O$2955,$A13,'Expense Details'!$N$2:$N$2955,I$4) -> 2273.8113 | ... M13: =SUMIFS('Expense Details'!$V$2:$V$2955,'Expense Details'!$O$2:$O$2955,$A13,'Expense Details'!$N$2:$N$2955,M$4) -> 258.59456 | N13: =SUM(B13:M13) -> 16283.857 | O13: =IFERROR(N13/N$23,0) -> 0.034144451 | P13: 120
A14: Fuel / Mileage | B14: =SUMIFS('Expense Details'!$V$2:$V$2955,'Expense Details'!$O$2:$O$2955,$A14,'Expense Details'!$N$2:$N$2955,B$4) -> 98.64025 | C14: =SUMIFS('Expense Details'!$V$2:$V$2955,'Expense Details'!$O$2:$O$2955,$A14,'Expense Details'!$N$2:$N$2955,C$4) -> 151.58576 | D14: =SUMIFS('Expense Details'!$V$2:$V$2955,'Expense Details'!$O$2:$O$2955,$A14,'Expense Details'!$N$2:$N$2955,D$4) -> 100.15875 | E14: =SUMIFS('Expense Details'!$V$2:$V$2955,'Expense Details'!$O$2:$O$2955,$A14,'Expense Details'!$N$2:$N$2955,E$4) -> 185.10505 | F14: =SUMIFS('Expense Details'!$V$2:$V$2955,'Expense Details'!$O$2:$O$2955,$A14,'Expense Details'!$N$2:$N$2955,F$4) -> 190.98309 | G14: =SUMIFS('Expense Details'!$V$2:$V$2955,'Expense Details'!$O$2:$O$2955,$A14,'Expense Details'!$N$2:$N$2955,G$4) -> 182.88394 | H14: =SUMIFS('Expense Details'!$V$2:$V$2955,'Expense Details'!$O$2:$O$2955,$A14,'Expense Details'!$N$2:$N$2955,H$4) -> 96.61946 | I14: =SUMIFS('Expense Details'!$V$2:$V$2955,'Expense Details'!$O$2:$O$2955,$A14,'Expense Details'!$N$2:$N$2955,I$4) -> 120.40267 | ... M14: =SUMIFS('Expense Details'!$V$2:$V$2955,'Expense Details'!$O$2:$O$2955,$A14,'Expense Details'!$N$2:$N$2955,M$4) -> 106.86816 | N14: =SUM(B14:M14) -> 1926.7333 | O14: =IFERROR(N14/N$23,0) -> 0.0040400287 | P14: 90
A15: Parking & Tolls | B15: =SUMIFS('Expense Details'!$V$2:$V$2955,'Expense Details'!$O$2:$O$2955,$A15,'Expense Details'!$N$2:$N$2955,B$4) -> 63.44465 | C15: =SUMIFS('Expense Details'!$V$2:$V$2955,'Expense Details'!$O$2:$O$2955,$A15,'Expense Details'!$N$2:$N$2955,C$4) -> 46.70308 | D15: =SUMIFS('Expense Details'!$V$2:$V$2955,'Expense Details'!$O$2:$O$2955,$A15,'Expense Details'!$N$2:$N$2955,D$4) -> 69.55445 | E15: =SUMIFS('Expense Details'!$V$2:$V$2955,'Expense Details'!$O$2:$O$2955,$A15,'Expense Details'!$N$2:$N$2955,E$4) -> 63.61624 | F15: =SUMIFS('Expense Details'!$V$2:$V$2955,'Expense Details'!$O$2:$O$2955,$A15,'Expense Details'!$N$2:$N$2955,F$4) -> 37.77592 | G15: =SUMIFS('Expense Details'!$V$2:$V$2955,'Expense Details'!$O$2:$O$2955,$A15,'Expense Details'!$N$2:$N$2955,G$4) -> 16.78768 | H15: =SUMIFS('Expense Details'!$V$2:$V$2955,'Expense Details'!$O$2:$O$2955,$A15,'Expense Details'!$N$2:$N$2955,H$4) -> 41.2332 | I15: =SUMIFS('Expense Details'!$V$2:$V$2955,'Expense Details'!$O$2:$O$2955,$A15,'Expense Details'!$N$2:$N$2955,I$4) -> 49.09336 | ... M15: =SUMIFS('Expense Details'!$V$2:$V$2955,'Expense Details'!$O$2:$O$2955,$A15,'Expense Details'!$N$2:$N$2955,M$4) -> 28.66074 | N15: =SUM(B15:M15) -> 650.42794 | O15: =IFERROR(N15/N$23,0) -> 0.0013638357 | P15: 45
A16: Conference / Event Fee | B16: =SUMIFS('Expense Details'!$V$2:$V$2955,'Expense Details'!$O$2:$O$2955,$A16,'Expense Details'!$N$2:$N$2955,B$4) -> 6093.3174 | C16: =SUMIFS('Expense Details'!$V$2:$V$2955,'Expense Details'!$O$2:$O$2955,$A16,'Expense Details'!$N$2:$N$2955,C$4) -> 1124.7426 | D16: =SUMIFS('Expense Details'!$V$2:$V$2955,'Expense Details'!$O$2:$O$2955,$A16,'Expense Details'!$N$2:$N$2955,D$4) -> 689.18827 | E16: =SUMIFS('Expense Details'!$V$2:$V$2955,'Expense Details'!$O$2:$O$2955,$A16,'Expense Details'!$N$2:$N$2955,E$4) -> 2325.5933 | F16: =SUMIFS('Expense Details'!$V$2:$V$2955,'Expense Details'!$O$2:$O$2955,$A16,'Expense Details'!$N$2:$N$2955,F$4) -> 1717.6645 | G16: =SUMIFS('Expense Details'!$V$2:$V$2955,'Expense Details'!$O$2:$O$2955,$A16,'Expense Details'!$N$2:$N$2955,G$4) -> 0 | H16: =SUMIFS('Expense Details'!$V$2:$V$2955,'Expense Details'!$O$2:$O$2955,$A16,'Expense Details'!$N$2:$N$2955,H$4) -> 3318.152 | I16: =SUMIFS('Expense Details'!$V$2:$V$2955,'Expense Details'!$O$2:$O$2955,$A16,'Expense Details'!$N$2:$N$2955,I$4) -> 4144.2712 | ... M16: =SUMIFS('Expense Details'!$V$2:$V$2955,'Expense Details'!$O$2:$O$2955,$A16,'Expense Details'!$N$2:$N$2955,M$4) -> 0 | N16: =SUM(B16:M16) -> 25304.574 | O16: =IFERROR(N16/N$23,0) -> 0.053059345 | P16: 1200
... A22: Office Supplies | B22: =SUMIFS('Expense Details'!$V$2:$V$2955,'Expense Details'!$O$2:$O$2955,$A22,'Expense Details'!$N$2:$N$2955,B$4) -> 21.63 | C22: =SUMIFS('Expense Details'!$V$2:$V$2955,'Expense Details'!$O$2:$O$2955,$A22,'Expense Details'!$N$2:$N$2955,C$4) -> 134.02908 | D22: =SUMIFS('Expense Details'!$V$2:$V$2955,'Expense Details'!$O$2:$O$2955,$A22,'Expense Details'!$N$2:$N$2955,D$4) -> 74.44 | E22: =SUMIFS('Expense Details'!$V$2:$V$2955,'Expense Details'!$O$2:$O$2955,$A22,'Expense Details'!$N$2:$N$2955,E$4) -> 25.48299 | F22: =SUMIFS('Expense Details'!$V$2:$V$2955,'Expense Details'!$O$2:$O$2955,$A22,'Expense Details'!$N$2:$N$2955,F$4) -> 110.91696 | G22: =SUMIFS('Expense Details'!$V$2:$V$2955,'Expense Details'!$O$2:$O$2955,$A22,'Expense Details'!$N$2:$N$2955,G$4) -> 75.74 | H22: =SUMIFS('Expense Details'!$V$2:$V$2955,'Expense Details'!$O$2:$O$2955,$A22,'Expense Details'!$N$2:$N$2955,H$4) -> 0 | I22: =SUMIFS('Expense Details'!$V$2:$V$2955,'Expense Details'!$O$2:$O$2955,$A22,'Expense Details'!$N$2:$N$2955,I$4) -> 51.212 | ... M22: =SUMIFS('Expense Details'!$V$2:$V$2955,'Expense Details'!$O$2:$O$2955,$A22,'Expense Details'!$N$2:$N$2955,M$4) -> 59.5448 | N22: =SUM(B22:M22) -> 693.6501 | O22: =IFERROR(N22/N$23,0) -> 0.0014544651 | P22: 60
A23: TOTAL | B23: =SUM(B5:B22) -> 64685.831 | C23: =SUM(C5:C22) -> 47972.754 | D23: =SUM(D5:D22) -> 39565.044 | E23: =SUM(E5:E22) -> 32604.019 | F23: =SUM(F5:F22) -> 34536.364 | G23: =SUM(G5:G22) -> 26272.705 | H23: =SUM(H5:H22) -> 44977.533 | I23: =SUM(I5:I22) -> 45959.109 | ... N23: =SUM(N5:N22) -> 476910.79 | O23: 1

Sheet Policy Exceptions
A1: Helios Instruments Pvt. Ltd. — Policy Exceptions & Audit Flags, 2025
A2: Rows flagged where the claim exceeds its category limit, or where no receipt was attached. Every cell links live to 'Expense Details'.
A4: Expense ID | B4: Employee Name | C4: Department | D4: Trip ID | E4: Expense Date | F4: Category | G4: Merchant / Vendor | H4: Amount (USD) | I4: Policy Limit (USD) | J4: Variance (USD) | K4: % Over Limit | L4: Receipt Attached | M4: Flag Reason | N4: Approval Status | O4: Manager / Approver
A5: ='Expense Details'!A2 -> EXP-00001 | B5: ='Expense Details'!C2 -> Rohit Malhotra | C5: ='Expense Details'!D2 -> Sales | D5: ='Expense Details'!G2 -> TRP-2025-061 | E5: ='Expense Details'!M2 -> 45658 | F5: ='Expense Details'!O2 -> Airfare | G5: ='Expense Details'!Q2 -> Lufthansa | H5: ='Expense Details'!V2 -> 1551.5347 | I5: ='Expense Details'!Z2 -> 1400 | J5: =H5-I5 -> 151.53472 | K5: =IFERROR(MAX(0,H5/I5-1),0) -> 0.10823909 | L5: ='Expense Details'!AC2 -> Yes | M5: Exceeds category policy limit | N5: ='Expense Details'!AG2 -> Approved | O5: ='Expense Details'!F2 -> Ananya Sengupta
A6: ='Expense Details'!A4 -> EXP-00003 | B6: ='Expense Details'!C4 -> Rohit Malhotra | C6: ='Expense Details'!D4 -> Sales | D6: ='Expense Details'!G4 -> TRP-2025-061 | E6: ='Expense Details'!M4 -> 45658 | F6: ='Expense Details'!O4 -> Meals - Breakfast | G6: ='Expense Details'!Q4 -> Cafe Nero | H6: ='Expense Details'!V4 -> 30.80784 | I6: ='Expense Details'!Z4 -> 25 | J6: =H6-I6 -> 5.80784 | K6: =IFERROR(MAX(0,H6/I6-1),0) -> 0.2323136 | L6: ='Expense Details'!AC4 -> Yes | M6: Exceeds category policy limit | N6: ='Expense Details'!AG4 -> Approved | O6: ='Expense Details'!F4 -> Ananya Sengupta
A7: ='Expense Details'!A13 -> EXP-00012 | B7: ='Expense Details'!C13 -> Rohit Malhotra | C7: ='Expense Details'!D13 -> Sales | D7: ='Expense Details'!G13 -> TRP-2025-061 | E7: ='Expense Details'!M13 -> 45660 | F7: ='Expense Details'!O13 -> Meals - Lunch | G7: ='Expense Details'!Q13 -> Sweetgreen | H7: ='Expense Details'!V13 -> 45.19416 | I7: ='Expense Details'!Z13 -> 35 | J7: =H7-I7 -> 10.19416 | K7: =IFERROR(MAX(0,H7/I7-1),0) -> 0.29126171 | L7: ='Expense Details'!AC13 -> Yes | M7: Exceeds category policy limit | N7: ='Expense Details'!AG13 -> Approved | O7: ='Expense Details'!F13 -> Ananya Sengupta
A8: ='Expense Details'!A14 -> EXP-00013 | B8: ='Expense Details'!C14 -> Rohit Malhotra | C8: ='Expense Details'!D14 -> Sales | D8: ='Expense Details'!G14 -> TRP-2025-061 | E8: ='Expense Details'!M14 -> 45661 | F8: ='Expense Details'!O14 -> Meals - Breakfast | G8: ='Expense Details'!Q14 -> Starbucks | H8: ='Expense Details'!V14 -> 9.7944 | I8: ='Expense Details'!Z14 -> 25 | J8: =H8-I8 -> -15.2056 | K8: =IFERROR(MAX(0,H8/I8-1),0) -> 0 | L8: ='Expense Details'!AC14 -> No | M8: No receipt attached | N8: ='Expense Details'!AG14 -> Approved | O8: ='Expense Details'!F14 -> Ananya Sengupta
A9: ='Expense Details'!A16 -> EXP-00015 | B9: ='Expense Details'!C16 -> Rohit Malhotra | C9: ='Expense Details'!D16 -> Sales | D9: ='Expense Details'!G16 -> TRP-2025-061 | E9: ='Expense Details'!M16 -> 45661 | F9: ='Expense Details'!O16 -> Meals - Lunch | G9: ='Expense Details'!Q16 -> Local Bistro | H9: ='Expense Details'!V16 -> 30.69336 | I9: ='Expense Details'!Z16 -> 35 | J9: =H9-I9 -> -4.30664 | K9: =IFERROR(MAX(0,H9/I9-1),0) -> 0 | L9: ='Expense Details'!AC16 -> No | M9: No receipt attached | N9: ='Expense Details'!AG16 -> Approved | O9: ='Expense Details'!F16 -> Ananya Sengupta
A10: ='Expense Details'!A20 -> EXP-00019 | B10: ='Expense Details'!C20 -> Samuel Adeyemi | C10: ='Expense Details'!D20 -> Field Engineering | D10: ='Expense Details'!G20 -> TRP-2025-116 | E10: ='Expense Details'!M20 -> 45661 | F10: ='Expense Details'!O20 -> Meals - Dinner | G10: ='Expense Details'!Q20 -> Osteria Vela | H10: ='Expense Details'!V20 -> 58.64581 | I10: ='Expense Details'!Z20 -> 75 | J10: =H10-I10 -> -16.35419 | K10: =IFERROR(MAX(0,H10/I10-1),0) -> 0 | L10: ='Expense Details'!AC20 -> No | M10: No receipt attached | N10: ='Expense Details'!AG20 -> Pending Approval | O10: ='Expense Details'!F20 -> Tomas Kovac
A11: ='Expense Details'!A27 -> EXP-00026 | B11: ='Expense Details'!C27 -> Priya Nair | C11: ='Expense Details'!D27 -> Field Engineering | D11: ='Expense Details'!G27 -> TRP-2025-109 | E11: ='Expense Details'!M27 -> 45662 | F11: ='Expense Details'!O27 -> Meals - Lunch | G11: ='Expense Details'!Q27 -> Local Bistro | H11: ='Expense Details'!V27 -> 44.1595 | I11: ='Expense Details'!Z27 -> 35 | J11: =H11-I11 -> 9.1595 | K11: =IFERROR(MAX(0,H11/I11-1),0) -> 0.2617 | L11: ='Expense Details'!AC27 -> Yes | M11: Exceeds category policy limit | N11: ='Expense Details'!AG27 -> Approved | O11: ='Expense Details'!F27 -> Tomas Kovac
A12: ='Expense Details'!A31 -> EXP-00030 | B12: ='Expense Details'!C31 -> Samuel Adeyemi | C12: ='Expense Details'!D31 -> Field Engineering | D12: ='Expense Details'!G31 -> TRP-2025-116 | E12: ='Expense Details'!M31 -> 45662 | F12: ='Expense Details'!O31 -> Meals - Dinner | G12: ='Expense Details'!Q31 -> The Grill House | H12: ='Expense Details'!V31 -> 37.36202 | I12: ='Expense Details'!Z31 -> 75 | J12: =H12-I12 -> -37.63798 | K12: =IFERROR(MAX(0,H12/I12-1),0) -> 0 | L12: ='Expense Details'!AC31 -> No | M12: No receipt attached | N12: ='Expense Details'!AG31 -> Pending Approval | O12: ='Expense Details'!F31 -> Tomas Kovac
A13: ='Expense Details'!A35 -> EXP-00034 | B13: ='Expense Details'!C35 -> Priya Nair | C13: ='Expense Details'!D35 -> Field Engineering | D13: ='Expense Details'!G35 -> TRP-2025-109 | E13: ='Expense Details'!M35 -> 45663 | F13: ='Expense Details'!O35 -> Meals - Dinner | G13: ='Expense Details'!Q35 -> The Grill House | H13: ='Expense Details'!V35 -> 52.95885 | I13: ='Expense Details'!Z35 -> 75 | J13: =H13-I13 -> -22.04115 | K13: =IFERROR(MAX(0,H13/I13-1),0) -> 0 | L13: ='Expense Details'!AC35 -> No | M13: No receipt attached | N13: ='Expense Details'!AG35 -> Approved | O13: ='Expense Details'!F35 -> Tomas Kovac
A14: ='Expense Details'!A50 -> EXP-00049 | B14: ='Expense Details'!C50 -> Samuel Adeyemi | C14: ='Expense Details'!D50 -> Field Engineering | D14: ='Expense Details'!G50 -> TRP-2025-116 | E14: ='Expense Details'!M50 -> 45665 | F14: ='Expense Details'!O50 -> Ground Transport - Taxi | G14: ='Expense Details'!Q50 -> Lyft | H14: ='Expense Details'!V50 -> 75.01002 | I14: ='Expense Details'!Z50 -> 60 | J14: =H14-I14 -> 15.01002 | K14: =IFERROR(MAX(0,H14/I14-1),0) -> 0.250167 | L14: ='Expense Details'!AC50 -> Yes | M14: Exceeds category policy limit | N14: ='Expense Details'!AG50 -> Pending Approval | O14: ='Expense Details'!F50 -> Tomas Kovac
A15: ='Expense Details'!A61 -> EXP-00060 | B15: ='Expense Details'!C61 -> Laura Bianchi | C15: ='Expense Details'!D61 -> Customer Success | D15: ='Expense Details'!G61 -> TRP-2025-117 | E15: ='Expense Details'!M61 -> 45667 | F15: ='Expense Details'!O61 -> Meals - Dinner | G15: ='Expense Details'!Q61 -> Osteria Vela | H15: ='Expense Details'!V61 -> 43.3217 | I15: ='Expense Details'!Z61 -> 75 | J15: =H15-I15 -> -31.6783 | K15: =IFERROR(MAX(0,H15/I15-1),0) -> 0 | L15: ='Expense Details'!AC61 -> No | M15: No receipt attached | N15: ='Expense Details'!AG61 -> Approved | O15: ='Expense Details'!F61 -> Sneha Iyer
A16: ='Expense Details'!A68 -> EXP-00067 | B16: ='Expense Details'!C68 -> Laura Bianchi | C16: ='Expense Details'!D68 -> Customer Success | D16: ='Expense Details'!G68 -> TRP-2025-117 | E16: ='Expense Details'!M68 -> 45668 | F16: ='Expense Details'!O68 -> Meals - Breakfast | G16: ='Expense Details'!Q68 -> Cafe Nero | H16: ='Expense Details'!V68 -> 30.2348 | I16: ='Expense Details'!Z68 -> 25 | J16: =H16-I16 -> 5.2348 | K16: =IFERROR(MAX(0,H16/I16-1),0) -> 0.209392 | L16: ='Expense Details'!AC68 -> Yes | M16: Exceeds category policy limit | N16: ='Expense Details'!AG68 -> Approved | O16: ='Expense Details'!F68 -> Sneha Iyer
A17: ='Expense Details'!A72 -> EXP-00071 | B17: ='Expense Details'!C72 -> Laura Bianchi | C17: ='Expense Details'!D72 -> Customer Success | D17: ='Expense Details'!G72 -> TRP-2025-117 | E17: ='Expense Details'!M72 -> 45669 | F17: ='Expense Details'!O72 -> Meals - Breakfast | G17: ='Expense Details'!Q72 -> Hotel Restaurant | H17: ='Expense Details'!V72 -> 28.38115 | I17: ='Expense Details'!Z72 -> 25 | J17: =H17-I17 -> 3.38115 | K17: =IFERROR(MAX(0,H17/I17-1),0) -> 0.135246 | L17: ='Expense Details'!AC72 -> Yes | M17: Exceeds category policy limit | N17: ='Expense Details'!AG72 -> Approved | O17: ='Expense Details'!F72 -> Sneha Iyer
A18: ='Expense Details'!A79 -> EXP-00078 | B18: ='Expense Details'!C79 -> Ravi Chandra | C18: ='Expense Details'!D79 -> Field Engineering | D18: ='Expense Details'!G79 -> TRP-2025-123 | E18: ='Expense Details'!M79 -> 45670 | F18: ='Expense Details'!O79 -> Airfare | G18: ='Expense Details'!Q79 -> British Airways | H18: ='Expense Details'!V79 -> 3160.1392 | I18: ='Expense Details'!Z79 -> 1400 | J18: =H18-I18 -> 1760.1392 | K18: =IFERROR(MAX(0,H18/I18-1),0) -> 1.2572423 | L18: ='Expense Details'!AC79 -> Yes | M18: Exceeds category policy limit | N18: ='Expense Details'!AG79 -> Approved | O18: ='Expense Details'!F79 -> Tomas Kovac
A19: ='Expense Details'!A90 -> EXP-00089 | B19: ='Expense Details'!C90 -> Ravi Chandra | C19: ='Expense Details'!D90 -> Field Engineering | D19: ='Expense Details'!G90 -> TRP-2025-123 | E19: ='Expense Details'!M90 -> 45671 | F19: ='Expense Details'!O90 -> Internet / Roaming | G19: ='Expense Details'!Q90 -> Vodafone Roaming | H19: ='Expense Details'!V90 -> 28.94445 | I19: ='Expense Details'!Z90 -> 55 | J19: =H19-I19 -> -26.05555 | K19: =IFERROR(MAX(0,H19/I19-1),0) -> 0 | L19: ='Expense Details'!AC90 -> No | M19: No receipt attached | N19: ='Expense Details'!AG90 -> Approved | O19: ='Expense Details'!F90 -> Tomas Kovac
A20: ='Expense Details'!A93 -> EXP-00092 | B20: ='Expense Details'!C93 -> Marcus Bell | C20: ='Expense Details'!D93 -> Sales | D20: ='Expense Details'!G93 -> TRP-2025-131 | E20: ='Expense Details'!M93 -> 45671 | F20: ='Expense Details'!O93 -> Airfare | G20: ='Expense Details'!Q93 -> British Airways | H20: ='Expense Details'!V93 -> 1959.4136 | I20: ='Expense Details'!Z93 -> 1400 | J20: =H20-I20 -> 559.41362 | K20: =IFERROR(MAX(0,H20/I20-1),0) -> 0.39958115 | L20: ='Expense Details'!AC93 -> Yes | M20: Exceeds category policy limit | N20: ='Expense Details'!AG93 -> Approved | O20: ='Expense Details'!F93 -> Diane Okafor
A21: ='Expense Details'!A95 -> EXP-00094 | B21: ='Expense Details'!C95 -> Marcus Bell | C21: ='Expense Details'!D95 -> Sales | D21: ='Expense Details'!G95 -> TRP-2025-131 | E21: ='Expense Details'!M95 -> 45671 | F21: ='Expense Details'!O95 -> Meals - Lunch | G21: ='Expense Details'!Q95 -> Sweetgreen | H21: ='Expense Details'!V95 -> 20.787382 | I21: ='Expense Details'!Z95 -> 35 | J21: =H21-I21 -> -14.212618 | K21: =IFERROR(MAX(0,H21/I21-1),0) -> 0 | L21: ='Expense Details'!AC95 -> No | M21: No receipt attached | N21: ='Expense Details'!AG95 -> Approved | O21: ='Expense Details'!F95 -> Diane Okafor
A22: ='Expense Details'!A101 -> EXP-00100 | B22: ='Expense Details'!C101 -> Ravi Chandra | C22: ='Expense Details'!D101 -> Field Engineering | D22: ='Expense Details'!G101 -> TRP-2025-123 | E22: ='Expense Details'!M101 -> 45672 | F22: ='Expense Details'!O101 -> Meals - Lunch | G22: ='Expense Details'!Q101 -> Food Court | H22: ='Expense Details'!V101 -> 17.35095 | I22: ='Expense Details'!Z101 -> 35 | J22: =H22-I22 -> -17.64905 | K22: =IFERROR(MAX(0,H22/I22-1),0) -> 0 | L22: ='Expense Details'!AC101 -> No | M22: No receipt attached | N22: ='Expense Details'!AG101 -> Approved | O22: ='Expense Details'!F101 -> Tomas Kovac
A23: ='Expense Details'!A110 -> EXP-00109 | B23: ='Expense Details'!C110 -> Ravi Chandra | C23: ='Expense Details'!D110 -> Field Engineering | D23: ='Expense Details'!G110 -> TRP-2025-123 | E23: ='Expense Details'!M110 -> 45673 | F23: ='Expense Details'!O110 -> Meals - Dinner | G23: ='Expense Details'!Q110 -> Brasserie Lyon | H23: ='Expense Details'!V110 -> 89.0014 | I23: ='Expense Details'!Z110 -> 75 | J23: =H23-I23 -> 14.0014 | K23: =IFERROR(MAX(0,H23/I23-1),0) -> 0.18668533 | L23: ='Expense Details'!AC110 -> No | M23: Exceeds category policy limit + No receipt attached | N23: ='Expense Details'!AG110 -> Approved | O23: ='Expense Details'!F110 -> Tomas Kovac
A24: ='Expense Details'!A120 -> EXP-00119 | B24: ='Expense Details'!C120 -> Ravi Chandra | C24: ='Expense Details'!D120 -> Field Engineering | D24: ='Expense Details'!G120 -> TRP-2025-123 | E24: ='Expense Details'!M120 -> 45674 | F24: ='Expense Details'!O120 -> Meals - Breakfast | G24: ='Expense Details'!Q120 -> Starbucks | H24: ='Expense Details'!V120 -> 17.8553 | I24: ='Expense Details'!Z120 -> 25 | J24: =H24-I24 -> -7.1447 | K24: =IFERROR(MAX(0,H24/I24-1),0) -> 0 | L24: ='Expense Details'!AC120 -> No | M24: No receipt attached | N24: ='Expense Details'!AG120 -> Approved | O24: ='Expense Details'!F120 -> Tomas Kovac
A25: ='Expense Details'!A133 -> EXP-00132 | B25: ='Expense Details'!C133 -> Ravi Chandra | C25: ='Expense Details'!D133 -> Field Engineering | D25: ='Expense Details'!G133 -> TRP-2025-123 | E25: ='Expense Details'!M133 -> 45675 | F25: ='Expense Details'!O133 -> Meals - Dinner | G25: ='Expense Details'!Q133 -> Sakura Izakaya | H25: ='Expense Details'!V133 -> 105.2192 | I25: ='Expense Details'!Z133 -> 75 | J25: =H25-I25 -> 30.2192 | K25: =IFERROR(MAX(0,H25/I25-1),0) -> 0.40292267 | L25: ='Expense Details'!AC133 -> Yes | M25: Exceeds category policy limit | N25: ='Expense Details'!AG133 -> Approved | O25: ='Expense Details'!F133 -> Tomas Kovac
A26: ='Expense Details'!A140 -> EXP-00139 | B26: ='Expense Details'!C140 -> Arjun Deshpande | C26: ='Expense Details'!D140 -> Product | D26: ='Expense Details'!G140 -> TRP-2025-137 | E26: ='Expense Details'!M140 -> 45675 | F26: ='Expense Details'!O140 -> Meals - Dinner | G26: ='Expense Details'!Q140 -> Sakura Izakaya | H26: ='Expense Details'!V140 -> 65.13 | I26: ='Expense Details'!Z140 -> 75 | J26: =H26-I26 -> -9.87 | K26: =IFERROR(MAX(0,H26/I26-1),0) -> 0 | L26: ='Expense Details'!AC140 -> No | M26: No receipt attached | N26: ='Expense Details'!AG140 -> Approved | O26: ='Expense Details'!F140 -> Elena Duarte
A27: ='Expense Details'!A144 -> EXP-00143 | B27: ='Expense Details'!C144 -> Kenji Watanabe | C27: ='Expense Details'!D144 -> Product | D27: ='Expense Details'!G144 -> TRP-2025-025 | E27: ='Expense Details'!M144 -> 45676 | F27: ='Expense Details'!O144 -> Meals - Lunch | G27: ='Expense Details'!Q144 -> Local Bistro | H27: ='Expense Details'!V144 -> 38.2354 | I27: ='Expense Details'!Z144 -> 35 | J27: =H27-I27 -> 3.2354 | K27: =IFERROR(MAX(0,H27/I27-1),0) -> 0.09244 | L27: ='Expense Details'!AC144 -> No | M27: Exceeds category policy limit + No receipt attached | N27: ='Expense Details'!AG144 -> Approved | O27: ='Expense Details'!F144 -> Elena Duarte
A28: ='Expense Details'!A146 -> EXP-00145 | B28: ='Expense Details'!C146 -> Ravi Chandra | C28: ='Expense Details'!D146 -> Field Engineering | D28: ='Expense Details'!G146 -> TRP-2025-123 | E28: ='Expense Details'!M146 -> 45676 | F28: ='Expense Details'!O146 -> Meals - Breakfast | G28: ='Expense Details'!Q146 -> Starbucks | H28: ='Expense Details'!V146 -> 29.7632 | I28: ='Expense Details'!Z146 -> 25 | J28: =H28-I28 -> 4.7632 | K28: =IFERROR(MAX(0,H28/I28-1),0) -> 0.190528 | L28: ='Expense Details'!AC146 -> Yes | M28: Exceeds category policy limit | N28: ='Expense Details'!AG146 -> Approved | O28: ='Expense Details'!F146 -> Tomas Kovac
A29: ='Expense Details'!A159 -> EXP-00158 | B29: ='Expense Details'!C159 -> Grace Lin | C29: ='Expense Details'!D159 -> Marketing | D29: ='Expense Details'!G159 -> TRP-2025-096 | E29: ='Expense Details'!M159 -> 45677 | F29: ='Expense Details'!O159 -> Airfare | G29: ='Expense Details'!Q159 -> Air India | H29: ='Expense Details'!V159 -> 1535.64 | I29: ='Expense Details'!Z159 -> 1400 | J29: =H29-I29 -> 135.64 | K29: =IFERROR(MAX(0,H29/I29-1),0) -> 0.096885714 | L29: ='Expense Details'!AC159 -> Yes | M29: Exceeds category policy limit | N29: ='Expense Details'!AG159 -> Approved | O29: ='Expense Details'!F159 -> Diane Okafor
A30: ='Expense Details'!A160 -> EXP-00159 | B30: ='Expense Details'!C160 -> Grace Lin | C30: ='Expense Details'!D160 -> Marketing | D30: ='Expense Details'!G160 -> TRP-2025-096 | E30: ='Expense Details'!M160 -> 45677 | F30: ='Expense Details'!O160 -> Baggage & Excess Fees | G30: ='Expense Details'!Q160 -> Air India | H30: ='Expense Details'!V160 -> 169.95 | I30: ='Expense Details'!Z160 -> 120 | J30: =H30-I30 -> 49.95 | K30: =IFERROR(MAX(0,H30/I30-1),0) -> 0.41625 | L30: ='Expense Details'!AC160 -> Yes | M30: Exceeds category policy limit | N30: ='Expense Details'!AG160 -> Approved | O30: ='Expense Details'!F160 -> Diane Okafor
A31: ='Expense Details'!A164 -> EXP-00163 | B31: ='Expense Details'!C164 -> Grace Lin | C31: ='Expense Details'!D164 -> Marketing | D31: ='Expense Details'!G164 -> TRP-2025-096 | E31: ='Expense Details'!M164 -> 45677 | F31: ='Expense Details'!O164 -> Meals - Lunch | G31: ='Expense Details'!Q164 -> Local Bistro | H31: ='Expense Details'!V164 -> 14.28 | I31: ='Expense Details'!Z164 -> 35 | J31: =H31-I31 -> -20.72 | K31: =IFERROR(MAX(0,H31/I31-1),0) -> 0 | L31: ='Expense Details'!AC164 -> No | M31: No receipt attached | N31: ='Expense Details'!AG164 -> Approved | O31: ='Expense Details'!F164 -> Diane Okafor
A32: ='Expense Details'!A169 -> EXP-00168 | B32: ='Expense Details'!C169 -> Grace Lin | C32: ='Expense Details'!D169 -> Marketing | D32: ='Expense Details'!G169 -> TRP-2025-124 | E32: ='Expense Details'!M169 -> 45677 | F32: ='Expense Details'!O169 -> Airfare | G32: ='Expense Details'!Q169 -> Singapore Airlines | H32: ='Expense Details'!V169 -> 2045.4556 | I32: ='Expense Details'!Z169 -> 1400 | J32: =H32-I32 -> 645.45564 | K32: =IFERROR(MAX(0,H32/I32-1),0) -> 0.46103974 | L32: ='Expense Details'!AC169 -> Yes | M32: Exceeds category policy limit | N32: ='Expense Details'!AG169 -> Approved | O32: ='Expense Details'!F169 -> Diane Okafor
A33: ='Expense Details'!A176 -> EXP-00175 | B33: ='Expense Details'!C176 -> Grace Lin | C33: ='Expense Details'!D176 -> Marketing | D33: ='Expense Details'!G176 -> TRP-2025-096 | E33: ='Expense Details'!M176 -> 45678 | F33: ='Expense Details'!O176 -> Ground Transport - Rail | G33: ='Expense Details'!Q176 -> SNCF | H33: ='Expense Details'!V176 -> 59.36 | I33: ='Expense Details'!Z176 -> 150 | J33: =H33-I33 -> -90.64 | K33: =IFERROR(MAX(0,H33/I33-1),0) -> 0 | L33: ='Expense Details'!AC176 -> No | M33: No receipt attached | N33: ='Expense Details'!AG176 -> Approved | O33: ='Expense Details'!F176 -> Diane Okafor
A34: ='Expense Details'!A178 -> EXP-00177 | B34: ='Expense Details'!C178 -> Grace Lin | C34: ='Expense Details'!D178 -> Marketing | D34: ='Expense Details'!G178 -> TRP-2025-096 | E34: ='Expense Details'!M178 -> 45678 | F34: ='Expense Details'!O178 -> Meals - Breakfast | G34: ='Expense Details'!Q178 -> Starbucks | H34: ='Expense Details'!V178 -> 38.29 | I34: ='Expense Details'!Z178 -> 25 | J34: =H34-I34 -> 13.29 | K34: =IFERROR(MAX(0,H34/I34-1),0) -> 0.5316 | L34: ='Expense Details'!AC178 -> Yes | M34: Exceeds category policy limit | N34: ='Expense Details'!AG178 -> Approved | O34: ='Expense Details'!F178 -> Diane Okafor
A35: ='Expense Details'!A179 -> EXP-00178 | B35: ='Expense Details'!C179 -> Grace Lin | C35: ='Expense Details'!D179 -> Marketing | D35: ='Expense Details'!G179 -> TRP-2025-096 | E35: ='Expense Details'!M179 -> 45678 | F35: ='Expense Details'!O179 -> Meals - Lunch | G35: ='Expense Details'!Q179 -> Local Bistro | H35: ='Expense Details'!V179 -> 39.53 | I35: ='Expense Details'!Z179 -> 35 | J35: =H35-I35 -> 4.53 | K35: =IFERROR(MAX(0,H35/I35-1),0) -> 0.12942857 | L35: ='Expense Details'!AC179 -> Yes | M35: Exceeds category policy limit | N35: ='Expense Details'!AG179 -> Approved | O35: ='Expense Details'!F179 -> Diane Okafor
A36: ='Expense Details'!A181 -> EXP-00180 | B36: ='Expense Details'!C181 -> Grace Lin | C36: ='Expense Details'!D181 -> Marketing | D36: ='Expense Details'!G181 -> TRP-2025-124 | E36: ='Expense Details'!M181 -> 45678 | F36: ='Expense Details'!O181 -> Internet / Roaming | G36: ='Expense Details'!Q181 -> Airport WiFi | H36: ='Expense Details'!V181 -> 47.50874 | I36: ='Expense Details'!Z181 -> 55 | J36: =H36-I36 -> -7.49126 | K36: =IFERROR(MAX(0,H36/I36-1),0) -> 0 | L36: ='Expense Details'!AC181 -> No | M36: No receipt attached | N36: ='Expense Details'!AG181 -> Approved | O36: ='Expense Details'!F181 -> Diane Okafor
A37: ='Expense Details'!A185 -> EXP-00184 | B37: ='Expense Details'!C185 -> Aisha Bello | C37: ='Expense Details'!D185 -> Operations | D37: ='Expense Details'!G185 -> TRP-2025-133 | E37: ='Expense Details'!M185 -> 45678 | F37: ='Expense Details'!O185 -> Ground Transport - Taxi | G37: ='Expense Details'!Q185 -> Ola Cabs | H37: ='Expense Details'!V185 -> 31.9 | I37: ='Expense Details'!Z185 -> 60 | J37: =H37-I37 -> -28.1 | K37: =IFERROR(MAX(0,H37/I37-1),0) -> 0 | L37: ='Expense Details'!AC185 -> No | M37: No receipt attached | N37: ='Expense Details'!AG185 -> Approved | O37: ='Expense Details'!F185 -> Viktor Petrov
A38: ='Expense Details'!A189 -> EXP-00188 | B38: ='Expense Details'!C189 -> Aisha Bello | C38: ='Expense Details'!D189 -> Operations | D38: ='Expense Details'!G189 -> TRP-2025-133 | E38: ='Expense Details'!M189 -> 45678 | F38: ='Expense Details'!O189 -> Meals - Lunch | G38: ='Expense Details'!Q189 -> Pret A Manger | H38: ='Expense Details'!V189 -> 40.64 | I38: ='Expense Details'!Z189 -> 35 | J38: =H38-I38 -> 5.64 | K38: =IFERROR(MAX(0,H38/I38-1),0) -> 0.16114286 | L38: ='Expense Details'!AC189 -> Yes | M38: Exceeds category policy limit | N38: ='Expense Details'!AG189 -> Approved | O38: ='Expense Details'!F189 -> Viktor Petrov
A39: ='Expense Details'!A190 -> EXP-00189 | B39: ='Expense Details'!C190 -> Grace Lin | C39: ='Expense Details'!D190 -> Marketing | D39: ='Expense Details'!G190 -> TRP-2025-096 | E39: ='Expense Details'!M190 -> 45679 | F39: ='Expense Details'!O190 -> Ground Transport - Taxi | G39: ='Expense Details'!Q190 -> Local Taxi | H39: ='Expense Details'!V190 -> 58.15 | I39: ='Expense Details'!Z190 -> 60 | J39: =H39-I39 -> -1.85 | K39: =IFERROR(MAX(0,H39/I39-1),0) -> 0 | L39: ='Expense Details'!AC190 -> No | M39: No receipt attached | N39: ='Expense Details'!AG190 -> Approved | O39: ='Expense Details'!F190 -> Diane Okafor
A40: ='Expense Details'!A203 -> EXP-00202 | B40: ='Expense Details'!C203 -> Marcus Bell | C40: ='Expense Details'!D203 -> Sales | D40: ='Expense Details'!G203 -> TRP-2025-039 | E40: ='Expense Details'!M203 -> 45680 | F40: ='Expense Details'!O203 -> Meals - Dinner | G40: ='Expense Details'!Q203 -> Spice Route | H40: ='Expense Details'!V203 -> 87.639 | I40: ='Expense Details'!Z203 -> 75 | J40: =H40-I40 -> 12.639 | K40: =IFERROR(MAX(0,H40/I40-1),0) -> 0.16852 | L40: ='Expense Details'!AC203 -> Yes | M40: Exceeds category policy limit | N40: ='Expense Details'!AG203 -> Approved | O40: ='Expense Details'!F203 -> Diane Okafor
A41: ='Expense Details'!A205 -> EXP-00204 | B41: ='Expense Details'!C205 -> Grace Lin | C41: ='Expense Details'!D205 -> Marketing | D41: ='Expense Details'!G205 -> TRP-2025-096 | E41: ='Expense Details'!M205 -> 45680 | F41: ='Expense Details'!O205 -> Ground Transport - Taxi | G41: ='Expense Details'!Q205 -> Lyft | H41: ='Expense Details'!V205 -> 79.7 | I41: ='Expense Details'!Z205 -> 60 | J41: =H41-I41 -> 19.7 | K41: =IFERROR(MAX(0,H41/I41-1),0) -> 0.32833333 | L41: ='Expense Details'!AC205 -> Yes | M41: Exceeds category policy limit | N41: ='Expense Details'!AG205 -> Approved | O41: ='Expense Details'!F205 -> Diane Okafor
A42: ='Expense Details'!A213 -> EXP-00212 | B42: ='Expense Details'!C213 -> Aisha Bello | C42: ='Expense Details'!D213 -> Operations | D42: ='Expense Details'!G213 -> TRP-2025-133 | E42: ='Expense Details'!M213 -> 45680 | F42: ='Expense Details'!O213 -> Meals - Lunch | G42: ='Expense Details'!Q213 -> Sweetgreen | H42: ='Expense Details'!V213 -> 42.84 | I42: ='Expense Details'!Z213 -> 35 | J42: =H42-I42 -> 7.84 | K42: =IFERROR(MAX(0,H42/I42-1),0) -> 0.224 | L42: ='Expense Details'!AC213 -> Yes | M42: Exceeds category policy limit | N42: ='Expense Details'!AG213 -> Approved | O42: ='Expense Details'!F213 -> Viktor Petrov
A43: ='Expense Details'!A219 -> EXP-00218 | B43: ='Expense Details'!C219 -> Paul Nkemelu | C43: ='Expense Details'!D219 -> Customer Success | D43: ='Expense Details'!G219 -> TRP-2025-073 | E43: ='Expense Details'!M219 -> 45681 | F43: ='Expense Details'!O219 -> Airfare | G43: ='Expense Details'!Q219 -> United Airlines | H43: ='Expense Details'!V219 -> 2277.8164 | I43: ='Expense Details'!Z219 -> 1400 | J43: =H43-I43 -> 877.81645 | K43: =IFERROR(MAX(0,H43/I43-1),0) -> 0.62701175 | L43: ='Expense Details'!AC219 -> No | M43: Exceeds category policy limit + No receipt attached | N43: ='Expense Details'!AG219 -> Approved | O43: ='Expense Details'!F219 -> Diane Okafor
A44: ='Expense Details'!A227 -> EXP-00226 | B44: ='Expense Details'!C227 -> Grace Lin | C44: ='Expense Details'!D227 -> Marketing | D44: ='Expense Details'!G227 -> TRP-2025-096 | E44: ='Expense Details'!M227 -> 45681 | F44: ='Expense Details'!O227 -> Meals - Lunch | G44: ='Expense Details'!Q227 -> Local Bistro | H44: ='Expense Details'!V227 -> 27.39 | I44: ='Expense Details'!Z227 -> 35 | J44: =H44-I44 -> -7.61 | K44: =IFERROR(MAX(0,H44/I44-1),0) -> 0 | L44: ='Expense Details'!AC227 -> No | M44: No receipt attached | N44: ='Expense Details'!AG227 -> Approved | O44: ='Expense Details'!F227 -> Diane Okafor
A45: ='Expense Details'!A233 -> EXP-00232 | B45: ='Expense Details'!C233 -> Marcus Bell | C45: ='Expense Details'!D233 -> Sales | D45: ='Expense Details'!G233 -> TRP-2025-039 | E45: ='Expense Details'!M233 -> 45682 | F45: ='Expense Details'!O233 -> Meals - Dinner | G45: ='Expense Details'!Q233 -> Spice Route | H45: ='Expense Details'!V233 -> 92.75455 | I45: ='Expense Details'!Z233 -> 75 | J45: =H45-I45 -> 17.75455 | K45: =IFERROR(MAX(0,H45/I45-1),0) -> 0.23672733 | L45: ='Expense Details'!AC233 -> Yes | M45: Exceeds category policy limit | N45: ='Expense Details'!AG233 -> Approved | O45: ='Expense Details'!F233 -> Diane Okafor
A46: ='Expense Details'!A236 -> EXP-00235 | B46: ='Expense Details'!C236 -> Paul Nkemelu | C46: ='Expense Details'!D236 -> Customer Success | D46: ='Expense Details'!G236 -> TRP-2025-073 | E46: ='Expense Details'!M236 -> 45682 | F46: ='Expense Details'!O236 -> Car Rental | G46: ='Expense Details'!Q236 -> Hertz | H46: ='Expense Details'!V236 -> 131.55625 | I46: ='Expense Details'!Z236 -> 120 | J46: =H46-I46 -> 11.55625 | K46: =IFERROR(MAX(0,H46/I46-1),0) -> 0.096302083 | L46: ='Expense Details'!AC236 -> Yes | M46: Exceeds category policy limit | N46: ='Expense Details'!AG236 -> Approved | O46: ='Expense Details'!F236 -> Diane Okafor
A47: ='Expense Details'!A246 -> EXP-00245 | B47: ='Expense Details'!C246 -> Hannah Weiss | C47: ='Expense Details'!D246 -> Field Engineering | D47: ='Expense Details'!G246 -> TRP-2025-091 | E47: ='Expense Details'!M246 -> 45682 | F47: ='Expense Details'!O246 -> Airfare | G47: ='Expense Details'!Q246 -> United Airlines | H47: ='Expense Details'!V246 -> 2723.3476 | I47: ='Expense Details'!Z246 -> 1400 | J47: =H47-I47 -> 1323.3476 | K47: =IFERROR(MAX(0,H47/I47-1),0) -> 0.9452483 | L47: ='Expense Details'!AC246 -> No | M47: Exceeds category policy limit + No receipt attached | N47: ='Expense Details'!AG246 -> Approved | O47: ='Expense Details'!F246 -> Tomas Kovac
A48: ='Expense Details'!A251 -> EXP-00250 | B48: ='Expense Details'!C251 -> Grace Lin | C48: ='Expense Details'!D251 -> Marketing | D48: ='Expense Details'!G251 -> TRP-2025-096 | E48: ='Expense Details'!M251 -> 45682 | F48: ='Expense Details'!O251 -> Meals - Lunch | G48: ='Expense Details'!Q251 -> Local Bistro | H48: ='Expense Details'!V251 -> 46.38 | I48: ='Expense Details'!Z251 -> 35 | J48: =H48-I48 -> 11.38 | K48: =IFERROR(MAX(0,H48/I48-1),0) -> 0.32514286 | L48: ='Expense Details'!AC251 -> Yes | M48: Exceeds category policy limit | N48: ='Expense Details'!AG251 -> Approved | O48: ='Expense Details'!F251 -> Diane Okafor
A49: ='Expense Details'!A253 -> EXP-00252 | B49: ='Expense Details'!C253 -> Aisha Bello | C49: ='Expense Details'!D253 -> Operations | D49: ='Expense Details'!G253 -> TRP-2025-133 | E49: ='Expense Details'!M253 -> 45682 | F49: ='Expense Details'!O253 -> Meals - Dinner | G49: ='Expense Details'!Q253 -> Osteria Vela | H49: ='Expense Details'!V253 -> 98.54 | I49: ='Expense Details'!Z253 -> 75 | J49: =H49-I49 -> 23.54 | K49: =IFERROR(MAX(0,H49/I49-1),0) -> 0.31386667 | L49: ='Expense Details'!AC253 -> Yes | M49: Exceeds category policy limit | N49: ='Expense Details'!AG253 -> Approved | O49: ='Expense Details'!F253 -> Viktor Petrov
A50: ='Expense Details'!A255 -> EXP-00254 | B50: ='Expense Details'!C255 -> Paul Nkemelu | C50: ='Expense Details'!D255 -> Customer Success | D50: ='Expense Details'!G255 -> TRP-2025-037 | E50: ='Expense Details'!M255 -> 45683 | F50: ='Expense Details'!O255 -> Airfare | G50: ='Expense Details'!Q255 -> United Airlines | H50: ='Expense Details'!V255 -> 1156.9845 | I50: ='Expense Details'!Z255 -> 1400 | J50: =H50-I50 -> -243.01552 | K50: =IFERROR(MAX(0,H50/I50-1),0) -> 0 | L50: ='Expense Details'!AC255 -> No | M50: No receipt attached | N50: ='Expense Details'!AG255 -> Approved | O50: ='Expense Details'!F255 -> Diane Okafor
A51: ='Expense Details'!A259 -> EXP-00258 | B51: ='Expense Details'!C259 -> Paul Nkemelu | C51: ='Expense Details'!D259 -> Customer Success | D51: ='Expense Details'!G259 -> TRP-2025-037 | E51: ='Expense Details'!M259 -> 45683 | F51: ='Expense Details'!O259 -> Meals - Dinner | G51: ='Expense Details'!Q259 -> Spice Route | H51: ='Expense Details'!V259 -> 102.52134 | I51: ='Expense Details'!Z259 -> 75 | J51: =H51-I51 -> 27.52134 | K51: =IFERROR(MAX(0,H51/I51-1),0) -> 0.3669512 | L51: ='Expense Details'!AC259 -> Yes | M51: Exceeds category policy limit | N51: ='Expense Details'!AG259 -> Approved | O51: ='Expense Details'!F259 -> Diane Okafor
A52: ='Expense Details'!A260 -> EXP-00259 | B52: ='Expense Details'!C260 -> Marcus Bell | C52: ='Expense Details'!D260 -> Sales | D52: ='Expense Details'!G260 -> TRP-2025-039 | E52: ='Expense Details'!M260 -> 45683 | F52: ='Expense Details'!O260 -> Client Gifts | G52: ='Expense Details'!Q260 -> Corporate Gifting Co. | H52: ='Expense Details'!V260 -> 150.73515 | I52: ='Expense Details'!Z260 -> 100 | J52: =H52-I52 -> 50.73515 | K52: =IFERROR(MAX(0,H52/I52-1),0) -> 0.5073515 | L52: ='Expense Details'!AC260 -> Yes | M52: Exceeds category policy limit | N52: ='Expense Details'!AG260 -> Approved | O52: ='Expense Details'!F260 -> Diane Okafor
A53: ='Expense Details'!A262 -> EXP-00261 | B53: ='Expense Details'!C262 -> Marcus Bell | C53: ='Expense Details'!D262 -> Sales | D53: ='Expense Details'!G262 -> TRP-2025-039 | E53: ='Expense Details'!M262 -> 45683 | F53: ='Expense Details'!O262 -> Meals - Breakfast | G53: ='Expense Details'!Q262 -> Cafe Nero | H53: ='Expense Details'!V262 -> 20.2264 | I53: ='Expense Details'!Z262 -> 25 | J53: =H53-I53 -> -4.7736 | K53: =IFERROR(MAX(0,H53/I53-1),0) -> 0 | L53: ='Expense Details'!AC262 -> No | M53: No receipt attached | N53: ='Expense Details'!AG262 -> Approved | O53: ='Expense Details'!F262 -> Diane Okafor
A54: ='Expense Details'!A266 -> EXP-00265 | B54: ='Expense Details'!C266 -> Hannah Weiss | C54: ='Expense Details'!D266 -> Field Engineering | D54: ='Expense Details'!G266 -> TRP-2025-091 | E54: ='Expense Details'!M266 -> 45683 | F54: ='Expense Details'!O266 -> Ground Transport - Rail | G54: ='Expense Details'!Q266 -> JR East | H54: ='Expense Details'!V266 -> 196.63495 | I54: ='Expense Details'!Z266 -> 150 | J54: =H54-I54 -> 46.63495 | K54: =IFERROR(MAX(0,H54/I54-1),0) -> 0.31089967 | L54: ='Expense Details'!AC266 -> Yes | M54: Exceeds category policy limit | N54: ='Expense Details'!AG266 -> Approved | O54: ='Expense Details'!F266 -> Tomas Kovac
A55: ='Expense Details'!A269 -> EXP-00268 | B55: ='Expense Details'!C269 -> Hannah Weiss | C55: ='Expense Details'!D269 -> Field Engineering | D55: ='Expense Details'!G269 -> TRP-2025-091 | E55: ='Expense Details'!M269 -> 45683 | F55: ='Expense Details'!O269 -> Internet / Roaming | G55: ='Expense Details'!Q269 -> Vodafone Roaming | H55: ='Expense Details'!V269 -> 63.54879 | I55: ='Expense Details'!Z269 -> 55 | J55: =H55-I55 -> 8.54879 | K55: =IFERROR(MAX(0,H55/I55-1),0) -> 0.15543255 | L55: ='Expense Details'!AC269 -> Yes | M55: Exceeds category policy limit | N55: ='Expense Details'!AG269 -> Approved | O55: ='Expense Details'!F269 -> Tomas Kovac
A56: ='Expense Details'!A272 -> EXP-00271 | B56: ='Expense Details'!C272 -> Hannah Weiss | C56: ='Expense Details'!D272 -> Field Engineering | D56: ='Expense Details'!G272 -> TRP-2025-091 | E56: ='Expense Details'!M272 -> 45683 | F56: ='Expense Details'!O272 -> Meals - Lunch | G56: ='Expense Details'!Q272 -> Sweetgreen | H56: ='Expense Details'!V272 -> 18.71617 | I56: ='Expense Details'!Z272 -> 35 | J56: =H56-I56 -> -16.28383 | K56: =IFERROR(MAX(0,H56/I56-1),0) -> 0 | L56: ='Expense Details'!AC272 -> No | M56: No receipt attached | N56: ='Expense Details'!AG272 -> Approved | O56: ='Expense Details'!F272 -> Tomas Kovac
A57: ='Expense Details'!A273 -> EXP-00272 | B57: ='Expense Details'!C273 -> Grace Lin | C57: ='Expense Details'!D273 -> Marketing | D57: ='Expense Details'!G273 -> TRP-2025-096 | E57: ='Expense Details'!M273 -> 45683 | F57: ='Expense Details'!O273 -> Ground Transport - Taxi | G57: ='Expense Details'!Q273 -> Grab | H57: ='Expense Details'!V273 -> 34.45 | I57: ='Expense Details'!Z273 -> 60 | J57: =H57-I57 -> -25.55 | K57: =IFERROR(MAX(0,H57/I57-1),0) -> 0 | L57: ='Expense Details'!AC273 -> No | M57: No receipt attached | N57: ='Expense Details'!AG273 -> Approved | O57: ='Expense Details'!F273 -> Diane Okafor
A58: ='Expense Details'!A279 -> EXP-00278 | B58: ='Expense Details'!C279 -> Aisha Bello | C58: ='Expense Details'!D279 -> Operations | D58: ='Expense Details'!G279 -> TRP-2025-133 | E58: ='Expense Details'!M279 -> 45683 | F58: ='Expense Details'!O279 -> Meals - Dinner | G58: ='Expense Details'!Q279 -> Spice Route | H58: ='Expense Details'!V279 -> 106.38 | I58: ='Expense Details'!Z279 -> 75 | J58: =H58-I58 -> 31.38 | K58: =IFERROR(MAX(0,H58/I58-1),0) -> 0.4184 | L58: ='Expense Details'!AC279 -> Yes | M58: Exceeds category policy limit | N58: ='Expense Details'!AG279 -> Approved | O58: ='Expense Details'!F279 -> Viktor Petrov
A59: ='Expense Details'!A281 -> EXP-00280 | B59: ='Expense Details'!C281 -> Fatima Al-Rashid | C59: ='Expense Details'!D281 -> Marketing | D59: ='Expense Details'!G281 -> TRP-2025-005 | E59: ='Expense Details'!M281 -> 45684 | F59: ='Expense Details'!O281 -> Airfare | G59: ='Expense Details'!Q281 -> Air India | H59: ='Expense Details'!V281 -> 1496.47 | I59: ='Expense Details'!Z281 -> 1400 | J59: =H59-I59 -> 96.47 | K59: =IFERROR(MAX(0,H59/I59-1),0) -> 0.068907143 | L59: ='Expense Details'!AC281 -> Yes | M59: Exceeds category policy limit | N59: ='Expense Details'!AG281 -> Approved | O59: ='Expense Details'!F281 -> Grace Lin
A60: ='Expense Details'!A287 -> EXP-00286 | B60: ='Expense Details'!C287 -> Paul Nkemelu | C60: ='Expense Details'!D287 -> Customer Success | D60: ='Expense Details'!G287 -> TRP-2025-037 | E60: ='Expense Details'!M287 -> 45684 | F60: ='Expense Details'!O287 -> Hotel / Lodging | G60: ='Expense Details'!Q287 -> Radisson Blu | H60: ='Expense Details'!V287 -> 2150.9338 | I60: ='Expense Details'!Z287 -> 1400 | J60: =H60-I60 -> 750.93376 | K60: =IFERROR(MAX(0,H60/I60-1),0) -> 0.53638126 | L60: ='Expense Details'!AC287 -> Yes | M60: Exceeds category policy limit | N60: ='Expense Details'!AG287 -> Approved | O60: ='Expense Details'!F287 -> Diane Okafor
A61: ='Expense Details'!A296 -> EXP-00295 | B61: ='Expense Details'!C296 -> Sneha Iyer | C61: ='Expense Details'!D296 -> Customer Success | D61: ='Expense Details'!G296 -> TRP-2025-081 | E61: ='Expense Details'!M296 -> 45684 | F61: ='Expense Details'!O296 -> Meals - Breakfast | G61: ='Expense Details'!Q296 -> Local Bakery | H61: ='Expense Details'!V296 -> 27.43 | I61: ='Expense Details'!Z296 -> 25 | J61: =H61-I61 -> 2.43 | K61: =IFERROR(MAX(0,H61/I61-1),0) -> 0.0972 | L61: ='Expense Details'!AC296 -> No | M61: Exceeds category policy limit + No receipt attached | N61: ='Expense Details'!AG296 -> Pending Approval | O61: ='Expense Details'!F296 -> Paul Nkemelu
A62: ='Expense Details'!A304 -> EXP-00303 | B62: ='Expense Details'!C304 -> Fatima Al-Rashid | C62: ='Expense Details'!D304 -> Marketing | D62: ='Expense Details'!G304 -> TRP-2025-005 | E62: ='Expense Details'!M304 -> 45685 | F62: ='Expense Details'!O304 -> Ground Transport - Taxi | G62: ='Expense Details'!Q304 -> Lyft | H62: ='Expense Details'!V304 -> 75.36 | I62: ='Expense Details'!Z304 -> 60 | J62: =H62-I62 -> 15.36 | K62: =IFERROR(MAX(0,H62/I62-1),0) -> 0.256 | L62: ='Expense Details'!AC304 -> Yes | M62: Exceeds category policy limit | N62: ='Expense Details'!AG304 -> Approved | O62: ='Expense Details'!F304 -> Grace Lin
A63: ='Expense Details'!A305 -> EXP-00304 | B63: ='Expense Details'!C305 -> Fatima Al-Rashid | C63: ='Expense Details'!D305 -> Marketing | D63: ='Expense Details'!G305 -> TRP-2025-005 | E63: ='Expense Details'!M305 -> 45685 | F63: ='Expense Details'!O305 -> Hotel / Lodging | G63: ='Expense Details'!Q305 -> Hyatt Place | H63: ='Expense Details'!V305 -> 1574.97 | I63: ='Expense Details'!Z305 -> 1960 | J63: =H63-I63 -> -385.03 | K63: =IFERROR(MAX(0,H63/I63-1),0) -> 0 | L63: ='Expense Details'!AC305 -> No | M63: No receipt attached | N63: ='Expense Details'!AG305 -> Approved | O63: ='Expense Details'!F305 -> Grace Lin
A64: ='Expense Details'!A307 -> EXP-00306 | B64: ='Expense Details'!C307 -> Fatima Al-Rashid | C64: ='Expense Details'!D307 -> Marketing | D64: ='Expense Details'!G307 -> TRP-2025-005 | E64: ='Expense Details'!M307 -> 45685 | F64: ='Expense Details'!O307 -> Meals - Dinner | G64: ='Expense Details'!Q307 -> Brasserie Lyon | H64: ='Expense Details'!V307 -> 102.51 | I64: ='Expense Details'!Z307 -> 75 | J64: =H64-I64 -> 27.51 | K64: =IFERROR(MAX(0,H64/I64-1),0) -> 0.3668 | L64: ='Expense Details'!AC307 -> Yes | M64: Exceeds category policy limit | N64: ='Expense Details'!AG307 -> Approved | O64: ='Expense Details'!F307 -> Grace Lin
A65: ='Expense Details'!A308 -> EXP-00307 | B65: ='Expense Details'!C308 -> Fatima Al-Rashid | C65: ='Expense Details'!D308 -> Marketing | D65: ='Expense Details'!G308 -> TRP-2025-005 | E65: ='Expense Details'!M308 -> 45685 | F65: ='Expense Details'!O308 -> Meals - Lunch | G65: ='Expense Details'!Q308 -> Sweetgreen | H65: ='Expense Details'!V308 -> 28.59 | I65: ='Expense Details'!Z308 -> 35 | J65: =H65-I65 -> -6.41 | K65: =IFERROR(MAX(0,H65/I65-1),0) -> 0 | L65: ='Expense Details'!AC308 -> No | M65: No receipt attached | N65: ='Expense Details'!AG308 -> Approved | O65: ='Expense Details'!F308 -> Grace Lin
A66: ='Expense Details'!A318 -> EXP-00317 | B66: ='Expense Details'!C318 -> Paul Nkemelu | C66: ='Expense Details'!D318 -> Customer Success | D66: ='Expense Details'!G318 -> TRP-2025-037 | E66: ='Expense Details'!M318 -> 45686 | F66: ='Expense Details'!O318 -> Ground Transport - Taxi | G66: ='Expense Details'!Q318 -> Lyft | H66: ='Expense Details'!V318 -> 92.93242 | I66: ='Expense Details'!Z318 -> 60 | J66: =H66-I66 -> 32.93242 | K66: =IFERROR(MAX(0,H66/I66-1),0) -> 0.54887367 | L66: ='Expense Details'!AC318 -> Yes | M66: Exceeds category policy limit | N66: ='Expense Details'!AG318 -> Approved | O66: ='Expense Details'!F318 -> Diane Okafor
A67: ='Expense Details'!A327 -> EXP-00326 | B67: ='Expense Details'!C327 -> Sneha Iyer | C67: ='Expense Details'!D327 -> Customer Success | D67: ='Expense Details'!G327 -> TRP-2025-081 | E67: ='Expense Details'!M327 -> 45686 | F67: ='Expense Details'!O327 -> Meals - Breakfast | G67: ='Expense Details'!Q327 -> Starbucks | H67: ='Expense Details'!V327 -> 26.6 | I67: ='Expense Details'!Z327 -> 25 | J67: =H67-I67 -> 1.6 | K67: =IFERROR(MAX(0,H67/I67-1),0) -> 0.064 | L67: ='Expense Details'!AC327 -> Yes | M67: Exceeds category policy limit | N67: ='Expense Details'!AG327 -> Pending Approval | O67: ='Expense Details'!F327 -> Paul Nkemelu
A68: ='Expense Details'!A359 -> EXP-00358 | B68: ='Expense Details'!C359 -> Sneha Iyer | C68: ='Expense Details'!D359 -> Customer Success | D68: ='Expense Details'!G359 -> TRP-2025-081 | E68: ='Expense Details'!M359 -> 45688 | F68: ='Expense Details'!O359 -> Meals - Dinner | G68: ='Expense Details'!Q359 -> Brasserie Lyon | H68: ='Expense Details'!V359 -> 39.76 | I68: ='Expense Details'!Z359 -> 75 | J68: =H68-I68 -> -35.24 | K68: =IFERROR(MAX(0,H68/I68-1),0) -> 0 | L68: ='Expense Details'!AC359 -> No | M68: No receipt attached | N68: ='Expense Details'!AG359 -> Pending Approval | O68: ='Expense Details'!F359 -> Paul Nkemelu
A69: ='Expense Details'!A368 -> EXP-00367 | B69: ='Expense Details'!C368 -> Paul Nkemelu | C69: ='Expense Details'!D368 -> Customer Success | D69: ='Expense Details'!G368 -> TRP-2025-078 | E69: ='Expense Details'!M368 -> 45689 | F69: ='Expense Details'!O368 -> Meals - Dinner | G69: ='Expense Details'!Q368 -> Sakura Izakaya | H69: ='Expense Details'!V368 -> 93.492 | I69: ='Expense Details'!Z368 -> 75 | J69: =H69-I69 -> 18.492 | K69: =IFERROR(MAX(0,H69/I69-1),0) -> 0.24656 | L69: ='Expense Details'!AC368 -> Yes | M69: Exceeds category policy limit | N69: ='Expense Details'!AG368 -> Approved | O69: ='Expense Details'!F368 -> Diane Okafor
A70: ='Expense Details'!A370 -> EXP-00369 | B70: ='Expense Details'!C370 -> Fatima Al-Rashid | C70: ='Expense Details'!D370 -> Marketing | D70: ='Expense Details'!G370 -> TRP-2025-005 | E70: ='Expense Details'!M370 -> 45690 | F70: ='Expense Details'!O370 -> Client Entertainment | G70: ='Expense Details'!Q370 -> Rooftop Lounge | H70: ='Expense Details'!V370 -> 110.14 | I70: ='Expense Details'!Z370 -> 200 | J70: =H70-I70 -> -89.86 | K70: =IFERROR(MAX(0,H70/I70-1),0) -> 0 | L70: ='Expense Details'!AC370 -> No | M70: No receipt attached | N70: ='Expense Details'!AG370 -> Approved | O70: ='Expense Details'!F370 -> Grace Lin
A71: ='Expense Details'!A377 -> EXP-00376 | B71: ='Expense Details'!C377 -> Tomas Kovac | C71: ='Expense Details'!D377 -> Field Engineering | D71: ='Expense Details'!G377 -> TRP-2025-076 | E71: ='Expense Details'!M377 -> 45690 | F71: ='Expense Details'!O377 -> Meals - Lunch | G71: ='Expense Details'!Q377 -> Sweetgreen | H71: ='Expense Details'!V377 -> 20.30392 | I71: ='Expense Details'!Z377 -> 35 | J71: =H71-I71 -> -14.69608 | K71: =IFERROR(MAX(0,H71/I71-1),0) -> 0 | L71: ='Expense Details'!AC377 -> No | M71: No receipt attached | N71: ='Expense Details'!AG377 -> Pending Approval | O71: ='Expense Details'!F377 -> Diane Okafor
A72: ='Expense Details'!A381 -> EXP-00380 | B72: ='Expense Details'!C381 -> Paul Nkemelu | C72: ='Expense Details'!D381 -> Customer Success | D72: ='Expense Details'!G381 -> TRP-2025-078 | E72: ='Expense Details'!M381 -> 45690 | F72: ='Expense Details'!O381 -> Meals - Dinner | G72: ='Expense Details'!Q381 -> Spice Route | H72: ='Expense Details'!V381 -> 109.5828 | I72: ='Expense Details'!Z381 -> 75 | J72: =H72-I72 -> 34.5828 | K72: =IFERROR(MAX(0,H72/I72-1),0) -> 0.461104 | L72: ='Expense Details'!AC381 -> Yes | M72: Exceeds category policy limit | N72: ='Expense Details'!AG381 -> Approved | O72: ='Expense Details'!F381 -> Diane Okafor
A73: ='Expense Details'!A382 -> EXP-00381 | B73: ='Expense Details'!C382 -> Paul Nkemelu | C73: ='Expense Details'!D382 -> Customer Success | D73: ='Expense Details'!G382 -> TRP-2025-078 | E73: ='Expense Details'!M382 -> 45690 | F73: ='Expense Details'!O382 -> Meals - Lunch | G73: ='Expense Details'!Q382 -> Sweetgreen | H73: ='Expense Details'!V382 -> 12.30024 | I73: ='Expense Details'!Z382 -> 35 | J73: =H73-I73 -> -22.69976 | K73: =IFERROR(MAX(0,H73/I73-1),0) -> 0 | L73: ='Expense Details'!AC382 -> No | M73: No receipt attached | N73: ='Expense Details'!AG382 -> Approved | O73: ='Expense Details'!F382 -> Diane Okafor
A74: ='Expense Details'!A391 -> EXP-00390 | B74: ='Expense Details'!C391 -> Paul Nkemelu | C74: ='Expense Details'!D391 -> Customer Success | D74: ='Expense Details'!G391 -> TRP-2025-078 | E74: ='Expense Details'!M391 -> 45691 | F74: ='Expense Details'!O391 -> Meals - Dinner | G74: ='Expense Details'!Q391 -> Brasserie Lyon | H74: ='Expense Details'!V391 -> 98.3892 | I74: ='Expense Details'!Z391 -> 75 | J74: =H74-I74 -> 23.3892 | K74: =IFERROR(MAX(0,H74/I74-1),0) -> 0.311856 | L74: ='Expense Details'!AC391 -> Yes | M74: Exceeds category policy limit | N74: ='Expense Details'!AG391 -> Approved | O74: ='Expense Details'!F391 -> Diane Okafor
A75: ='Expense Details'!A398 -> EXP-00397 | B75: ='Expense Details'!C398 -> Tomas Kovac | C75: ='Expense Details'!D398 -> Field Engineering | D75: ='Expense Details'!G398 -> TRP-2025-076 | E75: ='Expense Details'!M398 -> 45693 | F75: ='Expense Details'!O398 -> Client Entertainment | G75: ='Expense Details'!Q398 -> Harbour Club | H75: ='Expense Details'!V398 -> 249.68216 | I75: ='Expense Details'!Z398 -> 200 | J75: =H75-I75 -> 49.68216 | K75: =IFERROR(MAX(0,H75/I75-1),0) -> 0.2484108 | L75: ='Expense Details'!AC398 -> Yes | M75: Exceeds category policy limit | N75: ='Expense Details'!AG398 -> Pending Approval | O75: ='Expense Details'!F398 -> Diane Okafor
A76: ='Expense Details'!A399 -> EXP-00398 | B76: ='Expense Details'!C399 -> Tomas Kovac | C76: ='Expense Details'!D399 -> Field Engineering | D76: ='Expense Details'!G399 -> TRP-2025-076 | E76: ='Expense Details'!M399 -> 45693 | F76: ='Expense Details'!O399 -> Client Gifts | G76: ='Expense Details'!Q399 -> Duty Free | H76: ='Expense Details'!V399 -> 154.2268 | I76: ='Expense Details'!Z399 -> 100 | J76: =H76-I76 -> 54.2268 | K76: =IFERROR(MAX(0,H76/I76-1),0) -> 0.542268 | L76: ='Expense Details'!AC399 -> Yes | M76: Exceeds category policy limit | N76: ='Expense Details'!AG399 -> Pending Approval | O76: ='Expense Details'!F399 -> Diane Okafor
A77: ='Expense Details'!A401 -> EXP-00400 | B77: ='Expense Details'!C401 -> Tomas Kovac | C77: ='Expense Details'!D401 -> Field Engineering | D77: ='Expense Details'!G401 -> TRP-2025-076 | E77: ='Expense Details'!M401 -> 45693 | F77: ='Expense Details'!O401 -> Meals - Lunch | G77: ='Expense Details'!Q401 -> Local Bistro | H77: ='Expense Details'!V401 -> 38.83152 | I77: ='Expense Details'!Z401 -> 35 | J77: =H77-I77 -> 3.83152 | K77: =IFERROR(MAX(0,H77/I77-1),0) -> 0.109472 | L77: ='Expense Details'!AC401 -> Yes | M77: Exceeds category policy limit | N77: ='Expense Details'!AG401 -> Pending Approval | O77: ='Expense Details'!F401 -> Diane Okafor
A78: ='Expense Details'!A412 -> EXP-00411 | B78: ='Expense Details'!C412 -> Paul Nkemelu | C78: ='Expense Details'!D412 -> Customer Success | D78: ='Expense Details'!G412 -> TRP-2025-078 | E78: ='Expense Details'!M412 -> 45694 | F78: ='Expense Details'!O412 -> Meals - Breakfast | G78: ='Expense Details'!Q412 -> Starbucks | H78: ='Expense Details'!V412 -> 11.18088 | I78: ='Expense Details'!Z412 -> 25 | J78: =H78-I78 -> -13.81912 | K78: =IFERROR(MAX(0,H78/I78-1),0) -> 0 | L78: ='Expense Details'!AC412 -> No | M78: No receipt attached | N78: ='Expense Details'!AG412 -> Approved | O78: ='Expense Details'!F412 -> Diane Okafor
A79: ='Expense Details'!A415 -> EXP-00414 | B79: ='Expense Details'!C415 -> Diane Okafor | C79: ='Expense Details'!D415 -> Executive | D79: ='Expense Details'!G415 -> TRP-2025-118 | E79: ='Expense Details'!M415 -> 45694 | F79: ='Expense Details'!O415 -> Client Entertainment | G79: ='Expense Details'!Q415 -> Harbour Club | H79: ='Expense Details'!V415 -> 192.913 | I79: ='Expense Details'!Z415 -> 200 | J79: =H79-I79 -> -7.087 | K79: =IFERROR(MAX(0,H79/I79-1),0) -> 0 | L79: ='Expense Details'!AC415 -> No | M79: No receipt attached | N79: ='Expense Details'!AG415 -> Pending Approval | O79: ='Expense Details'!F415 -> Board
A80: ='Expense Details'!A419 -> EXP-00418 | B80: ='Expense Details'!C419 -> Diane Okafor | C80: ='Expense Details'!D419 -> Executive | D80: ='Expense Details'!G419 -> TRP-2025-118 | E80: ='Expense Details'!M419 -> 45694 | F80: ='Expense Details'!O419 -> Meals - Breakfast | G80: ='Expense Details'!Q419 -> Hotel Restaurant | H80: ='Expense Details'!V419 -> 17.76145 | I80: ='Expense Details'!Z419 -> 25 | J80: =H80-I80 -> -7.23855 | K80: =IFERROR(MAX(0,H80/I80-1),0) -> 0 | L80: ='Expense Details'!AC419 -> No | M80: No receipt attached | N80: ='Expense Details'!AG419 -> Pending Approval | O80: ='Expense Details'!F419 -> Board
A81: ='Expense Details'!A422 -> EXP-00421 | B81: ='Expense Details'!C422 -> Oliver Brandt | C81: ='Expense Details'!D422 -> Marketing | D81: ='Expense Details'!G422 -> TRP-2025-121 | E81: ='Expense Details'!M422 -> 45694 | F81: ='Expense Details'!O422 -> Airfare | G81: ='Expense Details'!Q422 -> United Airlines | H81: ='Expense Details'!V422 -> 1859.9938 | I81: ='Expense Details'!Z422 -> 1400 | J81: =H81-I81 -> 459.9938 | K81: =IFERROR(MAX(0,H81/I81-1),0) -> 0.328567 | L81: ='Expense Details'!AC422 -> Yes | M81: Exceeds category policy limit | N81: ='Expense Details'!AG422 -> Approved | O81: ='Expense Details'!F422 -> Grace Lin
A82: ='Expense Details'!A440 -> EXP-00439 | B82: ='Expense Details'!C440 -> Oliver Brandt | C82: ='Expense Details'!D440 -> Marketing | D82: ='Expense Details'!G440 -> TRP-2025-121 | E82: ='Expense Details'!M440 -> 45695 | F82: ='Expense Details'!O440 -> Meals - Dinner | G82: ='Expense Details'!Q440 -> Osteria Vela | H82: ='Expense Details'!V440 -> 51.0167 | I82: ='Expense Details'!Z440 -> 75 | J82: =H82-I82 -> -23.9833 | K82: =IFERROR(MAX(0,H82/I82-1),0) -> 0 | L82: ='Expense Details'!AC440 -> No | M82: No receipt attached | N82: ='Expense Details'!AG440 -> Approved | O82: ='Expense Details'!F440 -> Grace Lin
A83: ='Expense Details'!A444 -> EXP-00443 | B83: ='Expense Details'!C444 -> Arjun Deshpande | C83: ='Expense Details'!D444 -> Product | D83: ='Expense Details'!G444 -> TRP-2025-020 | E83: ='Expense Details'!M444 -> 45696 | F83: ='Expense Details'!O444 -> Internet / Roaming | G83: ='Expense Details'!Q444 -> AT&T International | H83: ='Expense Details'!V444 -> 69.80792 | I83: ='Expense Details'!Z444 -> 55 | J83: =H83-I83 -> 14.80792 | K83: =IFERROR(MAX(0,H83/I83-1),0) -> 0.26923491 | L83: ='Expense Details'!AC444 -> No | M83: Exceeds category policy limit + No receipt attached | N83: ='Expense Details'!AG444 -> Approved | O83: ='Expense Details'!F444 -> Elena Duarte
A84: ='Expense Details'!A448 -> EXP-00447 | B84: ='Expense Details'!C448 -> Arjun Deshpande | C84: ='Expense Details'!D448 -> Product | D84: ='Expense Details'!G448 -> TRP-2025-080 | E84: ='Expense Details'!M448 -> 45696 | F84: ='Expense Details'!O448 -> Airfare | G84: ='Expense Details'!Q448 -> British Airways | H84: ='Expense Details'!V448 -> 2177.7776 | I84: ='Expense Details'!Z448 -> 1400 | J84: =H84-I84 -> 777.77758 | K84: =IFERROR(MAX(0,H84/I84-1),0) -> 0.55555541 | L84: ='Expense Details'!AC448 -> Yes | M84: Exceeds category policy limit | N84: ='Expense Details'!AG448 -> Rejected | O84: ='Expense Details'!F448 -> Elena Duarte
A85: ='Expense Details'!A449 -> EXP-00448 | B85: ='Expense Details'!C449 -> Arjun Deshpande | C85: ='Expense Details'!D449 -> Product | D85: ='Expense Details'!G449 -> TRP-2025-080 | E85: ='Expense Details'!M449 -> 45696 | F85: ='Expense Details'!O449 -> Ground Transport - Taxi | G85: ='Expense Details'!Q449 -> Uber | H85: ='Expense Details'!V449 -> 76.55872 | I85: ='Expense Details'!Z449 -> 60 | J85: =H85-I85 -> 16.55872 | K85: =IFERROR(MAX(0,H85/I85-1),0) -> 0.27597867 | L85: ='Expense Details'!AC449 -> Yes | M85: Exceeds category policy limit | N85: ='Expense Details'!AG449 -> Rejected | O85: ='Expense Details'!F449 -> Elena Duarte
A86: ='Expense Details'!A451 -> EXP-00450 | B86: ='Expense Details'!C451 -> Arjun Deshpande | C86: ='Expense Details'!D451 -> Product | D86: ='Expense Details'!G451 -> TRP-2025-080 | E86: ='Expense Details'!M451 -> 45696 | F86: ='Expense Details'!O451 -> Meals - Lunch | G86: ='Expense Details'!Q451 -> Pret A Manger | H86: ='Expense Details'!V451 -> 43.04199 | I86: ='Expense Details'!Z451 -> 35 | J86: =H86-I86 -> 8.04199 | K86: =IFERROR(MAX(0,H86/I86-1),0) -> 0.22977114 | L86: ='Expense Details'!AC451 -> Yes | M86: Exceeds category policy limit | N86: ='Expense Details'!AG451 -> Rejected | O86: ='Expense Details'!F451 -> Elena Duarte
A87: ='Expense Details'!A453 -> EXP-00452 | B87: ='Expense Details'!C453 -> Oliver Brandt | C87: ='Expense Details'!D453 -> Marketing | D87: ='Expense Details'!G453 -> TRP-2025-121 | E87: ='Expense Details'!M453 -> 45696 | F87: ='Expense Details'!O453 -> Meals - Breakfast | G87: ='Expense Details'!Q453 -> Cafe Nero | H87: ='Expense Details'!V453 -> 15.0815 | I87: ='Expense Details'!Z453 -> 25 | J87: =H87-I87 -> -9.9185 | K87: =IFERROR(MAX(0,H87/I87-1),0) -> 0 | L87: ='Expense Details'!AC453 -> No | M87: No receipt attached | N87: ='Expense Details'!AG453 -> Approved | O87: ='Expense Details'!F453 -> Grace Lin
A88: ='Expense Details'!A457 -> EXP-00456 | B88: ='Expense Details'!C457 -> Arjun Deshpande | C88: ='Expense Details'!D457 -> Product | D88: ='Expense Details'!G457 -> TRP-2025-020 | E88: ='Expense Details'!M457 -> 45697 | F88: ='Expense Details'!O457 -> Ground Transport - Taxi | G88: ='Expense Details'!Q457 -> Uber | H88: ='Expense Details'!V457 -> 84.86296 | I88: ='Expense Details'!Z457 -> 60 | J88: =H88-I88 -> 24.86296 | K88: =IFERROR(MAX(0,H88/I88-1),0) -> 0.41438267 | L88: ='Expense Details'!AC457 -> Yes | M88: Exceeds category policy limit | N88: ='Expense Details'!AG457 -> Approved | O88: ='Expense Details'!F457 -> Elena Duarte
A89: ='Expense Details'!A464 -> EXP-00463 | B89: ='Expense Details'!C464 -> Arjun Deshpande | C89: ='Expense Details'!D464 -> Product | D89: ='Expense Details'!G464 -> TRP-2025-080 | E89: ='Expense Details'!M464 -> 45697 | F89: ='Expense Details'!O464 -> Meals - Lunch | G89: ='Expense Details'!Q464 -> Sweetgreen | H89: ='Expense Details'!V464 -> 19.77123 | I89: ='Expense Details'!Z464 -> 35 | J89: =H89-I89 -> -15.22877 | K89: =IFERROR(MAX(0,H89/I89-1),0) -> 0 | L89: ='Expense Details'!AC464 -> No | M89: No receipt attached | N89: ='Expense Details'!AG464 -> Rejected | O89: ='Expense Details'!F464 -> Elena Duarte
A90: ='Expense Details'!A471 -> EXP-00470 | B90: ='Expense Details'!C471 -> Arjun Deshpande | C90: ='Expense Details'!D471 -> Product | D90: ='Expense Details'!G471 -> TRP-2025-020 | E90: ='Expense Details'!M471 -> 45698 | F90: ='Expense Details'!O471 -> Meals - Dinner | G90: ='Expense Details'!Q471 -> Osteria Vela | H90: ='Expense Details'!V471 -> 109.65864 | I90: ='Expense Details'!Z471 -> 75 | J90: =H90-I90 -> 34.65864 | K90: =IFERROR(MAX(0,H90/I90-1),0) -> 0.4621152 | L90: ='Expense Details'!AC471 -> Yes | M90: Exceeds category policy limit | N90: ='Expense Details'!AG471 -> Approved | O90: ='Expense Details'!F471 -> Elena Duarte
A91: ='Expense Details'!A472 -> EXP-00471 | B91: ='Expense Details'!C472 -> Arjun Deshpande | C91: ='Expense Details'!D472 -> Product | D91: ='Expense Details'!G472 -> TRP-2025-020 | E91: ='Expense Details'!M472 -> 45698 | F91: ='Expense Details'!O472 -> Meals - Lunch | G91: ='Expense Details'!Q472 -> Pret A Manger | H91: ='Expense Details'!V472 -> 52.61256 | I91: ='Expense Details'!Z472 -> 35 | J91: =H91-I91 -> 17.61256 | K91: =IFERROR(MAX(0,H91/I91-1),0) -> 0.503216 | L91: ='Expense Details'!AC472 -> Yes | M91: Exceeds category policy limit | N91: ='Expense Details'!AG472 -> Approved | O91: ='Expense Details'!F472 -> Elena Duarte
A92: ='Expense Details'!A473 -> EXP-00472 | B92: ='Expense Details'!C473 -> Laura Bianchi | C92: ='Expense Details'!D473 -> Customer Success | D92: ='Expense Details'!G473 -> TRP-2025-056 | E92: ='Expense Details'!M473 -> 45698 | F92: ='Expense Details'!O473 -> Airfare | G92: ='Expense Details'!Q473 -> Delta Air Lines | H92: ='Expense Details'!V473 -> 1582.0196 | I92: ='Expense Details'!Z473 -> 1400 | J92: =H92-I92 -> 182.01964 | K92: =IFERROR(MAX(0,H92/I92-1),0) -> 0.13001403 | L92: ='Expense Details'!AC473 -> Yes | M92: Exceeds category policy limit | N92: ='Expense Details'!AG473 -> Approved | O92: ='Expense Details'!F473 -> Sneha Iyer
A93: ='Expense Details'!A479 -> EXP-00478 | B93: ='Expense Details'!C479 -> Arjun Deshpande | C93: ='Expense Details'!D479 -> Product | D93: ='Expense Details'!G479 -> TRP-2025-080 | E93: ='Expense Details'!M479 -> 45698 | F93: ='Expense Details'!O479 -> Meals - Lunch | G93: ='Expense Details'!Q479 -> Local Bistro | H93: ='Expense Details'!V479 -> 27.33497 | I93: ='Expense Details'!Z479 -> 35 | J93: =H93-I93 -> -7.66503 | K93: =IFERROR(MAX(0,H93/I93-1),0) -> 0 | L93: ='Expense Details'!AC479 -> No | M93: No receipt attached | N93: ='Expense Details'!AG479 -> Rejected | O93: ='Expense Details'!F479 -> Elena Duarte
A94: ='Expense Details'!A487 -> EXP-00486 | B94: ='Expense Details'!C487 -> Arjun Deshpande | C94: ='Expense Details'!D487 -> Product | D94: ='Expense Details'!G487 -> TRP-2025-080 | E94: ='Expense Details'!M487 -> 45699 | F94: ='Expense Details'!O487 -> Meals - Breakfast | G94: ='Expense Details'!Q487 -> Cafe Nero | H94: ='Expense Details'!V487 -> 22.54262 | I94: ='Expense Details'!Z487 -> 25 | J94: =H94-I94 -> -2.45738 | K94: =IFERROR(MAX(0,H94/I94-1),0) -> 0 | L94: ='Expense Details'!AC487 -> No | M94: No receipt attached | N94: ='Expense Details'!AG487 -> Rejected | O94: ='Expense Details'!F487 -> Elena Duarte
A95: ='Expense Details'!A503 -> EXP-00502 | B95: ='Expense Details'!C503 -> Meera Krishnan | C95: ='Expense Details'!D503 -> Finance | D95: ='Expense Details'!G503 -> TRP-2025-106 | E95: ='Expense Details'!M503 -> 45700 | F95: ='Expense Details'!O503 -> Airfare | G95: ='Expense Details'!Q503 -> Singapore Airlines | H95: ='Expense Details'!V503 -> 2466.1282 | I95: ='Expense Details'!Z503 -> 1400 | J95: =H95-I95 -> 1066.1282 | K95: =IFERROR(MAX(0,H95/I95-1),0) -> 0.76152011 | L95: ='Expense Details'!AC503 -> Yes | M95: Exceeds category policy limit | N95: ='Expense Details'!AG503 -> Pending Approval | O95: ='Expense Details'!F503 -> David Chen
A96: ='Expense Details'!A522 -> EXP-00521 | B96: ='Expense Details'!C522 -> Sneha Iyer | C96: ='Expense Details'!D522 -> Customer Success | D96: ='Expense Details'!G522 -> TRP-2025-102 | E96: ='Expense Details'!M522 -> 45701 | F96: ='Expense Details'!O522 -> Ground Transport - Taxi | G96: ='Expense Details'!Q522 -> Lyft | H96: ='Expense Details'!V522 -> 24.42 | I96: ='Expense Details'!Z522 -> 60 | J96: =H96-I96 -> -35.58 | K96: =IFERROR(MAX(0,H96/I96-1),0) -> 0 | L96: ='Expense Details'!AC522 -> No | M96: No receipt attached | N96: ='Expense Details'!AG522 -> Approved | O96: ='Expense Details'!F522 -> Paul Nkemelu
A97: ='Expense Details'!A533 -> EXP-00532 | B97: ='Expense Details'!C533 -> Laura Bianchi | C97: ='Expense Details'!D533 -> Customer Success | D97: ='Expense Details'!G533 -> TRP-2025-056 | E97: ='Expense Details'!M533 -> 45702 | F97: ='Expense Details'!O533 -> Meals - Breakfast | G97: ='Expense Details'!Q533 -> Local Bakery | H97: ='Expense Details'!V533 -> 29.69667 | I97: ='Expense Details'!Z533 -> 25 | J97: =H97-I97 -> 4.69667 | K97: =IFERROR(MAX(0,H97/I97-1),0) -> 0.1878668 | L97: ='Expense Details'!AC533 -> Yes | M97: Exceeds category policy limit | N97: ='Expense Details'!AG533 -> Approved | O97: ='Expense Details'!F533 -> Sneha Iyer
A98: ='Expense Details'!A541 -> EXP-00540 | B98: ='Expense Details'!C541 -> Viktor Petrov | C98: ='Expense Details'!D541 -> Operations | D98: ='Expense Details'!G541 -> TRP-2025-092 | E98: ='Expense Details'!M541 -> 45702 | F98: ='Expense Details'!O541 -> Meals - Dinner | G98: ='Expense Details'!Q541 -> Spice Route | H98: ='Expense Details'!V541 -> 55.5 | I98: ='Expense Details'!Z541 -> 75 | J98: =H98-I98 -> -19.5 | K98: =IFERROR(MAX(0,H98/I98-1),0) -> 0 | L98: ='Expense Details'!AC541 -> No | M98: No receipt attached | N98: ='Expense Details'!AG541 -> Approved | O98: ='Expense Details'!F541 -> Diane Okafor
A99: ='Expense Details'!A550 -> EXP-00549 | B99: ='Expense Details'!C550 -> Laura Bianchi | C99: ='Expense Details'!D550 -> Customer Success | D99: ='Expense Details'!G550 -> TRP-2025-056 | E99: ='Expense Details'!M550 -> 45703 | F99: ='Expense Details'!O550 -> Meals - Breakfast | G99: ='Expense Details'!Q550 -> Hotel Restaurant | H99: ='Expense Details'!V550 -> 31.9465 | I99: ='Expense Details'!Z550 -> 25 | J99: =H99-I99 -> 6.9465 | K99: =IFERROR(MAX(0,H99/I99-1),0) -> 0.27786 | L99: ='Expense Details'!AC550 -> Yes | M99: Exceeds category policy limit | N99: ='Expense Details'!AG550 -> Approved | O99: ='Expense Details'!F550 -> Sneha Iyer
A100: ='Expense Details'!A564 -> EXP-00563 | B100: ='Expense Details'!C564 -> Laura Bianchi | C100: ='Expense Details'!D564 -> Customer Success | D100: ='Expense Details'!G564 -> TRP-2025-056 | E100: ='Expense Details'!M564 -> 45704 | F100: ='Expense Details'!O564 -> Meals - Lunch | G100: ='Expense Details'!Q564 -> Local Bistro | H100: ='Expense Details'!V564 -> 52.39769 | I100: ='Expense Details'!Z564 -> 35 | J100: =H100-I100 -> 17.39769 | K100: =IFERROR(MAX(0,H100/I100-1),0) -> 0.49707686 | L100: ='Expense Details'!AC564 -> Yes | M100: Exceeds category policy limit | N100: ='Expense Details'!AG564 -> Approved | O100: ='Expense Details'!F564 -> Sneha Iyer
A101: ='Expense Details'!A570 -> EXP-00569 | B101: ='Expense Details'!C570 -> Meera Krishnan | C101: ='Expense Details'!D570 -> Finance | D101: ='Expense Details'!G570 -> TRP-2025-106 | E101: ='Expense Details'!M570 -> 45704 | F101: ='Expense Details'!O570 -> Ground Transport - Taxi | G101: ='Expense Details'!Q570 -> Lyft | H101: ='Expense Details'!V570 -> 44.22744 | I101: ='Expense Details'!Z570 -> 60 | J101: =H101-I101 -> -15.77256 | K101: =IFERROR(MAX(0,H101/I101-1),0) -> 0 | L101: ='Expense Details'!AC570 -> No | M101: No receipt attached | N101: ='Expense Details'!AG570 -> Pending Approval | O101: ='Expense Details'!F570 -> David Chen
...
